Workbook

Sheet Yr-2Approved Budget
A1: Partner: DAPTA (Development Agency for Poor and Tribal Awakening)
A2: Project Title: Ensuring food and livelihood security of indigenous and other marginalized communities(MCC) in Thakurmunda Block, Mayurbhanj, Odisha
A3: Project Location (District/State: Thakurmunda Block, Odisha
A4: Proposed project period: 1 June 2023 to 31 March 2026 | D4: PROJECT START DATE 1 JUNE -2023 END DATE 31 MARCH -2026
A5: ID | B5: Proposed Budget | C5: Unit description | D5: Year-1-2023-24 | I5: Revised Year-1 Budget (2023-24) (for 10 months) | O5: Year-1 budget Break-up | U5: Year-2-2024-25 (Initial Budget) | AA5: Approved Revised Year-2 Budget (2024-25) | AF5: Year-3 2025-26 | AK5: Total of 3 years: 2023-2026 | AO5: MCC comments (4 Jan 2023) | AP5: Remarks | AR5: Quarter-wise bifurcation of Year-2 MCC Budget
D6: Price per unit | E6: Year- 1 unit quantity | F6: Year-1 MCC Contribution | G6: Year-1 Partner or others' contribution | H6: Year- 1 Total Budgeted Amount | I6: Revised Unit Quantity | J6: Revised Unit Price | K6: MCC Revised Contribution Yr-1 | L6: Participants' contribution | M6: Total Revised Budget Yr-1 | O6: 1st Qtr. (June 23) | P6: 2nd Qtr. | Q6: 3rd Qtr. | R6: 4th Qtr. | S6: Total | U6: Price per unit | V6: Year 2 unit quantity | W6: Year-2 MCC Contribution | X6: Year-2 Partner or others' contribution | Y6: Year- 2 Total Budgeted Amount | AA6: Revised Unit price | AB6: Revised Unit quantity | AC6: MCC Revised Contribution Yr-2 | AD6: Participants'/ others contribution | AE6: Total Revised Budget Yr-2 | AF6: Price per unit | AG6: Year 3 unit quantity | AH6: Year-3 MCC Contribution | AI6: Year-3 Partner or others' contribution | AJ6: Year 3 Total Budgeted Amount | AK6: Total Proposed Quantity of 3 years | AL6: Total MCC Contribution | AM6: Total Partner or others' contribution | AN6: Total Budget of Project Period | AR6: Qtr-1 (Apr-Jun 2024) | AS6: Qtr-2 (Jul-Sept 2024) | AT6: Qtr-3 (Oct-Dec 2024) | AU6: Qtr-4 (Jan-Mar 2025) | AV6: Total MCC Budget 2024-25
A7: 1 | B7: Outcome :1 Activities | AO7: For Amy Martens: Changes made are in blue font. Justification in change in uniti price in Year 1,2 & 3 can be seen as per the calculation shown under Column B.
A8: 1.1 | B8: Baseline | C8: 0 | D8: 0 | E8: 0 | F8: 0 | G8: 0 | H8: 0 | I8: 1 | J8: 30000 | K8: =I8*J8 -> 30000 | M8: =K8+L8 -> 30000 | O8: =M8 -> 30000 | S8: =O8+P8+Q8+R8 -> 30000
A9: 1.2 | B9: Monthly PRA/ Data collection/ Village Community Meeting | S9: =O9+P9+Q9+R9 -> 0
A10: 1.2.1 | B10: Monthly Village Community Meeting (Biscuits / Snacks /per time /12 Months) @Rs.15 x 437 + 6 staff =Rs.6660/- | C10: Resource person | D10: 6660 | E10: 12 | F10: =D10*E10 -> 79920 | H10: =F10+G10 -> 79920 | I10: =443*10 -> 4430 | J10: 15 | K10: =I10*J10 -> 66450 | M10: =K10+L10 -> 66450 | O10: =443*15 -> 6645 | P10: =443*15*3 -> 19935 | Q10: =443*15*3 -> 19935 | R10: =443*15*3 -> 19935 | S10: =O10+P10+Q10+R10 -> 66450 | U10: 6660 | V10: 12 | W10: =U10*V10 -> 79920 | Y10: =W10+X10 -> 79920 | AA10: 6660 | AB10: 12 | AC10: =AA10*AB10 -> 79920 | AE10: =AC10+AD10 -> 79920 | AF10: 6660 | AG10: 12 | AH10: =AF10*AG10 -> 79920 | AJ10: =AH10+AI10 -> 79920 | AK10: =E10+V10+AG10 -> 36 | AL10: =F10+W10+AH10 -> 239760 | AM10: =G10+X10+AI10 -> 0 | AN10: =AL10+AM10 -> 239760 | AR10: 19980 | AS10: 19980 | AT10: 19980 | AU10: 19980 | AV10: =AR10+AS10+AT10+AU10 -> 79920
B11: Activities Sub Total 1.2 | D11: =SUM(D10:D10) -> 6660 | E11: =SUM(E10:E10) -> 12 | F11: =SUM(F10:F10) -> 79920 | G11: =SUM(G10:G10) -> 0 | H11: =SUM(H8:H10) -> 79920 | I11: 12 | K11: =SUM(K8:K10) -> 96450 | L11: =SUM(L10:L10) -> 0 | M11: =SUM(M8:M10) -> 96450 | O11: =SUM(O8:O10) -> 36645 | P11: =SUM(P8:P10) -> 19935 | Q11: =SUM(Q8:Q10) -> 19935 | R11: =SUM(R8:R10) -> 19935 | S11: =O11+P11+Q11+R11 -> 96450 | U11: =SUM(U10:U10) -> 6660 | V11: =SUM(V10:V10) -> 12 | W11: =SUM(W10:W10) -> 79920 | X11: =SUM(X10:X10) -> 0 | Y11: =SUM(Y10:Y10) -> 79920 | AB11: =AB10 -> 12 | AC11: =AC10 -> 79920 | AD11: =AD10 -> 0 | AE11: =AE10 -> 79920 | AF11: =AF10 -> 6660 | AG11: =AG10 -> 12 | AH11: =AH10 -> 79920 | AI11: =AI10 -> 0 | ... AO11: =AO10 -> 0 | AR11: =AR10 -> 19980 | AS11: =AS10 -> 19980 | AT11: =AT10 -> 19980 | AU11: =AU10 -> 19980 | AV11: =AR11+AS11+AT11+AU11 -> 79920
A12: 1.3 | B12: Training on Improved agriculture methods and Technology :- a) SRI (Paddy farming in row) b) Multi cropping c) Crop diversification d) Crop rotation e) Azola growing f) Seed preservation g) Seed treatment
A13: 1.3.1 | B13: Honorarium , travelling & food for resource person @Rs.2000 (above mentioned some subject will be conducted by the Project staff) | C13: Resource person | D13: 2000 | E13: 1 | F13: =D13*E13 -> 2000 | H13: =F13+G13 -> 2000 | I13: 1 | J13: 2000 | K13: =I13*J13 -> 2000 | M13: =K13+L13 -> 2000 | O13: =+M13 -> 2000 | U13: 2000 | V13: 1 | W13: =U13*V13 -> 2000 | Y13: =W13+X13 -> 2000 | AA13: 2000 | AB13: 1 | AC13: =AA13*AB13 -> 2000 | AE13: =AC13+AD13 -> 2000 | AF13: 2000 | AG13: 1 | AH13: =AF13*AG13 -> 2000 | AJ13: =AH13+AI13 -> 2000 | AK13: =E13+V13+AG13 -> 3 | AL13: =F13+W13+AH13 -> 6000 | AM13: =G13+X13+AI13 -> 0 | AN13: =AL13+AM13 -> 6000 | AP13: Mukul: Will the RP be called only once out of 4 Trainings and other trainings will be taken over by project staff? RAJU : Yes | AQ13: =2000*4 -> 8000 | AR13: 2000 | AS13: 0 | AT13: 0 | AU13: 0 | AV13: =AR13+AS13+AT13+AU13 -> 2000
A14: 1.3.2 | B14: Food for 20 participants & 6 staff @ Rs.120 x 26 Person | C14: Fooding | D14: 3360 | E14: 3 | F14: =D14*E14 -> 10080 | H14: =F14+G14 -> 10080 | I14: 26 | J14: 120 | K14: =I14*J14 -> 3120 | M14: =K14+L14 -> 3120 | O14: =+M14 -> 3120 | U14: 3360 | V14: 4 | W14: =U14*V14 -> 13440 | Y14: =W14+X14 -> 13440 | AA14: 3120 | AB14: 4 | AC14: =AA14*AB14 -> 12480 | AE14: =AC14+AD14 -> 12480 | AF14: 3360 | AG14: 3 | AH14: =AF14*AG14 -> 10080 | AJ14: =AH14+AI14 -> 10080 | AK14: =E14+V14+AG14 -> 10 | AL14: =F14+W14+AH14 -> 33600 | AM14: =G14+X14+AI14 -> 0 | AN14: =AL14+AM14 -> 33600 | AP14: Rectified the calculation | AR14: 3120 | AS14: 3120 | AT14: 3120 | AU14: 3120 | AV14: =AR14+AS14+AT14+AU14 -> 12480
A15: 1.3.3 | B15: Project village to training venue Transportation charges 20 participants x 1 Project villages @ Rs.2500/-; 2 vehicles | C15: Travelling | D15: 3500 | E15: 3 | F15: =D15*E15 -> 10500 | H15: =F15+G15 -> 10500 | I15: 2 | J15: 2500 | K15: =I15*J15 -> 5000 | M15: =K15+L15 -> 5000 | O15: =+M15 -> 5000 | U15: 3500 | V15: 4 | W15: =U15*V15 -> 14000 | Y15: =W15+X15 -> 14000 | AA15: 2500 | AB15: 8 | AC15: =AA15*AB15 -> 20000 | AE15: =AC15+AD15 -> 20000 | AF15: 3500 | AG15: 3 | AH15: =AF15*AG15 -> 10500 | AJ15: =AH15+AI15 -> 10500 | AK15: =E15+V15+AG15 -> 10 | AL15: =F15+W15+AH15 -> 35000 | AM15: =G15+X15+AI15 -> 0 | AN15: =AL15+AM15 -> 35000 | AP15: We have calculated @Rs2500 as per budget description, 2 vehicles per training. | AQ15: =2500*4*4 -> 40000 | AR15: 5000 | AS15: 5000 | AT15: 5000 | AU15: 5000 | AV15: =AR15+AS15+AT15+AU15 -> 20000
A16: 1.3.4 | B16: Arrangements & training matterials @ Rs.500/- | C16: matterials | D16: 500 | E16: 3 | F16: =D16*E16 -> 1500 | H16: =F16+G16 -> 1500 | I16: 20 | J16: 50 | K16: =I16*J16 -> 1000 | M16: =K16+L16 -> 1000 | O16: =+M16 -> 1000 | U16: 500 | V16: 4 | W16: =U16*V16 -> 2000 | Y16: =W16+X16 -> 2000 | AA16: 500 | AB16: 4 | AC16: =AA16*AB16 -> 2000 | AE16: =AC16+AD16 -> 2000 | AF16: 500 | AG16: 3 | AH16: =AF16*AG16 -> 1500 | AJ16: =AH16+AI16 -> 1500 | AK16: =E16+V16+AG16 -> 10 | AL16: =F16+W16+AH16 -> 5000 | AM16: =G16+X16+AI16 -> 0 | AN16: =AL16+AM16 -> 5000 | AR16: 500 | AS16: 500 | AT16: 500 | AU16: 500 | AV16: =AR16+AS16+AT16+AU16 -> 2000
B17: Activities Sub Total 1.3 | D17: =SUM(D13:D16) -> 9360 | E17: 3 | F17: =SUM(F13:F16) -> 24080 | G17: =SUM(G13:G16) -> 0 | H17: =SUM(H13:H16) -> 24080 | I17: 1 | K17: =SUM(K13:K16) -> 11120 | L17: =SUM(L13:L16) -> 0 | M17: =SUM(M13:M16) -> 11120 | O17: =SUM(O13:O16) -> 11120 | Q17: =SUM(Q13:Q16) -> 0 | R17: =SUM(R13:R16) -> 0 | S17: =O17+P17+Q17+R17 -> 11120 | U17: =SUM(U13:U16) -> 9360 | V17: 4 | W17: =SUM(W13:W16) -> 31440 | X17: =SUM(X13:X16) -> 0 | Y17: =SUM(Y13:Y16) -> 31440 | AB17: 4 | AC17: =SUM(AC13:AC16) -> 36480 | AD17: =SUM(AD13:AD16) -> 0 | AE17: =SUM(AE13:AE16) -> 36480 | AF17: =SUM(AF13:AF16) -> 9360 | AG17: 3 | AH17: =SUM(AH13:AH16) -> 24080 | AI17: =SUM(AI13:AI16) -> 0 | AJ17: =SUM(AJ13:AJ16) -> 24080 | AK17: =AG17+V17+E17 -> 10 | AL17: =SUM(AL13:AL16) -> 79600 | AM17: =SUM(AM13:AM16) -> 0 | AN17: =SUM(AN13:AN16) -> 79600 | AR17: =SUM(AR13:AR16) -> 10620 | AS17: =SUM(AS13:AS16) -> 8620 | AT17: =SUM(AT13:AT16) -> 8620 | AU17: =SUM(AU13:AU16) -> 8620 | AV17: =AR17+AS17+AT17+AU17 -> 36480
A18: 1.4 | B18: Training on Natural Resource Management a) Soil health ( Testing, treatment and preservation) b) Organic farming (Chemical free) c) Compost pit & its preparation d) Vermin compost making e) Bio- Pesticide f) Bio- fertilizer
A19: 1.4.1 | B19: Honorarium, travelling & food for resource person @Rs.2000 | C19: Resource person | D19: 2000 | E19: 2 | F19: =D19*E19 -> 4000 | H19: =F19+G19 -> 4000 | I19: 2 | J19: 2000 | K19: =I19*J19 -> 4000 | M19: =K19+L19 -> 4000 | O19: =J19 -> 2000 | R19: 2000 | S19: =O19+P19+Q19+R19 -> 4000 | U19: 2000 | V19: 4 | W19: =U19*V19 -> 8000 | Y19: =W19+X19 -> 8000 | AA19: 2000 | AB19: 4 | AC19: =AA19*AB19 -> 8000 | AE19: =AC19+AD19 -> 8000 | AF19: 2000 | AG19: 3 | AH19: =AF19*AG19 -> 6000 | AJ19: =AH19+AI19 -> 6000 | AK19: =E19+V19+AG19 -> 9 | AL19: =F19+W19+AH19 -> 18000 | AM19: =G19+X19+AI19 -> 0 | AN19: =AL19+AM19 -> 18000 | AR19: 2000 | AS19: 2000 | AT19: 2000 | AU19: 2000 | AV19: =AR19+AS19+AT19+AU19 -> 8000
A20: 1.4.2 | B20: Food for 35 participants form 7 project located villages each village 5 participants & 6 staff @ Rs.120 x 41 Person =Rs.3360 | C20: Fooding | D20: 3360 | E20: 2 | F20: =D20*E20 -> 6720 | H20: =F20+G20 -> 6720 | I20: 82 | J20: 120 | K20: =I20*J20 -> 9840 | M20: =K20+L20 -> 9840 | O20: =M20/2 -> 4920 | R20: =M20/2 -> 4920 | S20: =O20+P20+Q20+R20 -> 9840 | U20: 3360 | V20: 4 | W20: =U20*V20 -> 13440 | Y20: =W20+X20 -> 13440 | AA20: 4920 | AB20: 4 | AC20: =AA20*AB20 -> 19680 | AE20: =AC20+AD20 -> 19680 | AF20: 3360 | AG20: 3 | AH20: =AF20*AG20 -> 10080 | AJ20: =AH20+AI20 -> 10080 | AK20: =E20+V20+AG20 -> 9 | AL20: =F20+W20+AH20 -> 30240 | AM20: =G20+X20+AI20 -> 0 | AN20: =AL20+AM20 -> 30240 | AP20: Rectified the calculation | AR20: 4920 | AS20: 4920 | AT20: 4920 | AU20: 4920 | AV20: =AR20+AS20+AT20+AU20 -> 19680
A21: 1.4.3 | B21: Project village to training venue transportation charges Rs.7500/- each village 5 participants x 7 Project villges 3 vehicles for 2 trainings | C21: Travelling | D21: 3500 | E21: 2 | F21: =D21*E21 -> 7000 | H21: =F21+G21 -> 7000 | I21: =3*2 -> 6 | J21: 2500 | K21: =I21*J21 -> 15000 | M21: =K21+L21 -> 15000 | O21: =M21/2 -> 7500 | R21: =M21/2 -> 7500 | S21: =O21+P21+Q21+R21 -> 15000 | U21: 3500 | V21: 4 | W21: =U21*V21 -> 14000 | Y21: =W21+X21 -> 14000 | AA21: 2500 | AB21: 12 | AC21: =AA21*AB21 -> 30000 | AE21: =AC21+AD21 -> 30000 | AF21: 3500 | AG21: 3 | AH21: =AF21*AG21 -> 10500 | AJ21: =AH21+AI21 -> 10500 | AK21: =E21+V21+AG21 -> 9 | AL21: =F21+W21+AH21 -> 31500 | AM21: =G21+X21+AI21 -> 0 | AN21: =AL21+AM21 -> 31500 | AP21: We have calculated @Rs2500 as per budget description, 3 vehicles per training | AR21: 7500 | AS21: 7500 | AT21: 7500 | AU21: 7500 | AV21: =AR21+AS21+AT21+AU21 -> 30000
A22: 1.4.4 | B22: Arrangements & training matterials @ Rs.500/- | C22: matterials | D22: 500 | E22: 2 | F22: =D22*E22 -> 1000 | H22: =F22+G22 -> 1000 | I22: =2*35 -> 70 | J22: 50 | K22: =I22*J22 -> 3500 | M22: =K22+L22 -> 3500 | O22: =M22/2 -> 1750 | R22: =M22/2 -> 1750 | S22: =O22+P22+Q22+R22 -> 3500 | U22: 500 | V22: 4 | W22: =U22*V22 -> 2000 | Y22: =W22+X22 -> 2000 | AA22: 500 | AB22: 4 | AC22: =AA22*AB22 -> 2000 | AE22: =AC22+AD22 -> 2000 | AF22: 500 | AG22: 3 | AH22: =AF22*AG22 -> 1500 | AJ22: =AH22+AI22 -> 1500 | AK22: =E22+V22+AG22 -> 9 | AL22: =F22+W22+AH22 -> 4500 | AM22: =G22+X22+AI22 -> 0 | AN22: =AL22+AM22 -> 4500 | AR22: 500 | AS22: 500 | AT22: 500 | AU22: 500 | AV22: =AR22+AS22+AT22+AU22 -> 2000
B23: Activities Sub Total 1.4 | E23: 2 | F23: =SUM(F19:F22) -> 18720 | G23: =SUM(G19:G22) -> 0 | H23: =SUM(H19:H22) -> 18720 | I23: 2 | K23: =SUM(K19:K22) -> 32340 | L23: =SUM(L19:L22) -> 0 | M23: =SUM(M19:M22) -> 32340 | O23: =SUM(O19:O22) -> 16170 | P23: =SUM(P19:P22) -> 0 | Q23: =SUM(Q19:Q22) -> 0 | R23: =SUM(R19:R22) -> 16170 | S23: =O23+P23+Q23+R23 -> 32340 | V23: 4 | W23: =SUM(W19:W22) -> 37440 | X23: =SUM(X19:X22) -> 0 | Y23: =SUM(Y19:Y22) -> 37440 | AB23: 4 | AC23: =SUM(AC19:AC22) -> 59680 | AD23: =SUM(AD19:AD22) -> 0 | AE23: =SUM(AE19:AE22) -> 59680 | AG23: 3 | AH23: =SUM(AH19:AH22) -> 28080 | AI23: =SUM(AI19:AI22) -> 0 | AJ23: =SUM(AJ19:AJ22) -> 28080 | AK23: =AG23+V23+E23 -> 9 | AL23: =SUM(AL19:AL22) -> 84240 | AM23: =SUM(AM19:AM22) -> 0 | AN23: =SUM(AN19:AN22) -> 84240 | AO23: =SUM(AO19:AO22) -> 0 | AR23: =SUM(AR19:AR22) -> 14920 | AS23: =SUM(AS19:AS22) -> 14920 | AT23: =SUM(AT19:AT22) -> 14920 | AU23: =SUM(AU19:AU22) -> 14920 | AV23: =AR23+AS23+AT23+AU23 -> 59680
A24: 1.5 | B24: Pulses Seeds (Horse gram & Black gram) distribution
A25: 1.5.1 | B25: Pulses Seeds Distribution for 437 families Black Gram 2kg, Kulthi 2kg @Rs.360/- for 4 Kg x 437 families (Contribution Local labor charges@500 x 437 families) | C25: matterials | D25: 157320 | E25: 0 | F25: =D25*E25 -> 0 | G25: 0 | H25: =F25+G25 -> 0 | I25: 437 | J25: 212.86 | K25: =I25*J25 -> 93019.82 | M25: =K25+L25 -> 93019.82 | P25: =M25 -> 93019.82 | S25: =O25+P25+Q25+R25 -> 93019.82 | U25: 157320 | V25: 1 | W25: =U25*V25 -> 157320 | X25: 218500 | Y25: =W25+X25 -> 375820 | AA25: 157320 | AB25: 1 | AC25: =AA25*AB25 -> 157320 | AD25: 218500 | AE25: =AC25+AD25 -> 375820 | AF25: 157320 | AG25: 0 | AH25: =AF25*AG25 -> 0 | AJ25: =AH25+AI25 -> 0 | AK25: =E25+V25+AG25 -> 1 | AL25: =F25+W25+AH25 -> 157320 | AM25: =G25+X25+AI25 -> 218500 | AN25: =AL25+AM25 -> 375820 | AR25: 0 | AS25: 157320 | AT25: 0 | AU25: 0 | AV25: =AR25+AS25+AT25+AU25 -> 157320
B26: Activities Sub Total 1.5 | D26: =SUM(D25) -> 157320 | E26: =SUM(E25) -> 0 | F26: =SUM(F25) -> 0 | G26: =SUM(G25) -> 0 | H26: =SUM(H25) -> 0 | I26: 1 | K26: =SUM(K25) -> 93019.82 | L26: =SUM(L25) -> 0 | M26: =SUM(M25) -> 93019.82 | O26: =SUM(O25) -> 0 | P26: =SUM(P25) -> 93019.82 | Q26: =SUM(Q25) -> 0 | R26: =SUM(R25) -> 0 | S26: =O26+P26+Q26+R26 -> 93019.82 | U26: =SUM(U25) -> 157320 | V26: =SUM(V25) -> 1 | W26: =SUM(W25) -> 157320 | X26: =SUM(X25) -> 218500 | Y26: =SUM(Y25) -> 375820 | AB26: =SUM(AB25) -> 1 | AC26: =SUM(AC25) -> 157320 | AD26: =SUM(AD25) -> 218500 | AE26: =SUM(AE25) -> 375820 | AF26: =SUM(AF25) -> 157320 | AG26: =SUM(AG25) -> 0 | AH26: =SUM(AH25) -> 0 | AI26: =SUM(AI25) -> 0 | AJ26: =SUM(AJ25) -> 0 | AK26: =AG26+V26+E26 -> 1 | AL26: =SUM(AL25) -> 157320 | AM26: =SUM(AM25) -> 218500 | AN26: =SUM(AN25) -> 375820 | AO26: =SUM(AO25) -> 0 | AR26: =SUM(AR25) -> 0 | AS26: =SUM(AS25) -> 157320 | AT26: =SUM(AT25) -> 0 | AU26: =SUM(AU25) -> 0 | AV26: =AR26+AS26+AT26+AU26 -> 157320
A27: 1.6 | B27: Exposure visit on adaption of improved new technology
A28: 1.6.1 | B28: Honorarium for resource person @Rs.2000 | C28: Fooding | D28: 2000 | E28: 1 | F28: =D28*E28 -> 2000 | H28: =F28+G28 -> 2000 | K28: =I28*J28 -> 0 | M28: =K28+L28 -> 0 | S28: =O28+P28+Q28+R28 -> 0 | U28: 2000 | V28: 1 | W28: =U28*V28 -> 2000 | Y28: =W28+X28 -> 2000 | AF28: 2000 | AG28: 1 | AH28: =AF28*AG28 -> 2000 | AJ28: =AH28+AI28 -> 2000 | AK28: =E28+V28+AG28 -> 3 | AL28: =F28+W28+AH28 -> 6000 | AM28: =G28+X28+AI28 -> 0 | AN28: =AL28+AM28 -> 6000 | AO28: Why Honorarium is required for Exposure visit? | AP28: Exposure visit excluded due to shortage of fund. MUKUL: It has been included in additional budget in Year-1 | AV28: =AR28+AS28+AT28+AU28 -> 0
A29: 1.6.2 | B29: Food for 35 participants & 6 staff @ Rs.200 x 41 Person x 1 day = 8400/- | C29: Fooding | D29: 8400 | E29: 1 | F29: =D29*E29 -> 8400 | H29: =F29+G29 -> 8400 | K29: =I29*J29 -> 0 | M29: =K29+L29 -> 0 | S29: =O29+P29+Q29+R29 -> 0 | U29: 15400 | V29: 1 | W29: =U29*V29 -> 15400 | Y29: =W29+X29 -> 15400 | AF29: 16800 | AG29: 1 | AH29: =AF29*AG29 -> 16800 | AJ29: =AH29+AI29 -> 16800 | AK29: =E29+V29+AG29 -> 3 | AL29: =F29+W29+AH29 -> 40600 | AM29: =G29+X29+AI29 -> 0 | AN29: =AL29+AM29 -> 40600 | AV29: =AR29+AS29+AT29+AU29 -> 0
A30: 1.6.3 | B30: Bus charges @ Rs.25000/- in Year -1 @ Rs. 26000/- x 2 bus in Year-2 and for Long distance place Exposure Visit in Yr-3 Bus Charges @Rs.35000/- | C30: Travelling | D30: 25000 | E30: 1 | F30: =D30*E30 -> 25000 | H30: =F30+G30 -> 25000 | K30: =I30*J30 -> 0 | M30: =K30+L30 -> 0 | S30: =O30+P30+Q30+R30 -> 0 | U30: 52000 | V30: 1 | W30: =U30*V30 -> 52000 | Y30: =W30+X30 -> 52000 | AF30: 35000 | AG30: 1 | AH30: =AF30*AG30 -> 35000 | AJ30: =AH30+AI30 -> 35000 | AK30: =E30+V30+AG30 -> 3 | AL30: =F30+W30+AH30 -> 112000 | AM30: =G30+X30+AI30 -> 0 | AN30: =AL30+AM30 -> 112000 | AV30: =AR30+AS30+AT30+AU30 -> 0
A31: 1.6.4 | B31: First Aid medicine & other expenses @ Rs.500/- and Rs.1000/- | C31: matterials | D31: 500 | E31: 1 | F31: =D31*E31 -> 500 | H31: =F31+G31 -> 500 | K31: =I31*J31 -> 0 | M31: =K31+L31 -> 0 | S31: =O31+P31+Q31+R31 -> 0 | U31: 1000 | V31: 1 | W31: =U31*V31 -> 1000 | Y31: =W31+X31 -> 1000 | AF31: 1000 | AG31: 1 | AH31: =AF31*AG31 -> 1000 | AJ31: =AH31+AI31 -> 1000 | AK31: =E31+V31+AG31 -> 3 | AL31: =F31+W31+AH31 -> 2500 | AM31: =G31+X31+AI31 -> 0 | AN31: =AL31+AM31 -> 2500 | AV31: =AR31+AS31+AT31+AU31 -> 0
B32: Activities Sub Total 1.6 | D32: =SUM(D28:D31) -> 35900 | E32: 1 | F32: =SUM(F28:F31) -> 35900 | G32: =SUM(G28:G31) -> 0 | H32: =SUM(H28:H31) -> 35900 | I32: 0 | K32: =SUM(K28:K31) -> 0 | L32: =SUM(L28:L31) -> 0 | M32: =SUM(M28:M31) -> 0 | O32: =SUM(O28:O31) -> 0 | P32: =SUM(P28:P31) -> 0 | Q32: =SUM(Q28:Q31) -> 0 | R32: =SUM(R28:R31) -> 0 | S32: =O32+P32+Q32+R32 -> 0 | U32: =SUM(U28:U31) -> 70400 | V32: 1 | W32: =SUM(W28:W31) -> 70400 | X32: =SUM(X28:X31) -> 0 | Y32: =SUM(Y28:Y31) -> 70400 | AA32: =SUM(AA28:AA31) -> 0 | AB32: =SUM(AB28:AB31) -> 0 | AC32: =SUM(AC28:AC31) -> 0 | AD32: =SUM(AD28:AD31) -> 0 | AE32: =SUM(AE28:AE31) -> 0 | AF32: =SUM(AF28:AF31) -> 54800 | AG32: 1 | AH32: =SUM(AH28:AH31) -> 54800 | AI32: =SUM(AI28:AI31) -> 0 | AJ32: =SUM(AJ28:AJ31) -> 54800 | AK32: =AG32+V32+E32 -> 3 | AL32: =SUM(AL28:AL31) -> 161100 | AM32: =SUM(AM28:AM31) -> 0 | AN32: =SUM(AN28:AN31) -> 161100 | AO32: =SUM(AO28:AO31) -> 0 | AR32: =SUM(AR28:AR31) -> 0 | AS32: =SUM(AS28:AS31) -> 0 | AT32: =SUM(AT28:AT31) -> 0 | AU32: =SUM(AU28:AU31) -> 0 | AV32: =AR32+AS32+AT32+AU32 -> 0
B33: Activities Sub Total for Outcomes :1 | D33: =SUM(D11+D17+D23+D26+D32) -> 209240 | E33: =SUM(E11+E17+E23+E26+E32) -> 18 | F33: =SUM(F11+F17+F23+F26+F32) -> 158620 | G33: =SUM(G11+G17+G23+G26+G32) -> 0 | H33: =SUM(H11+H17+H23+H26+H32) -> 158620 | K33: =SUM(K11+K17+K23+K26+K32) -> 232929.82 | L33: =SUM(L11+L17+L23+L26+L32) -> 0 | M33: =SUM(M11+M17+M23+M26+M32) -> 232929.82 | O33: =SUM(O11+O17+O23+O26+O32) -> 63935 | P33: =SUM(P11+P17+P23+P26+P32) -> 112954.82 | Q33: =SUM(Q11+Q17+Q23+Q26+Q32) -> 19935 | R33: =SUM(R11+R17+R23+R26+R32) -> 36105 | S33: =SUM(S11+S17+S23+S26+S32) -> 232929.82 | U33: =SUM(U11+U17+U23+U26+U32) -> 243740 | V33: =SUM(V11+V17+V23+V26+V32) -> 22 | W33: =SUM(W11+W17+W23+W26+W32) -> 376520 | X33: =SUM(X11+X17+X23+X26+X32) -> 218500 | Y33: =SUM(Y11+Y17+Y23+Y26+Y32) -> 595020 | AC33: =SUM(AC11+AC17+AC23+AC26+AC32) -> 333400 | AD33: =SUM(AD11+AD17+AD23+AD26+AD32) -> 218500 | AE33: =SUM(AE11+AE17+AE23+AE26+AE32) -> 551900 | AF33: =SUM(AF11+AF17+AF23+AF26+AF32) -> 228140 | AG33: =SUM(AG11+AG17+AG23+AG26+AG32) -> 19 | AH33: =SUM(AH11+AH17+AH23+AH26+AH32) -> 186880 | AI33: =SUM(AI11+AI17+AI23+AI26+AI32) -> 0 | AJ33: =SUM(AJ11+AJ17+AJ23+AJ26+AJ32) -> 186880 | AL33: =SUM(AL11+AL17+AL23+AL26+AL32) -> 722020 | AM33: =SUM(AM11+AM17+AM23+AM26+AM32) -> 218500 | AN33: =SUM(AN11+AN17+AN23+AN26+AN32) -> 940520 | AO33: =SUM(AO11+AQ17+AO23+AO26+AO32) -> 0 | AP33: =AC33+AD33 -> 551900 | AQ33: =SUM(AQ11+AQ17+AQ23+AQ26+AQ32) -> 0 | AR33: =SUM(AR11+AR17+AR23+AR26+AR32) -> 45520 | AS33: =SUM(AS11+AS17+AS23+AS26+AS32) -> 200840 | AT33: =SUM(AT11+AT17+AT23+AT26+AT32) -> 43520 | AU33: =SUM(AU11+AU17+AU23+AU26+AU32) -> 43520 | AV33: =AR33+AS33+AT33+AU33 -> 333400
B34: Activities for Outcome :2
A35: 2.1 | B35: Training to the CBO’s (SHG) on topics a) Account book keeping, b) Record maintaining, c) Rules and Regulations, d) Responsibilities of the group leaders and members. e) Training on loan taking and refunding. f) Sack bag potatoes farming g) tuber crop farming i) Encourage to farming of Millet ( Mandia)
A36: 2.1.1 | B36: Honorarium , Travelling & food for Resource person @Rs.2000 | C36: Resource person | D36: 2000 | E36: 2 | F36: =D36*E36 -> 4000 | H36: =F36+G36 -> 4000 | I36: 2 | J36: 2000 | K36: =I36*J36 -> 4000 | M36: =K36+L36 -> 4000 | Q36: =M36/2 -> 2000 | R36: 2000 | S36: =O36+P36+Q36+R36 -> 4000 | U36: 2000 | V36: 4 | W36: =U36*V36 -> 8000 | Y36: =W36+X36 -> 8000 | AA36: 2000 | AB36: 4 | AC36: =AA36*AB36 -> 8000 | AE36: =AC36+AD36 -> 8000 | AF36: 2000 | AG36: 3 | AH36: =AF36*AG36 -> 6000 | AJ36: =AH36+AI36 -> 6000 | AK36: =E36+V36+AG36 -> 9 | AL36: =F36+W36+AH36 -> 18000 | AM36: =G36+X36+AI36 -> 0 | AN36: =AL36+AM36 -> 18000 | AR36: 2000 | AS36: 2000 | AT36: 2000 | AU36: 2000 | AV36: =AR36+AS36+AT36+AU36 -> 8000
A37: 2.1.2 | B37: Food for 35 participants form 7 project located villages each village 5 participants & 6 staff @ Rs.120 x 42 Person =Rs.3360 | C37: Fooding | D37: 3360 | E37: 2 | F37: =D37*E37 -> 6720 | H37: =F37+G37 -> 6720 | I37: =2*41 -> 82 | J37: 120 | K37: =I37*J37 -> 9840 | M37: =K37+L37 -> 9840 | Q37: =M37/2 -> 4920 | R37: 4920 | S37: =O37+P37+Q37+R37 -> 9840 | U37: 3360 | V37: 4 | W37: =U37*V37 -> 13440 | Y37: =W37+X37 -> 13440 | AA37: 4920 | AB37: 4 | AC37: =AA37*AB37 -> 19680 | AE37: =AC37+AD37 -> 19680 | AF37: 3360 | AG37: 3 | AH37: =AF37*AG37 -> 10080 | AJ37: =AH37+AI37 -> 10080 | AK37: =E37+V37+AG37 -> 9 | AL37: =F37+W37+AH37 -> 30240 | AM37: =G37+X37+AI37 -> 0 | AN37: =AL37+AM37 -> 30240 | AP37: Rectified the calculation | AR37: 4920 | AS37: 4920 | AT37: 4920 | AU37: 4920 | AV37: =AR37+AS37+AT37+AU37 -> 19680
A38: 2.1.3 | B38: Project village to training venue transportation charges Rs.2500/- each village 5 participants x 7 Project villages, 2 vehicles | C38: Travelling | D38: 3500 | E38: 2 | F38: =D38*E38 -> 7000 | H38: =F38+G38 -> 7000 | I38: 2 | J38: =2*2500 -> 5000 | K38: =I38*J38 -> 10000 | M38: =K38+L38 -> 10000 | Q38: =M38/2 -> 5000 | R38: 5000 | S38: =O38+P38+Q38+R38 -> 10000 | U38: 3500 | V38: 4 | W38: =U38*V38 -> 14000 | Y38: =W38+X38 -> 14000 | AA38: 2500 | AB38: 8 | AC38: =AA38*AB38 -> 20000 | AE38: =AC38+AD38 -> 20000 | AF38: 3500 | AG38: 3 | AH38: =AF38*AG38 -> 10500 | AJ38: =AH38+AI38 -> 10500 | AK38: =E38+V38+AG38 -> 9 | AL38: =F38+W38+AH38 -> 31500 | AM38: =G38+X38+AI38 -> 0 | AN38: =AL38+AM38 -> 31500 | AP38: We have calculated @Rs2500 as per budget description 2 vehicles per training. | AQ38: =2500*4*4 -> 40000 | AR38: 5000 | AS38: 5000 | AT38: 5000 | AU38: 5000 | AV38: =AR38+AS38+AT38+AU38 -> 20000
A39: 2.1.4 | B39: Arrangements & training materials @ Rs.500/- | C39: matterials | D39: 500 | E39: 2 | F39: =D39*E39 -> 1000 | H39: =F39+G39 -> 1000 | I39: 70 | J39: 50 | K39: =I39*J39 -> 3500 | M39: =K39+L39 -> 3500 | Q39: =M39/2 -> 1750 | R39: 1750 | S39: =O39+P39+Q39+R39 -> 3500 | U39: 500 | V39: 4 | W39: =U39*V39 -> 2000 | Y39: =W39+X39 -> 2000 | AA39: 500 | AB39: 4 | AC39: =AA39*AB39 -> 2000 | AE39: =AC39+AD39 -> 2000 | AF39: 500 | AG39: 3 | AH39: =AF39*AG39 -> 1500 | AJ39: =AH39+AI39 -> 1500 | AK39: =E39+V39+AG39 -> 9 | AL39: =F39+W39+AH39 -> 4500 | AM39: =G39+X39+AI39 -> 0 | AN39: =AL39+AM39 -> 4500 | AR39: 500 | AS39: 500 | AT39: 500 | AU39: 500 | AV39: =AR39+AS39+AT39+AU39 -> 2000
B40: Activities Sub Total 2.1 | D40: =SUM(D36:D39) -> 9360 | E40: 2 | F40: =SUM(F36:F39) -> 18720 | G40: =SUM(G36:G39) -> 0 | H40: =SUM(H36:H39) -> 18720 | I40: 2 | K40: =SUM(K36:K39) -> 27340 | L40: =SUM(L36:L39) -> 0 | M40: =SUM(M36:M39) -> 27340 | O40: =SUM(O36:O39) -> 0 | P40: =SUM(P36:P39) -> 0 | Q40: =SUM(Q36:Q39) -> 13670 | R40: =SUM(R36:R39) -> 13670 | S40: =O40+P40+Q40+R40 -> 27340 | U40: =SUM(U36:U39) -> 9360 | V40: 4 | W40: =SUM(W36:W39) -> 37440 | X40: =SUM(X36:X39) -> 0 | Y40: =SUM(Y36:Y39) -> 37440 | AB40: 4 | AC40: =SUM(AC36:AC39) -> 49680 | AD40: =SUM(AD36:AD39) -> 0 | AE40: =SUM(AE36:AE39) -> 49680 | AF40: =SUM(AF36:AF39) -> 9360 | AG40: 3 | AH40: =SUM(AH36:AH39) -> 28080 | AI40: =SUM(AI36:AI39) -> 0 | AJ40: =SUM(AJ36:AJ39) -> 28080 | AK40: =AG40+V40+E40 -> 9 | AL40: =SUM(AL36:AL39) -> 84240 | AM40: =SUM(AM36:AM39) -> 0 | AN40: =SUM(AN36:AN39) -> 84240 | AO40: =SUM(AO36:AO39) -> 0 | AR40: =SUM(AR36:AR39) -> 12420 | AS40: =SUM(AS36:AS39) -> 12420 | AT40: =SUM(AT36:AT39) -> 12420 | AU40: =SUM(AU36:AU39) -> 12420 | AV40: =AR40+AS40+AT40+AU40 -> 49680
A41: 2.2 | B41: Trainings on Alternate Livelihood Options: Poultry & Goat Rearing
A42: 2.2.1 | B42: Honorarium , travelling & food for resource person @Rs.2500 | C42: Resource person | D42: 2500 | E42: 1 | F42: =D42*E42 -> 2500 | H42: =F42+G42 -> 2500 | I42: 1 | J42: 2500 | K42: =I42*J42 -> 2500 | M42: =K42+L42 -> 2500 | Q42: =M42 -> 2500 | S42: =O42+P42+Q42+R42 -> 2500 | U42: 2500 | V42: 2 | W42: =U42*V42 -> 5000 | Y42: =W42+X42 -> 5000 | AA42: 2500 | AB42: 2 | AC42: =AA42*AB42 -> 5000 | AE42: =AC42+AD42 -> 5000 | AF42: 2500 | AG42: 1 | AH42: =AF42*AG42 -> 2500 | AJ42: =AH42+AI42 -> 2500 | AK42: =E42+V42+AG42 -> 4 | AL42: =F42+W42+AH42 -> 10000 | AM42: =G42+X42+AI42 -> 0 | AN42: =AL42+AM42 -> 10000 | AS42: 2500 | AU42: 2500 | AV42: =AR42+AS42+AT42+AU42 -> 5000
A43: 2.2.2 | B43: Food for 35 participants form 7 project located villages each village 5 participants &6 staff @ Rs.120 x 41 Person =Rs.3360 | C43: Fooding | D43: 3360 | E43: 1 | F43: =D43*E43 -> 3360 | H43: =F43+G43 -> 3360 | I43: 41 | J43: 120 | K43: =I43*J43 -> 4920 | M43: =K43+L43 -> 4920 | Q43: =M43 -> 4920 | S43: =O43+P43+Q43+R43 -> 4920 | U43: 3360 | V43: 2 | W43: =U43*V43 -> 6720 | Y43: =W43+X43 -> 6720 | AA43: 4920 | AB43: 2 | AC43: =AA43*AB43 -> 9840 | AE43: =AC43+AD43 -> 9840 | AF43: 3360 | AG43: 1 | AH43: =AF43*AG43 -> 3360 | AJ43: =AH43+AI43 -> 3360 | AK43: =E43+V43+AG43 -> 4 | AL43: =F43+W43+AH43 -> 13440 | AM43: =G43+X43+AI43 -> 0 | AN43: =AL43+AM43 -> 13440 | AP43: Rectified the calculation | AS43: 4920 | AU43: 4920 | AV43: =AR43+AS43+AT43+AU43 -> 9840
A44: 2.2.3 | B44: Project village to training venue transportation charges @Rs.2500/- 2 vehicles | C44: Travelling | D44: 3500 | E44: 1 | F44: =D44*E44 -> 3500 | H44: =F44+G44 -> 3500 | I44: 2 | J44: 2500 | K44: =I44*J44 -> 5000 | M44: =K44+L44 -> 5000 | Q44: =M44 -> 5000 | S44: =O44+P44+Q44+R44 -> 5000 | U44: 3500 | V44: 2 | W44: =U44*V44 -> 7000 | Y44: =W44+X44 -> 7000 | AA44: 2500 | AB44: 4 | AC44: =AA44*AB44 -> 10000 | AE44: =AC44+AD44 -> 10000 | AF44: 3500 | AG44: 1 | AH44: =AF44*AG44 -> 3500 | AJ44: =AH44+AI44 -> 3500 | AK44: =E44+V44+AG44 -> 4 | AL44: =F44+W44+AH44 -> 14000 | AM44: =G44+X44+AI44 -> 0 | AN44: =AL44+AM44 -> 14000 | AP44: We have calculated @Rs2500 as per budget description, 2 vehicles per training. | AQ44: =2500*2*2 -> 10000 | AS44: 5000 | AU44: 5000 | AV44: =AR44+AS44+AT44+AU44 -> 10000
A45: 2.2.4 | B45: Arrangements & training materials @ Rs.500/- | C45: matterials | D45: 500 | E45: 1 | F45: =D45*E45 -> 500 | H45: =F45+G45 -> 500 | I45: 35 | J45: 50 | K45: =I45*J45 -> 1750 | M45: =K45+L45 -> 1750 | Q45: =M45 -> 1750 | S45: =O45+P45+Q45+R45 -> 1750 | U45: 500 | V45: 2 | W45: =U45*V45 -> 1000 | Y45: =W45+X45 -> 1000 | AA45: 500 | AB45: 2 | AC45: =AA45*AB45 -> 1000 | AE45: =AC45+AD45 -> 1000 | AF45: 500 | AG45: 1 | AH45: =AF45*AG45 -> 500 | AJ45: =AH45+AI45 -> 500 | AK45: =E45+V45+AG45 -> 4 | AL45: =F45+W45+AH45 -> 2000 | AM45: =G45+X45+AI45 -> 0 | AN45: =AL45+AM45 -> 2000 | AS45: 500 | AU45: 500 | AV45: =AR45+AS45+AT45+AU45 -> 1000
B46: Activities Sub Total 2.2 | D46: =SUM(D42:D45) -> 9860 | E46: 2 | F46: =SUM(F42:F45) -> 9860 | G46: =SUM(G42:G45) -> 0 | H46: =SUM(H42:H45) -> 9860 | I46: 1 | K46: =SUM(K42:K45) -> 14170 | L46: =SUM(L42:L45) -> 0 | M46: =SUM(M42:M45) -> 14170 | O46: =SUM(O42:O45) -> 0 | P46: =SUM(P42:P45) -> 0 | Q46: =SUM(Q42:Q45) -> 14170 | R46: =SUM(R42:R45) -> 0 | S46: =O46+P46+Q46+R46 -> 14170 | U46: =SUM(U42:U45) -> 9860 | V46: 2 | W46: =SUM(W42:W45) -> 19720 | X46: =SUM(X42:X45) -> 0 | Y46: =SUM(Y42:Y45) -> 19720 | AB46: 2 | AC46: =SUM(AC42:AC45) -> 25840 | AD46: =SUM(AD42:AD45) -> 0 | AE46: =SUM(AE42:AE45) -> 25840 | AF46: =SUM(AF42:AF45) -> 9860 | AG46: =SUM(AG42:AG45) -> 4 | AH46: =SUM(AH42:AH45) -> 9860 | AI46: =SUM(AI42:AI45) -> 0 | AJ46: =SUM(AJ42:AJ45) -> 9860 | ... AO46: =SUM(AO42:AO45) -> 0 | AR46: =SUM(AR42:AR45) -> 0 | AS46: =SUM(AS42:AS45) -> 12920 | AT46: =SUM(AT42:AT45) -> 0 | AU46: =SUM(AU42:AU45) -> 12920 | AV46: =AR46+AS46+AT46+AU46 -> 25840
A47: 2.3 | B47: Training on primary treatments and Vaccination for the domestic animals
A48: 2.3.1 | B48: Honorarium , travelling & food for resource person @Rs.2500 | C48: fruits saplling | D48: 2500 | E48: 2 | F48: =D48*E48 -> 5000 | G48: 0 | H48: =F48+G48 -> 5000 | I48: 1 | J48: 2500 | K48: =I48*J48 -> 2500 | M48: =K48+L48 -> 2500 | P48: =M48 -> 2500 | S48: =O48+P48+Q48+R48 -> 2500 | U48: 2500 | V48: 2 | W48: =U48*V48 -> 5000 | Y48: =W48+X48 -> 5000 | AA48: 2500 | AB48: 2 | AC48: =AA48*AB48 -> 5000 | AE48: =AC48+AD48 -> 5000 | AF48: 2500 | AG48: 2 | AH48: =AF48*AG48 -> 5000 | AJ48: =AH48+AI48 -> 5000 | AK48: =E48+V48+AG48 -> 6 | AL48: =F48+W48+AH48 -> 15000 | AM48: =G48+X48+AI48 -> 0 | AN48: =AL48+AM48 -> 15000 | AS48: 2500 | AU48: 2500 | AV48: =AR48+AS48+AT48+AU48 -> 5000
A49: 2.3.2 | B49: Food for 21 participants form 7 project located villages each village 3 participants & 6 staff @ Rs.120 x 21 Person =Rs.1680/- | C49: elephants potatos | D49: 1680 | E49: 2 | F49: =D49*E49 -> 3360 | G49: 0 | H49: =F49+G49 -> 3360 | I49: =21+6 -> 27 | J49: 120 | K49: =I49*J49 -> 3240 | M49: =K49+L49 -> 3240 | P49: =M49 -> 3240 | S49: =O49+P49+Q49+R49 -> 3240 | U49: 1680 | V49: 2 | W49: =U49*V49 -> 3360 | Y49: =W49+X49 -> 3360 | AA49: 3240 | AB49: 2 | AC49: =AA49*AB49 -> 6480 | AE49: =AC49+AD49 -> 6480 | AF49: 1680 | AG49: 2 | AH49: =AF49*AG49 -> 3360 | AJ49: =AH49+AI49 -> 3360 | AK49: =E49+V49+AG49 -> 6 | AL49: =F49+W49+AH49 -> 10080 | AM49: =G49+X49+AI49 -> 0 | AN49: =AL49+AM49 -> 10080 | AP49: Rectified the calculation | AS49: 3240 | AU49: 3240 | AV49: =AR49+AS49+AT49+AU49 -> 6480
A50: 2.3.3 | B50: Project village to training venue transportation charges Rs.2500/- each village 2 participants x 7 Project villages 2 vehicles | C50: Ginger | D50: 1400 | E50: 2 | F50: =D50*E50 -> 2800 | G50: 0 | H50: =F50+G50 -> 2800 | I50: 2 | J50: 2500 | K50: =I50*J50 -> 5000 | M50: =K50+L50 -> 5000 | P50: =M50 -> 5000 | S50: =O50+P50+Q50+R50 -> 5000 | U50: 1400 | V50: 2 | W50: =U50*V50 -> 2800 | Y50: =W50+X50 -> 2800 | AA50: 2500 | AB50: 4 | AC50: =AA50*AB50 -> 10000 | AE50: =AC50+AD50 -> 10000 | AF50: 1400 | AG50: 2 | AH50: =AF50*AG50 -> 2800 | AJ50: =AH50+AI50 -> 2800 | AK50: =E50+V50+AG50 -> 6 | AL50: =F50+W50+AH50 -> 8400 | AM50: =G50+X50+AI50 -> 0 | AN50: =AL50+AM50 -> 8400 | AP50: We have calculated @Rs2500 as per budget description, 2 vehicles per training. | AQ50: =2500*2*2 -> 10000 | AS50: 5000 | AU50: 5000 | AV50: =AR50+AS50+AT50+AU50 -> 10000
A51: 2.3.4 | B51: Arrangements & training matterials @ Rs.500/- | C51: Pulses | D51: 500 | E51: 2 | F51: =D51*E51 -> 1000 | G51: 0 | H51: =F51+G51 -> 1000 | I51: 21 | J51: 50 | K51: =I51*J51 -> 1050 | M51: =K51+L51 -> 1050 | P51: =M51 -> 1050 | S51: =O51+P51+Q51+R51 -> 1050 | U51: 500 | V51: 2 | W51: =U51*V51 -> 1000 | Y51: =W51+X51 -> 1000 | AA51: 500 | AB51: 2 | AC51: =AA51*AB51 -> 1000 | AE51: =AC51+AD51 -> 1000 | AF51: 500 | AG51: 2 | AH51: =AF51*AG51 -> 1000 | AJ51: =AH51+AI51 -> 1000 | AK51: =E51+V51+AG51 -> 6 | AL51: =F51+W51+AH51 -> 3000 | AM51: =G51+X51+AI51 -> 0 | AN51: =AL51+AM51 -> 3000 | AS51: 500 | AU51: 500 | AV51: =AR51+AS51+AT51+AU51 -> 1000
B52: Activities Sub Total 2.3 | D52: =SUM(D48:D51) -> 6080 | E52: 2 | F52: =SUM(F48:F51) -> 12160 | G52: =SUM(G48:G51) -> 0 | H52: =SUM(H48:H51) -> 12160 | I52: 1 | K52: =SUM(K48:K51) -> 11790 | L52: =SUM(L48:L51) -> 0 | M52: =SUM(M48:M51) -> 11790 | O52: =SUM(O48:O51) -> 0 | P52: =SUM(P48:P51) -> 11790 | Q52: =SUM(Q48:Q51) -> 0 | R52: =SUM(R48:R51) -> 0 | S52: =O52+P52+Q52+R52 -> 11790 | U52: =SUM(U48:U51) -> 6080 | V52: 2 | W52: =SUM(W48:W51) -> 12160 | X52: =SUM(X48:X51) -> 0 | Y52: =SUM(Y48:Y51) -> 12160 | AB52: 2 | AC52: =SUM(AC48:AC51) -> 22480 | AD52: =SUM(AD48:AD51) -> 0 | AE52: =SUM(AE48:AE51) -> 22480 | AF52: =SUM(AF48:AF51) -> 6080 | AG52: 2 | AH52: =SUM(AH48:AH51) -> 12160 | AI52: =SUM(AI48:AI51) -> 0 | AJ52: =SUM(AJ48:AJ51) -> 12160 | AK52: =AG52+V52+E52 -> 6 | AL52: =SUM(AL48:AL51) -> 36480 | AM52: =SUM(AM48:AM51) -> 0 | AN52: =SUM(AN48:AN51) -> 36480 | AO52: =SUM(AO48:AO51) -> 0 | AR52: =SUM(AR48:AR51) -> 0 | AS52: =SUM(AS48:AS51) -> 11240 | AT52: =SUM(AT48:AT51) -> 0 | AU52: =SUM(AU48:AU51) -> 11240 | AV52: =AR52+AS52+AT52+AU52 -> 22480
A53: 2.4 | B53: Need based training on Income Generation activity like fish cultivation
A54: 2.4.1 | B54: Honorarium , travelling & food for resource person @Rs.2500 | C54: Resource person | D54: 2500 | E54: 1 | F54: =D54*E54 -> 2500 | H54: =F54+G54 -> 2500 | I54: 1 | J54: 2500 | K54: =I54*J54 -> 2500 | M54: =K54+L54 -> 2500 | P54: =M54 -> 2500 | S54: =O54+P54+Q54+R54 -> 2500 | U54: 2500 | V54: 2 | W54: =U54*V54 -> 5000 | Y54: =W54+X54 -> 5000 | AA54: 2500 | AB54: 2 | AC54: =AA54*AB54 -> 5000 | AE54: =AC54+AD54 -> 5000 | AF54: 2500 | AG54: 1 | AH54: =AF54*AG54 -> 2500 | AJ54: =AH54+AI54 -> 2500 | AK54: =E54+V54+AG54 -> 4 | AL54: =F54+W54+AH54 -> 10000 | AM54: =G54+X54+AI54 -> 0 | AN54: =AL54+AM54 -> 10000 | AR54: 2500 | AT54: 2500 | AV54: =AR54+AS54+AT54+AU54 -> 5000
A55: 2.4.2 | B55: Food for 35 participants & 6 staff @ Rs.120 x 41 Person | C55: Fooding | D55: 3360 | E55: 1 | F55: =D55*E55 -> 3360 | H55: =F55+G55 -> 3360 | I55: 41 | J55: 120 | K55: =I55*J55 -> 4920 | M55: =K55+L55 -> 4920 | P55: =M55 -> 4920 | S55: =O55+P55+Q55+R55 -> 4920 | U55: 3360 | V55: 2 | W55: =U55*V55 -> 6720 | Y55: =W55+X55 -> 6720 | AA55: 4920 | AB55: 2 | AC55: =AA55*AB55 -> 9840 | AE55: =AC55+AD55 -> 9840 | AF55: 3360 | AG55: 1 | AH55: =AF55*AG55 -> 3360 | AJ55: =AH55+AI55 -> 3360 | AK55: =E55+V55+AG55 -> 4 | AL55: =F55+W55+AH55 -> 13440 | AM55: =G55+X55+AI55 -> 0 | AN55: =AL55+AM55 -> 13440 | AP55: Rectified the calculation | AR55: 4920 | AT55: 4920 | AV55: =AR55+AS55+AT55+AU55 -> 9840
A56: 2.4.3 | B56: Project village to training venue transportation charges Rs.2500/- 2 vehicles | C56: Travelling | D56: 3500 | E56: 1 | F56: =D56*E56 -> 3500 | H56: =F56+G56 -> 3500 | I56: 2 | J56: 2500 | K56: =I56*J56 -> 5000 | M56: =K56+L56 -> 5000 | P56: =M56 -> 5000 | S56: =O56+P56+Q56+R56 -> 5000 | U56: 3500 | V56: 2 | W56: =U56*V56 -> 7000 | Y56: =W56+X56 -> 7000 | AA56: 2500 | AB56: 4 | AC56: =AA56*AB56 -> 10000 | AE56: =AC56+AD56 -> 10000 | AF56: 3500 | AG56: 1 | AH56: =AF56*AG56 -> 3500 | AJ56: =AH56+AI56 -> 3500 | AK56: =E56+V56+AG56 -> 4 | AL56: =F56+W56+AH56 -> 14000 | AM56: =G56+X56+AI56 -> 0 | AN56: =AL56+AM56 -> 14000 | AP56: We have calculated @Rs2500 as per budget description, 2 vehicles per training. | AQ56: =2500*2*2 -> 10000 | AR56: 5000 | AT56: 5000 | AV56: =AR56+AS56+AT56+AU56 -> 10000
A57: 2.4.4 | B57: Arrangements & training matterials @ Rs.500/- | C57: matterials | D57: 500 | E57: 1 | F57: =D57*E57 -> 500 | H57: =F57+G57 -> 500 | I57: 35 | J57: 50 | K57: =I57*J57 -> 1750 | M57: =K57+L57 -> 1750 | P57: =M57 -> 1750 | S57: =O57+P57+Q57+R57 -> 1750 | U57: 500 | V57: 2 | W57: =U57*V57 -> 1000 | Y57: =W57+X57 -> 1000 | AA57: 500 | AB57: 2 | AC57: =AA57*AB57 -> 1000 | AE57: =AC57+AD57 -> 1000 | AF57: 500 | AG57: 1 | AH57: =AF57*AG57 -> 500 | AJ57: =AH57+AI57 -> 500 | AK57: =E57+V57+AG57 -> 4 | AL57: =F57+W57+AH57 -> 2000 | AM57: =G57+X57+AI57 -> 0 | AN57: =AL57+AM57 -> 2000 | AR57: 500 | AT57: 500 | AV57: =AR57+AS57+AT57+AU57 -> 1000
B58: Activities Sub Total 2.4 | D58: =SUM(D54:D57) -> 9860 | E58: 1 | F58: =SUM(F54:F57) -> 9860 | G58: =SUM(G54:G57) -> 0 | H58: =SUM(H54:H57) -> 9860 | I58: 1 | K58: =SUM(K54:K57) -> 14170 | L58: =SUM(L54:L57) -> 0 | M58: =SUM(M54:M57) -> 14170 | O58: =SUM(O54:O57) -> 0 | P58: =SUM(P54:P57) -> 14170 | Q58: =SUM(Q54:Q57) -> 0 | R58: =SUM(R54:R57) -> 0 | S58: =O58+P58+Q58+R58 -> 14170 | U58: =SUM(U54:U57) -> 9860 | V58: 2 | W58: =SUM(W54:W57) -> 19720 | X58: =SUM(X54:X57) -> 0 | Y58: =SUM(Y54:Y57) -> 19720 | AB58: 2 | AC58: =SUM(AC54:AC57) -> 25840 | AD58: =SUM(AD54:AD57) -> 0 | AE58: =SUM(AE54:AE57) -> 25840 | AF58: =SUM(AF54:AF57) -> 9860 | AG58: 1 | AH58: =SUM(AH54:AH57) -> 9860 | AI58: =SUM(AI54:AI57) -> 0 | AJ58: =SUM(AJ54:AJ57) -> 9860 | AK58: =AG58+V58+E58 -> 4 | AL58: =SUM(AL54:AL57) -> 39440 | AM58: =SUM(AM54:AM57) -> 0 | AN58: =SUM(AN54:AN57) -> 39440 | AO58: =SUM(AO54:AO57) -> 0 | AR58: =SUM(AR54:AR57) -> 12920 | AS58: =SUM(AS54:AS57) -> 0 | AT58: =SUM(AT54:AT57) -> 12920 | AU58: =SUM(AU54:AU57) -> 0 | AV58: =AR58+AS58+AT58+AU58 -> 25840
A59: 2.5 | B59: Training on Nutritional Kitchen garden and commercial vegetable gardening a) Fruits b) Vegetable
A60: 2.5.1 | B60: Resource person travelling and honorarium charges for Year-1 only and then Project staff will conduct it | C60: Resource person | D60: 2000 | E60: 2 | F60: =D60*E60 -> 4000 | H60: =F60+G60 -> 4000 | I60: 2 | J60: 2000 | K60: =I60*J60 -> 4000 | M60: =K60+L60 -> 4000 | P60: =M60/2 -> 2000 | R60: =M60/2 -> 2000 | S60: =O60+P60+Q60+R60 -> 4000 | U60: 0 | W60: =U60*V60 -> 0 | Y60: =W60+X60 -> 0 | AA60: 0 | AC60: =AA60*AB60 -> 0 | AE60: =AC60+AD60 -> 0 | AF60: 0 | AG60: 0 | AH60: =AF60*AG60 -> 0 | AJ60: =AH60+AI60 -> 0 | AK60: =E60+V60+AG60 -> 2 | AL60: =F60+W60+AH60 -> 4000 | AM60: =G60+X60+AI60 -> 0 | AN60: =AL60+AM60 -> 4000 | AQ60: 0 | AV60: =AR60+AS60+AT60+AU60 -> 0
A61: 2.5.2 | B61: Food for 35 participants form 7 project located villages each village 5 participants & 6 staff @ Rs.120 x 41 Person | C61: Fooding | D61: 3360 | E61: 2 | F61: =D61*E61 -> 6720 | H61: =F61+G61 -> 6720 | I61: 82 | J61: 120 | K61: =I61*J61 -> 9840 | M61: =K61+L61 -> 9840 | P61: =M61/2 -> 4920 | R61: =M61/2 -> 4920 | S61: =O61+P61+Q61+R61 -> 9840 | U61: 3360 | V61: 3 | W61: =U61*V61 -> 10080 | Y61: =W61+X61 -> 10080 | AA61: 4920 | AB61: 3 | AC61: =AA61*AB61 -> 14760 | AE61: =AC61+AD61 -> 14760 | AF61: 3360 | AG61: 3 | AH61: =AF61*AG61 -> 10080 | AJ61: =AH61+AI61 -> 10080 | AK61: =E61+V61+AG61 -> 8 | AL61: =F61+W61+AH61 -> 26880 | AM61: =G61+X61+AI61 -> 0 | AN61: =AL61+AM61 -> 26880 | AO61: Price per unit in year 2 & 3 is much higher than in year 1. Why is this the case? | AP61: Rectified the calculation | AR61: 4920 | AT61: 4920 | AU61: 4920 | AV61: =AR61+AS61+AT61+AU61 -> 14760
A62: 2.5.3 | B62: Project village to training venue transportaion charges Rs.2500, 2 Vehicles x2 trainings | C62: Travelling | D62: 3500 | E62: 2 | F62: =D62*E62 -> 7000 | H62: =F62+G62 -> 7000 | I62: =2*2 -> 4 | J62: 2500 | K62: =I62*J62 -> 10000 | M62: =K62+L62 -> 10000 | P62: =M62/2 -> 5000 | R62: =M62/2 -> 5000 | S62: =O62+P62+Q62+R62 -> 10000 | U62: 3500 | V62: 3 | W62: =U62*V62 -> 10500 | Y62: =W62+X62 -> 10500 | AA62: 2500 | AB62: 6 | AC62: =AA62*AB62 -> 15000 | AE62: =AC62+AD62 -> 15000 | AF62: 3500 | AG62: 3 | AH62: =AF62*AG62 -> 10500 | AJ62: =AH62+AI62 -> 10500 | AK62: =E62+V62+AG62 -> 8 | AL62: =F62+W62+AH62 -> 28000 | AM62: =G62+X62+AI62 -> 0 | AN62: =AL62+AM62 -> 28000 | AP62: We have calculated @Rs2500 as per budget description for 2 vehicles per training. | AQ62: =2500*3*2 -> 15000 | AR62: 5000 | AT62: 5000 | AU62: 5000 | AV62: =AR62+AS62+AT62+AU62 -> 15000
A63: 2.5.4 | B63: Arrangements & training matterials @ Rs.500/- Year-3 @Rs.400/- | C63: medicenes | D63: 500 | E63: 2 | F63: =D63*E63 -> 1000 | H63: =F63+G63 -> 1000 | I63: =35*2 -> 70 | J63: 50 | M63: =K63+L63 -> 0 | P63: =M63/2 -> 0 | R63: =M63/2 -> 0 | S63: =O63+P63+Q63+R63 -> 0 | U63: 500 | V63: 3 | W63: =U63*V63 -> 1500 | Y63: =W63+X63 -> 1500 | AA63: 500 | AB63: 3 | AC63: =AA63*AB63 -> 1500 | AE63: =AC63+AD63 -> 1500 | AF63: 500 | AG63: 3 | AH63: =AF63*AG63 -> 1500 | AJ63: =AH63+AI63 -> 1500 | AK63: =E63+V63+AG63 -> 8 | AL63: =F63+W63+AH63 -> 4000 | AM63: =G63+X63+AI63 -> 0 | AN63: =AL63+AM63 -> 4000 | AR63: 500 | AT63: 500 | AU63: 500 | AV63: =AR63+AS63+AT63+AU63 -> 1500
B64: Activities Sub Total 2.5 | D64: =SUM(D60:D63) -> 9360 | E64: 2 | F64: =SUM(F60:F63) -> 18720 | G64: =SUM(G60:G63) -> 0 | H64: =SUM(H60:H63) -> 18720 | I64: 2 | K64: =SUM(K60:K63) -> 23840 | L64: =SUM(L60:L63) -> 0 | M64: =SUM(M60:M63) -> 23840 | O64: =SUM(O60:O63) -> 0 | P64: =SUM(P60:P63) -> 11920 | Q64: =SUM(Q60:Q63) -> 0 | R64: =SUM(R60:R63) -> 11920 | S64: =O64+P64+Q64+R64 -> 23840 | U64: =SUM(U60:U63) -> 7360 | V64: 3 | W64: =SUM(W60:W63) -> 22080 | X64: =SUM(X60:X63) -> 0 | Y64: =SUM(Y60:Y63) -> 22080 | AB64: 3 | AC64: =SUM(AC60:AC63) -> 31260 | AD64: =SUM(AD60:AD63) -> 0 | AE64: =SUM(AE60:AE63) -> 31260 | AF64: =SUM(AF60:AF63) -> 7360 | AG64: 2 | AH64: =SUM(AH60:AH63) -> 22080 | AI64: =SUM(AI60:AI63) -> 0 | AJ64: =SUM(AJ60:AJ63) -> 22080 | AK64: =AG64+V64+E64 -> 7 | AL64: =SUM(AL60:AL63) -> 62880 | AM64: =SUM(AM60:AM63) -> 0 | AN64: =SUM(AN60:AN63) -> 62880 | AO64: =SUM(AO60:AO63) -> 0 | AR64: =SUM(AR60:AR63) -> 10420 | AS64: =SUM(AS60:AS63) -> 0 | AT64: =SUM(AT60:AT63) -> 10420 | AU64: =SUM(AU60:AU63) -> 10420 | AV64: =AR64+AS64+AT64+AU64 -> 31260
A65: 2.6 | B65: Vaccination and medication to the domestic animals
A66: 2.6.1 | B66: Vet visit 6 times in a year @ 1200 per visit | C66: Resource person | D66: 7000 | E66: 2 | F66: =D66*E66 -> 14000 | H66: =F66+G66 -> 14000 | I66: 6 | J66: 1200 | K66: =I66*J66 -> 7200 | M66: =K66+L66 -> 7200 | O66: 0 | P66: =2*J66 -> 2400 | Q66: =2*J66 -> 2400 | R66: =2*J66 -> 2400 | S66: =O66+P66+Q66+R66 -> 7200 | U66: 7000 | V66: 2 | W66: =U66*V66 -> 14000 | Y66: =W66+X66 -> 14000 | AA66: 1200 | AB66: 6 | AC66: =AA66*AB66 -> 7200 | AE66: =AC66+AD66 -> 7200 | AF66: 7000 | AG66: 2 | AH66: =AF66*AG66 -> 14000 | AJ66: =AH66+AI66 -> 14000 | AK66: =E66+V66+AG66 -> 6 | AL66: =F66+W66+AH66 -> 42000 | AM66: =G66+X66+AI66 -> 0 | AN66: =AL66+AM66 -> 42000 | AO66: I could not understand this. 14 persons will be trained out of project participants? And they will charge to provide services of vaccination & medication? | AQ66: =1200*6*7 -> 50400 | AS66: 3600 | AU66: 3600 | AV66: =AR66+AS66+AT66+AU66 -> 7200
A67: 2.6.2 | B67: Vaccination & medication to the domestic animals medicens avarage expenses each hhs @ 200/- x 437, twice in a year | C67: Fooding | D67: 87400 | E67: 2 | F67: =D67*E67 -> 174800 | H67: =F67+G67 -> 174800 | I67: 437 | J67: =2*200 -> 400 | K67: =I67*J67 -> 174800 | M67: =K67+L67 -> 174800 | O67: 0 | Q67: =M67/2 -> 87400 | R67: =M67/2 -> 87400 | S67: =O67+P67+Q67+R67 -> 174800 | U67: 87400 | V67: 2 | W67: =U67*V67 -> 174800 | Y67: =W67+X67 -> 174800 | AA67: 87400 | AB67: 2 | AC67: =AA67*AB67 -> 174800 | AE67: =AC67+AD67 -> 174800 | AF67: 87400 | AG67: 2 | AH67: =AF67*AG67 -> 174800 | AJ67: =AH67+AI67 -> 174800 | AK67: =E67+V67+AG67 -> 6 | AL67: =F67+W67+AH67 -> 524400 | AM67: =G67+X67+AI67 -> 0 | AN67: =AL67+AM67 -> 524400 | AP67: RAJU: Govt. has no provision, so we have to purchase | AQ67: 174800 | AS67: 87400 | AU67: 87400 | AV67: =AR67+AS67+AT67+AU67 -> 174800
B68: Activities Sub Total 2.6 | D68: =SUM(D66:D67) -> 94400 | E68: 2 | F68: =SUM(F66:F67) -> 188800 | G68: =SUM(G66:G67) -> 0 | H68: =SUM(H66:H67) -> 188800 | K68: =SUM(K66:K67) -> 182000 | L68: =SUM(L66:L67) -> 0 | M68: =SUM(M66:M67) -> 182000 | O68: =SUM(O66:O67) -> 0 | P68: =SUM(P66:P67) -> 2400 | Q68: =SUM(Q66:Q67) -> 89800 | R68: =SUM(R66:R67) -> 89800 | S68: =O68+P68+Q68+R68 -> 182000 | U68: =SUM(U66:U67) -> 94400 | V68: 2 | W68: =SUM(W66:W67) -> 188800 | X68: =SUM(X66:X67) -> 0 | Y68: =SUM(Y66:Y67) -> 188800 | AB68: 2 | AC68: =SUM(AC66:AC67) -> 182000 | AD68: =SUM(AD66:AD67) -> 0 | AE68: =SUM(AE66:AE67) -> 182000 | AF68: =SUM(AF66:AF67) -> 94400 | AG68: 2 | AH68: =SUM(AH66:AH67) -> 188800 | AI68: =SUM(AI66:AI67) -> 0 | AJ68: =SUM(AJ66:AJ67) -> 188800 | AK68: =AG68+V68+E68 -> 6 | AL68: =SUM(AL66:AL67) -> 566400 | AM68: =SUM(AM66:AM67) -> 0 | AN68: =SUM(AN66:AN67) -> 566400 | AO68: =SUM(AO66:AO67) -> 0 | AR68: =SUM(AR66:AR67) -> 0 | AS68: =SUM(AS66:AS67) -> 91000 | AT68: =SUM(AT66:AT67) -> 0 | AU68: =SUM(AU66:AU67) -> 91000 | AV68: =AR68+AS68+AT68+AU68 -> 182000
A69: 2.7 | B69: Distribution of goats
A70: 2.7.1 | B70: Goat distribution @Rs.4500 x 62 No. of farmers (each farmer 1 goat) from 7 Targeted villages (Contribution by participants for goats shed making @Rs.2000 x 62 families) | C70: Resource person | D70: 360000 | E70: 1 | F70: =D70*E70 -> 360000 | G70: 160000 | H70: =F70+G70 -> 520000 | I70: 62 | J70: 4500 | K70: =I70*J70 -> 279000 | L70: =2000*80 -> 160000 | M70: =K70+L70 -> 439000 | Q70: =K70 -> 279000 | S70: =O70+P70+Q70+R70 -> 279000 | U70: 360000 | V70: 0 | W70: =U70*V70 -> 0 | Y70: =W70+X70 -> 0 | AF70: 360000 | AG70: 0 | AH70: =AF70*AG70 -> 0 | AJ70: =AH70+AI70 -> 0 | AK70: =E70+V70+AG70 -> 1 | AL70: =F70+W70+AH70 -> 360000 | AM70: =G70+X70+AI70 -> 160000 | AN70: =AL70+AM70 -> 520000 | AV70: =AR70+AS70+AT70+AU70 -> 0
A71: 2.7.2 | B71: Goats transpotation cost @ Rs.5250/- | C71: matterials | D71: 5250 | E71: 1 | F71: =D71*E71 -> 5250 | H71: =F71+G71 -> 5250 | I71: 1 | J71: 5250 | K71: =I71*J71 -> 5250 | M71: =K71+L71 -> 5250 | Q71: =M71 -> 5250 | S71: =O71+P71+Q71+R71 -> 5250 | U71: 5000 | V71: 0 | W71: =U71*V71 -> 0 | Y71: =W71+X71 -> 0 | AF71: 5000 | AG71: 0 | AH71: =AF71*AG71 -> 0 | AJ71: =AH71+AI71 -> 0 | AK71: =E71+V71+AG71 -> 1 | AL71: =F71+W71+AH71 -> 5250 | AM71: =G71+X71+AI71 -> 0 | AN71: =AL71+AM71 -> 5250 | AV71: =AR71+AS71+AT71+AU71 -> 0
B72: Activities Sub Total 2.7 | D72: =SUM(D70:D71) -> 365250 | E72: 1 | F72: =SUM(F70:F71) -> 365250 | G72: =SUM(G70:G71) -> 160000 | H72: =SUM(H70:H71) -> 525250 | K72: =SUM(K70:K71) -> 284250 | L72: =SUM(L70:L71) -> 160000 | M72: =SUM(M70:M71) -> 444250 | O72: =SUM(O70:O71) -> 0 | P72: =SUM(P70:P71) -> 0 | Q72: =SUM(Q70:Q71) -> 284250 | R72: =SUM(R70:R71) -> 0 | S72: =O72+P72+Q72+R72 -> 284250 | U72: =SUM(U70:U71) -> 365000 | V72: =SUM(V70:V71) -> 0 | W72: =SUM(W70:W71) -> 0 | X72: =SUM(X70:X71) -> 0 | Y72: =SUM(Y70:Y71) -> 0 | AF72: =SUM(AF70:AF71) -> 365000 | AG72: =SUM(AG70:AG71) -> 0 | AH72: =SUM(AH70:AH71) -> 0 | AI72: =SUM(AI70:AI71) -> 0 | AJ72: =SUM(AJ70:AJ71) -> 0 | AK72: =AG72+V72+E72 -> 1 | AL72: =SUM(AL70:AL71) -> 365250 | AM72: =SUM(AM70:AM71) -> 160000 | AN72: =SUM(AN70:AN71) -> 525250 | AO72: =SUM(AO70:AO71) -> 0 | AV72: =AR72+AS72+AT72+AU72 -> 0
B73: Distribution of ginger to the SHGs for cultivation
B74: Ginger distribution to the 7 SHGs in Year-1 & 18 SHGs in Year -2 for doing of cultivation @ Rs.120 x 50 kg x 7 SHGs = Rs.42000/- & 18 SHGs in = 108000/- ( SHGs contribution fencing and labor charges Rs.21000) | C74: Resource person | D74: 42000 | E74: 1 | F74: =D74*E74 -> 42000 | G74: 21000 | H74: =F74+G74 -> 63000 | K74: =I74*J74 -> 0 | M74: =K74+L74 -> 0 | S74: =O74+P74+Q74+R74 -> 0 | U74: 108000 | V74: 1 | W74: =U74*V74 -> 108000 | X74: 21000 | Y74: =W74+X74 -> 129000 | AF74: 42000 | AG74: 0 | AH74: =AF74*AG74 -> 0 | AI74: 21000 | AJ74: =AH74+AI74 -> 21000 | AK74: =E74+V74+AG74 -> 2 | AL74: =F74+W74+AH74 -> 150000 | AM74: =G74+X74+AI74 -> 63000 | AN74: =AL74+AM74 -> 213000 | AP74: The budget for distribution of Ginger has excluded from the budget as it is not feasible in the area. | AV74: =AR74+AS74+AT74+AU74 -> 0
B75: Ginger purchasing and transpotation cost @ 1000/- Year-1 & Year-2 @ Rs. 4800/- | C75: Fooding | D75: 1000 | E75: 1 | F75: =D75*E75 -> 1000 | H75: =F75+G75 -> 1000 | K75: =I75*J75 -> 0 | M75: =K75+L75 -> 0 | S75: =O75+P75+Q75+R75 -> 0 | U75: 3400 | V75: 1 | W75: =U75*V75 -> 3400 | Y75: =W75+X75 -> 3400 | AF75: 1000 | AG75: 0 | AH75: =AF75*AG75 -> 0 | AJ75: =AH75+AI75 -> 0 | AK75: =E75+V75+AG75 -> 2 | AL75: =F75+W75+AH75 -> 4400 | AM75: =G75+X75+AI75 -> 0 | AN75: =AL75+AM75 -> 4400 | AV75: =AR75+AS75+AT75+AU75 -> 0
B76: Activities Sub Total 2.8 | D76: =SUM(D74:D75) -> 43000 | E76: 1 | F76: =SUM(F74:F75) -> 43000 | G76: =SUM(G74:G75) -> 21000 | H76: =SUM(H74:H75) -> 64000 | K76: =SUM(K74:K75) -> 0 | L76: =SUM(L74:L75) -> 0 | M76: =SUM(M74:M75) -> 0 | O76: =SUM(O74:O75) -> 0 | P76: =SUM(P74:P75) -> 0 | Q76: =SUM(Q74:Q75) -> 0 | R76: =SUM(R74:R75) -> 0 | S76: =O76+P76+Q76+R76 -> 0 | U76: =SUM(U74:U75) -> 111400 | V76: 1 | W76: =SUM(W74:W75) -> 111400 | X76: =SUM(X74:X75) -> 21000 | Y76: =SUM(Y74:Y75) -> 132400 | AF76: =SUM(AF74:AF75) -> 43000 | AG76: =SUM(AG74:AG75) -> 0 | AH76: =SUM(AH74:AH75) -> 0 | AI76: =SUM(AI74:AI75) -> 21000 | AJ76: =SUM(AJ74:AJ75) -> 21000 | AK76: =AG76+V76+E76 -> 2 | AL76: =SUM(AL74:AL75) -> 154400 | AM76: =SUM(AM74:AM75) -> 63000 | AN76: =SUM(AN74:AN75) -> 217400 | AO76: =SUM(AO74:AO75) -> 0 | AV76: =AR76+AS76+AT76+AU76 -> 0
A77: 2.8 | B77: Training on Minor Millet farming
A78: 2.8.1 | B78: Resource person travelling and honorarium charges for Year-1 only and then Project staff will conduct it | I78: 1 | J78: 2500 | K78: =I78*J78 -> 2500 | M78: =K78+L78 -> 2500 | O78: =M78 -> 2500 | S78: =O78+P78+Q78+R78 -> 2500 | AV78: =AR78+AS78+AT78+AU78 -> 0
A79: 2.8.2 | B79: Food for 35 participants form 7 project located villages each village 5 participants & 6 staff @ Rs.120 x 41 Person | I79: 41 | J79: 120 | K79: =I79*J79 -> 4920 | M79: =K79+L79 -> 4920 | O79: =M79 -> 4920 | S79: =O79+P79+Q79+R79 -> 4920 | AV79: =AR79+AS79+AT79+AU79 -> 0
A80: 2.8.3 | B80: Project village to training venue transportaion charges Rs.2500, 2 Vehicles | I80: 1 | J80: =2*2500 -> 5000 | K80: =I80*J80 -> 5000 | M80: =K80+L80 -> 5000 | O80: =M80 -> 5000 | S80: =O80+P80+Q80+R80 -> 5000 | AV80: =AR80+AS80+AT80+AU80 -> 0
A81: 2.8.4 | B81: Arrangements & training matterials @ Rs.50 | I81: 35 | J81: 50 | K81: =I81*J81 -> 1750 | M81: =K81+L81 -> 1750 | O81: =M81 -> 1750 | S81: =O81+P81+Q81+R81 -> 1750 | AV81: =AR81+AS81+AT81+AU81 -> 0
A82: 2.8.1 | B82: Millet (Mandia) seeds distribution to the 20 farmers for doing of cultivation @ Rs.50 x 1.5 kg x 30 farmer ( Contribution fencing and labor charges Rs.200 x 30 = Rs.6000) | C82: Resource person | D82: 4800 | E82: 1 | F82: =D82*E82 -> 4800 | G82: 6000 | H82: =F82+G82 -> 10800 | M82: =K82+L82 -> 0 | O82: =M82 -> 0 | S82: =O82+P82+Q82+R82 -> 0 | U82: 4800 | V82: 1 | W82: =U82*V82 -> 4800 | X82: 6000 | Y82: =W82+X82 -> 10800 | AA82: 4800 | AB82: 1 | AC82: =AA82*AB82 -> 4800 | AD82: 6000 | AE82: =AC82+AD82 -> 10800 | AF82: 4800 | AG82: 0 | AH82: =AF82*AG82 -> 0 | AJ82: =AH82+AI82 -> 0 | AK82: =E82+V82+AG82 -> 2 | AL82: =F82+W82+AH82 -> 9600 | AM82: =G82+X82+AI82 -> 12000 | AN82: =AL82+AM82 -> 21600 | AR82: 4800 | AV82: =AR82+AS82+AT82+AU82 -> 4800
A83: 2.8.2 | B83: Millet (Mandia) transpotation cost @ 1500/- | C83: Fooding | D83: 1500 | E83: 1 | F83: =D83*E83 -> 1500 | H83: =F83+G83 -> 1500 | M83: =K83+L83 -> 0 | U83: 1500 | V83: 1 | W83: =U83*V83 -> 1500 | Y83: =W83+X83 -> 1500 | AA83: 1500 | AB83: 1 | AC83: =AA83*AB83 -> 1500 | AE83: =AC83+AD83 -> 1500 | AF83: 1500 | AG83: 0 | AH83: =AF83*AG83 -> 0 | AJ83: =AH83+AI83 -> 0 | AK83: =E83+V83+AG83 -> 2 | AL83: =F83+W83+AH83 -> 3000 | AM83: =G83+X83+AI83 -> 0 | AN83: =AL83+AM83 -> 3000 | AR83: 1500 | AV83: =AR83+AS83+AT83+AU83 -> 1500
B84: Activities Sub Total 2.8 | D84: =SUM(D82:D83) -> 6300 | E84: 1 | F84: =SUM(F82:F83) -> 6300 | G84: =SUM(G82:G83) -> 6000 | H84: =SUM(H82:H83) -> 12300 | I84: 1 | K84: =SUM(K78:K81) -> 14170 | L84: =SUM(L82:L83) -> 0 | M84: =SUM(M78:M81) -> 14170 | O84: =SUM(O78:O81) -> 14170 | P84: =SUM(P78:P81) -> 0 | Q84: =SUM(Q78:Q81) -> 0 | R84: =SUM(R78:R81) -> 0 | S84: =O84+P84+Q84+R84 -> 14170 | U84: =SUM(U82:U83) -> 6300 | V84: 1 | W84: =SUM(W82:W83) -> 6300 | X84: =SUM(X82:X83) -> 6000 | Y84: =SUM(Y82:Y83) -> 12300 | AB84: 1 | AC84: =SUM(AC82:AC83) -> 6300 | AD84: =SUM(AD82:AD83) -> 6000 | AE84: =SUM(AE82:AE83) -> 12300 | AF84: =SUM(AF82:AF83) -> 6300 | AG84: =SUM(AG82:AG83) -> 0 | AH84: =SUM(AH82:AH83) -> 0 | AI84: =SUM(AI82:AI83) -> 0 | AJ84: =SUM(AJ82:AJ83) -> 0 | AK84: =AG84+V84+E84 -> 2 | AL84: =SUM(AL82:AL83) -> 12600 | AM84: =SUM(AM82:AM83) -> 12000 | AN84: =SUM(AN82:AN83) -> 24600 | AO84: =SUM(AO82:AO83) -> 0 | AR84: =SUM(AR82:AR83) -> 6300 | AS84: =SUM(AS82:AS83) -> 0 | AT84: =SUM(AT82:AT83) -> 0 | AU84: =SUM(AU82:AU83) -> 0 | AV84: =AR84+AS84+AT84+AU84 -> 6300
A85: 2.9 | B85: Distribution of small Petty business materials
A86: 2.9.1 | B86: Selected people will be distributed the business materials as per their choice | C86: Resource person | D86: 90000 | E86: 1 | F86: =D86*E86 -> 90000 | G86: 30000 | H86: =F86+G86 -> 120000 | K86: 90000 | L86: 30000 | M86: =K86+L86 -> 120000 | Q86: =K86/2 -> 45000 | R86: =K86/2 -> 45000 | S86: =O86+P86+Q86+R86 -> 90000 | U86: 90000 | V86: 0 | W86: =U86*V86 -> 0 | X86: 0 | Y86: =W86+X86 -> 0 | AF86: 90000 | AG86: 0 | AH86: =AF86*AG86 -> 0 | AJ86: =AH86+AI86 -> 0 | AK86: =E86+V86+AG86 -> 1 | AL86: =F86+W86+AH86 -> 90000 | AM86: =G86+X86+AI86 -> 30000 | AN86: =AL86+AM86 -> 120000 | AV86: =AR86+AS86+AT86+AU86 -> 0
A87: 2.10.2 | B87: Matterials purchasing and transpotation cost @Rs.2000/- | C87: Fooding | D87: 2000 | E87: 1 | F87: =D87*E87 -> 2000 | G87: 0 | H87: =F87+G87 -> 2000 | K87: =I87*J87 -> 0 | M87: =K87+L87 -> 0 | S87: =O87+P87+Q87+R87 -> 0 | U87: 2000 | V87: 0 | W87: =U87*V87 -> 0 | X87: 0 | Y87: =W87+X87 -> 0 | AF87: 2000 | AG87: 0 | AH87: =AF87*AG87 -> 0 | AJ87: =AH87+AI87 -> 0 | AK87: =E87+V87+AG87 -> 1 | AL87: =F87+W87+AH87 -> 2000 | AM87: =G87+X87+AI87 -> 0 | AN87: =AL87+AM87 -> 2000 | AV87: =AR87+AS87+AT87+AU87 -> 0
B88: Activities Sub Total 2.10 | D88: =SUM(D86:D87) -> 92000 | E88: 1 | F88: =SUM(F86:F87) -> 92000 | G88: =SUM(G86:G87) -> 30000 | H88: =SUM(H86:H87) -> 122000 | I88: 2 | K88: =SUM(K86:K87) -> 90000 | L88: =SUM(L86:L87) -> 30000 | M88: =SUM(M86:M87) -> 120000 | O88: =SUM(O86:O87) -> 0 | P88: =SUM(P86:P87) -> 0 | Q88: =SUM(Q86:Q87) -> 45000 | R88: =SUM(R86:R87) -> 45000 | S88: =O88+P88+Q88+R88 -> 90000 | U88: =SUM(U86:U87) -> 92000 | V88: =SUM(V86:V87) -> 0 | W88: =SUM(W86:W87) -> 0 | X88: =SUM(X86:X87) -> 0 | Y88: =SUM(Y86:Y87) -> 0 | AF88: =SUM(AF86:AF87) -> 92000 | AG88: =SUM(AG86:AG87) -> 0 | AH88: =SUM(AH86:AH87) -> 0 | AI88: =SUM(AI86:AI87) -> 0 | AJ88: =SUM(AJ86:AJ87) -> 0 | AK88: =AG88+V88+E88 -> 1 | AL88: =SUM(AL86:AL87) -> 92000 | AM88: =SUM(AM86:AM87) -> 30000 | AN88: =SUM(AN86:AN87) -> 122000 | AO88: =SUM(AO86:AO87) -> 0 | AV88: =AR88+AS88+AT88+AU88 -> 0
A89: 2.1 | B89: Vegetable seeds distribution for Kitchen gardening
A90: 2.10.1 | B90: Vegetable Seeds support (Contribution fencing and labor charges @250 x 437 families) | C90: matterials | D90: 109250 | E90: 1 | F90: =D90*E90 -> 109250 | G90: 109250 | H90: =F90+G90 -> 218500 | I90: 437 | J90: 250 | K90: =I90*J90 -> 109250 | M90: =K90+L90 -> 109250 | Q90: =K90 -> 109250 | S90: =O90+P90+Q90+R90 -> 109250 | U90: 109250 | V90: 0 | W90: =U90*V90 -> 0 | Y90: =W90+X90 -> 0 | AF90: 109250 | AG90: 0 | AH90: =AF90*AG90 -> 0 | AJ90: =AH90+AI90 -> 0 | AK90: =E90+V90+AG90 -> 1 | AL90: =F90+W90+AH90 -> 109250 | AM90: =G90+X90+AI90 -> 109250 | AN90: =AL90+AM90 -> 218500 | AV90: =AR90+AS90+AT90+AU90 -> 0
A91: 2.10.2 | B91: Seeds transpotation cost @ 1000/- | C91: Transpotration | D91: 1000 | E91: 1 | F91: =D91*E91 -> 1000 | H91: =F91+G91 -> 1000 | I91: 1 | J91: 1000 | K91: 1000 | M91: =K91+L91 -> 1000 | Q91: =M91 -> 1000 | S91: =O91+P91+Q91+R91 -> 1000 | U91: 1000 | V91: 0 | W91: =U91*V91 -> 0 | Y91: =W91+X91 -> 0 | AF91: 1000 | AG91: 0 | AH91: =AF91*AG91 -> 0 | AJ91: =AH91+AI91 -> 0 | AK91: =E91+V91+AG91 -> 1 | AL91: =F91+W91+AH91 -> 1000 | AM91: =G91+X91+AI91 -> 0 | AN91: =AL91+AM91 -> 1000 | AV91: =AR91+AS91+AT91+AU91 -> 0
B92: Activities Sub Total 2.10 | D92: =SUM(D90:D91) -> 110250 | E92: 1 | F92: =SUM(F90:F91) -> 110250 | G92: =SUM(G90:G91) -> 109250 | H92: =SUM(H90:H91) -> 219500 | I92: 1 | K92: =SUM(K90:K91) -> 110250 | L92: =SUM(L90:L91) -> 0 | M92: =SUM(M90:M91) -> 110250 | O92: =SUM(O90:O91) -> 0 | P92: =SUM(P90:P91) -> 0 | Q92: =SUM(Q90:Q91) -> 110250 | R92: =SUM(R90:R91) -> 0 | S92: =O92+P92+Q92+R92 -> 110250 | U92: =SUM(U90:U91) -> 110250 | V92: =SUM(V90:V91) -> 0 | W92: =SUM(W90:W91) -> 0 | X92: =SUM(X90:X91) -> 0 | Y92: =SUM(Y90:Y91) -> 0 | AF92: =SUM(AF90:AF91) -> 110250 | AG92: =SUM(AG90:AG91) -> 0 | AH92: =SUM(AH90:AH91) -> 0 | AI92: =SUM(AI90:AI91) -> 0 | AJ92: =SUM(AJ90:AJ91) -> 0 | AK92: =AG92+V92+E92 -> 1 | AL92: =SUM(AL90:AL91) -> 110250 | AM92: =SUM(AM90:AM91) -> 109250 | AN92: =SUM(AN90:AN91) -> 219500 | AO92: =SUM(AO90:AO91) -> 0 | AV92: =AR92+AS92+AT92+AU92 -> 0
A93: 2.11 | B93: Distribution of earthen pot for micro water harvest and use it in the kitchen garden
A94: 2.11.1 | B94: Promote 437 hh to do homestead kitchen garden and will be provided a mud water pot for harvesting of west water @ Rs 120 (437 hh contribute their own labor & fencing it for making kitchen garden @ Rs.250 x 1 days x 437 hh = Rs109250/- | C94: matterials | D94: 52440 | E94: 0 | F94: =D94*E94 -> 0 | G94: 0 | H94: 0 | K94: =I94*J94 -> 0 | M94: =K94+L94 -> 0 | S94: =O94+P94+Q94+R94 -> 0 | U94: 52440 | V94: 1 | W94: =U94*V94 -> 52440 | X94: 109250 | Y94: =W94+X94 -> 161690 | AF94: 52440 | AG94: 0 | AH94: =AF94*AG94 -> 0 | AJ94: =AH94+AI94 -> 0 | AK94: =E94+V94+AG94 -> 1 | AL94: =F94+W94+AH94 -> 52440 | AM94: =G94+X94+AI94 -> 109250 | AN94: =AL94+AM94 -> 161690 | AP94: Due to adjustment in Budget we have deducted the cost of mud pot | AV94: =AR94+AS94+AT94+AU94 -> 0
A95: 2.11.2 | B95: Mud pot purchasing and transpotation cost @ Rs.3000/- | C95: Transpotration | D95: 3000 | E95: 0 | F95: =D95*E95 -> 0 | H95: =F95+G95 -> 0 | K95: =I95*J95 -> 0 | M95: =K95+L95 -> 0 | S95: =O95+P95+Q95+R95 -> 0 | U95: 3000 | V95: 1 | W95: =U95*V95 -> 3000 | Y95: =W95+X95 -> 3000 | AF95: 3000 | AG95: 0 | AH95: =AF95*AG95 -> 0 | AJ95: =AH95+AI95 -> 0 | AK95: =E95+V95+AG95 -> 1 | AL95: =F95+W95+AH95 -> 3000 | AM95: =G95+X95+AI95 -> 0 | AN95: =AL95+AM95 -> 3000 | AV95: =AR95+AS95+AT95+AU95 -> 0
B96: Activities Sub Total 2.11 | D96: =SUM(D94:D95) -> 55440 | E96: =SUM(E94:E95) -> 0 | F96: =SUM(F94:F95) -> 0 | G96: =SUM(G94:G95) -> 0 | H96: =SUM(H94:H95) -> 0 | I96: 0 | K96: =SUM(K94:K95) -> 0 | L96: =SUM(L94:L95) -> 0 | M96: =SUM(M94:M95) -> 0 | O96: =SUM(O94:O95) -> 0 | P96: =SUM(P94:P95) -> 0 | Q96: =SUM(Q94:Q95) -> 0 | R96: =SUM(R94:R95) -> 0 | S96: =O96+P96+Q96+R96 -> 0 | U96: =SUM(U94:U95) -> 55440 | V96: 1 | W96: =SUM(W94:W95) -> 55440 | X96: =SUM(X94:X95) -> 109250 | Y96: =SUM(Y94:Y95) -> 164690 | AA96: =SUM(AA94:AA95) -> 0 | AC96: =SUM(AC94:AC95) -> 0 | AD96: =SUM(AD94:AD95) -> 0 | AE96: =SUM(AE94:AE95) -> 0 | AF96: =SUM(AF94:AF95) -> 55440 | AG96: =SUM(AG94:AG95) -> 0 | AH96: =SUM(AH94:AH95) -> 0 | AI96: =SUM(AI94:AI95) -> 0 | AJ96: =SUM(AJ94:AJ95) -> 0 | AK96: =AG96+V96+E96 -> 1 | AL96: =SUM(AL94:AL95) -> 55440 | AM96: =SUM(AM94:AM95) -> 109250 | AN96: =SUM(AN94:AN95) -> 164690 | AO96: =SUM(AO94:AO95) -> 0 | AR96: =SUM(AR94:AR95) -> 0 | AS96: =SUM(AS94:AS95) -> 0 | AT96: =SUM(AT94:AT95) -> 0 | AU96: =SUM(AU94:AU95) -> 0 | AV96: =AR96+AS96+AT96+AU96 -> 0
A97: 2.12 | B97: Distribution of fish seeds for fish Cultivation
A98: 2.12.1 | B98: Fish seeds distribution to pond holder farmers for doing of fish cultivation @ Rs.2000/- x 35 person = Rs.70000/- | C98: matterials | D98: 70000 | E98: 1 | F98: =D98*E98 -> 70000 | H98: =F98+G98 -> 70000 | M98: =K98+L98 -> 0 | S98: =O98+P98+Q98+R98 -> 0 | U98: 70000 | V98: 0 | W98: =U98*V98 -> 0 | Y98: =W98+X98 -> 0 | AF98: 70000 | AG98: 0 | AH98: =AF98*AG98 -> 0 | AJ98: =AH98+AI98 -> 0 | AK98: =E98+V98+AG98 -> 1 | AL98: =F98+W98+AH98 -> 70000 | AM98: =G98+X98+AI98 -> 0 | AN98: =AL98+AM98 -> 70000 | AV98: =AR98+AS98+AT98+AU98 -> 0
B99: Activities Sub Total 2.12 | D99: =SUM(D98) -> 70000 | E99: =SUM(E98) -> 1 | F99: =SUM(F98) -> 70000 | G99: =SUM(G98) -> 0 | H99: =SUM(H98) -> 70000 | I99: 0 | K99: =SUM(K98) -> 0 | L99: =SUM(L98) -> 0 | M99: =SUM(M98) -> 0 | O99: =SUM(O98) -> 0 | P99: =SUM(P98) -> 0 | Q99: =SUM(Q98) -> 0 | R99: =SUM(R98) -> 0 | S99: =O99+P99+Q99+R99 -> 0 | U99: =SUM(U98) -> 70000 | V99: =SUM(V98) -> 0 | W99: =SUM(W98) -> 0 | X99: =SUM(X98) -> 0 | Y99: =SUM(Y98) -> 0 | AA99: =SUM(AA98) -> 0 | AB99: =SUM(AB98) -> 0 | AC99: =SUM(AC98) -> 0 | AD99: =SUM(AD98) -> 0 | AE99: =SUM(AE98) -> 0 | AF99: =SUM(AF98) -> 70000 | AG99: =SUM(AG98) -> 0 | AH99: =SUM(AH98) -> 0 | ... AJ99: =SUM(AJ98) -> 0 | AK99: =AG99+V99+E99 -> 1 | AL99: =SUM(AL98) -> 70000 | AM99: =SUM(AM98) -> 0 | AN99: =SUM(AN98) -> 70000 | AO99: =SUM(AO98) -> 0 | AR99: =SUM(AR98) -> 0 | AS99: =SUM(AS98) -> 0 | AT99: =SUM(AT98) -> 0 | AU99: =SUM(AU98) -> 0 | AV99: =AR99+AS99+AT99+AU99 -> 0
B100: Activities Sub Total for Outcomes :2 | D100: =SUM(D40+D46+D52+D58+D64+D68+D72+D76+D84+D88+D92+D96+D99) -> 881160 | F100: =SUM(F40+F46+F52+F58+F64+F68+F72+F76+F84+F88+F92+F96+F99) -> 944920 | G100: =SUM(G40+G46+G52+G58+G64+G68+G72+G76+G84+G88+G92+G96+G99) -> 326250 | H100: =SUM(H40+H46+H52+H58+H64+H68+H72+H76+H84+H88+H92+H96+H99) -> 1271170 | K100: =SUM(K40+K46+K52+K58+K64+K68+K72+K76+K84+K88+K92+K96+K99) -> 771980 | L100: =SUM(L40+L46+L52+L58+L64+L68+L72+L76+L84+L88+L92+L96+L99) -> 190000 | M100: =SUM(M40+M46+M52+M58+M64+M68+M72+M76+M84+M88+M92+M96+M99) -> 961980 | O100: =SUM(O40+O46+O52+O58+O64+O68+O72+O76+O84+O88+O92+O96+O99) -> 14170 | P100: =SUM(P40+P46+P52+P58+P64+P68+P72+P76+P84+P88+P92+P96+P99) -> 40280 | Q100: =SUM(Q40+Q46+Q52+Q58+Q64+Q68+Q72+Q76+Q84+Q88+Q92+Q96+Q99) -> 557140 | R100: =SUM(R40+R46+R52+R58+R64+R68+R72+R76+R84+R88+R92+R96+R99) -> 160390 | S100: =O100+P100+Q100+R100 -> 771980 | U100: =SUM(U40+U46+U52+U58+U64+U68+U72+U76+U84+U88+U92+U96+U99) -> 947310 | W100: =SUM(W40+W46+W52+W58+W64+W68+W72+W76+W84+W88+W92+W96+W99) -> 473060 | X100: =SUM(X40+X46+X52+X58+X64+X68+X72+X76+X84+X88+X92+X96+X99) -> 136250 | Y100: =SUM(Y40+Y46+Y52+Y58+Y64+Y68+Y72+Y76+Y84+Y88+Y92+Y96+Y99) -> 609310 | AA100: =SUM(AA40+AA46+AA52+AA58+AA64+AA68+AA72+AA76+AA84+AA88+AA92+AA96+AA99) -> 0 | AC100: =SUM(AC40+AC46+AC52+AC58+AC64+AC68+AC72+AC76+AC84+AC88+AC92+AC96+AC99) -> 343400 | AD100: =SUM(AD40+AD46+AD52+AD58+AD64+AD68+AD72+AD76+AD84+AD88+AD92+AD96+AD99) -> 6000 | AE100: =SUM(AE40+AE46+AE52+AE58+AE64+AE68+AE72+AE76+AE84+AE88+AE92+AE96+AE99) -> 349400 | AF100: =SUM(AF40+AF46+AF52+AF58+AF64+AF68+AF72+AF76+AF84+AF88+AF92+AF96+AF99) -> 878910 | AH100: =SUM(AH40+AH46+AH52+AH58+AH64+AH68+AH72+AH76+AH84+AH88+AH92+AH96+AH99) -> 270840 | AI100: =SUM(AI40+AI46+AI52+AI58+AI64+AI68+AI72+AI76+AI84+AI88+AI92+AI96+AI99) -> 21000 | AJ100: =SUM(AJ40+AJ46+AJ52+AJ58+AJ64+AJ68+AJ72+AJ76+AJ84+AJ88+AJ92+AJ96+AJ99) -> 291840 | AK100: =SUM(AK40+AK46+AK52+AK58+AK64+AK68+AK72+AK76+AK84+AK88+AK92+AK96+AK99) -> 57 | AL100: =SUM(AL40+AL46+AL52+AL58+AL64+AL68+AL72+AL76+AL84+AL88+AL92+AL96+AL99) -> 1688820 | AM100: =SUM(AM40+AM46+AM52+AM58+AM64+AM68+AM72+AM76+AM84+AM88+AM92+AM96+AM99) -> 483500 | AN100: =SUM(AN40+AN46+AN52+AN58+AN64+AN68+AN72+AN76+AN84+AN88+AN92+AN96+AN99) -> 2172320 | AO100: =SUM(AO40+AO46+AO52+AO58+AO64+AO68+AO72+AO76+AO84+AO88+AO92+AO96+AO99) -> 0 | AQ100: =SUM(AQ40+AQ46+AQ52+AQ58+AQ64+AQ68+AQ72+AQ76+AQ84+AQ88+AQ92+AQ96+AQ99) -> 0 | AR100: =SUM(AR40+AR46+AR52+AR58+AR64+AR68+AR72+AR76+AR84+AR88+AR92+AR96+AR99) -> 42060 | AS100: =SUM(AS40+AS46+AS52+AS58+AS64+AS68+AS72+AS76+AS84+AS88+AS92+AS96+AS99) -> 127580 | AT100: =SUM(AT40+AT46+AT52+AT58+AT64+AT68+AT72+AT76+AT84+AT88+AT92+AT96+AT99) -> 35760 | AU100: =SUM(AU40+AU46+AU52+AU58+AU64+AU68+AU72+AU76+AU84+AU88+AU92+AU96+AU99) -> 138000 | AV100: =AR100+AS100+AT100+AU100 -> 343400
...

Sheet Summary Sheet
A1: Project Title: Ensuring food and livelihood security of indigenous and other marginalized communities in Thakurmunda Block, Mayurbhanj, Odisha
A2: Accounting Period From 01. April-2024 to 31.March 2025
A3: Project Partner: DAPTA (Development Agency for Poor and Tribal Awakening)
A4: Contact person | C4: Aadarsh Bharat Mishra Sharma ( +91 94370 29124)
A5: E-mail ID | C5: dapta@rediffmail.com
A6: Summery sheet of Project Grant & Expenses in Year-2- 2024-25
A7: Total Approved Budget in 2024-25 | C7: 2917500 | K7: TOTAL
A8: MCC Share in budget for 2024-25 | C8: 2675000
A9: Cash in hand from 2024-25 | C9: 0
A10: Balance in bank (minimum bal to be maintained,not to be used for project) | C10: 0 | K10: =C8+C9 -> 2675000
D11: 1st Qtr | F11: 2nd Qtr | H11: 3rd Qtr. | J11: 4th Qtr.
A12: Total Brought Forward | C12: → | D12: 67601.6 | F12: =D22 -> 111252.22 | H12: =F22 -> 70766.32 | J12: =H22 -> 21424.2 | K12: =C9 -> 0
A14: MCC Grant Received | C14: → | D14: 577475 | F14: 720885 | H14: 526803 | K14: =SUM(D14+F14+H14+J14) -> 1825163
K15: =SUM(D15+F15+H15+J15) -> 0
A16: Bank Interest earned | C16: → | D16: 2150 | F16: 2994 | H16: 2912 | K16: =SUM(D16+F16+H16+J16) -> 8056
K17: =SUM(D17+F17+H17+J17) -> 0
A18: Total Available | C18: → | D18: =SUM(D12+D14+D16) -> 647226.6 | F18: =SUM(F12+F14+F16) -> 835131.22 | H18: =SUM(H12+H14+H16) -> 600481.32 | K18: =D12+K14+K16 -> 1900820.6
K19: =SUM(D19+F19+H19+J19) -> 0
A20: Grant utilization | C20: → | D20: 535974.38 | F20: 764364.9 | H20: 579057.12 | K20: =SUM(D20+F20+H20+J20) -> 1879396.4
A22: Balance available | C22: → | D22: =D18-D20 -> 111252.22 | F22: =F18-F20 -> 70766.32 | H22: =H18-H20 -> 21424.2 | J22: =J18-J20 -> 0 | K22: =K18-K20 -> 21424.2

Sheet Budget Comparison
B1: Partner: DAPTA (Development Agency for Poor and Tribal Awakening)
A2: Project Title: Ensuring food and livelihood security of indigenous and other marginalized communities in Thakurmunda Block, Mayurbhanj, Odisha
A3: Accounting Period From 01. April 2024 to 31.March 2025
A4: ID | B4: Description | C4: Year-2 | D4: 1st Qtr Exp. | E4: 2nd Qtr Exp. | F4: 3rd Qtr Exp. | G4: 4th Qtr Exp. | H4: TOTAL Expenses | I4: EXPENSES % | J4: UNSPENT BUDGET balance | K4: UNSPENT % | L4: Explanation for significant variance (< or >10%)
C5: Approved MCC Budget
A6: 1 | B6: Outcome :1 Activities
A7: 1.1 | B7: Baseline | C7: 0 | D7: =+' Qtr-1 April-24 to June-24 '!F17 -> 0 | E7: =+' Qtr- 2 July-24 to Sept-24 (2)'!F17 -> 0 | F7: =+' Qtr-3 Octo-24 to Dec-24'!F18 -> 0 | G7: =+' Qtr-4 Jan-25 to march-25'!F16 -> 0 | H7: =SUM(D7:G7) -> 0 | I7: =H7/C7 -> #DIV/0! | J7: =C7-H7 -> 0 | K7: =J7/C7 -> #DIV/0!
A8: 1.2 | B8: Monthly PRA/ Data collection/ Village Community Meeting
A9: 1.2.1 | B9: Monthly Village Community Meeting (Biscuits / Snacks /per time /12 Months) @Rs.15 x 437 + 6 staff =Rs.6660/- | C9: 79920 | D9: =+' Qtr-1 April-24 to June-24 '!F23 -> 19365 | E9: =+' Qtr- 2 July-24 to Sept-24 (2)'!F23 -> 17580 | F9: =+' Qtr-3 Octo-24 to Dec-24'!F24 -> 18735 | G9: =+' Qtr-4 Jan-25 to march-25'!F21 -> 0 | H9: =SUM(D9:G9) -> 55680 | I9: =H9/C9 -> 0.6966967 | J9: =C9-H9 -> 24240 | K9: =J9/C9 -> 0.3033033
B10: Activities Sub Total 1.2 | C10: =SUM(C7,C9) -> 79920 | D10: =SUM(D7,D9) -> 19365 | E10: =SUM(E7,E9) -> 17580 | F10: =SUM(F7,F9) -> 18735 | G10: =SUM(G7,G9) -> 0 | H10: =SUM(H7,H9) -> 55680 | J10: =SUM(J7,J9) -> 24240 | K10: =J10/C10 -> 0.3033033
A11: 1.3 | B11: Training on Improved agriculture methods and Technology :- a) SRI (Paddy farming in row) b) Multi cropping c) Crop diversification d) Crop rotation e) Azola growing f) Seed preservation g) Seed treatment
A12: 1.3.1 | B12: Honorarium , travelling & food for resource person @Rs.2000 (above mentioned some subject will be conducted by the Project staff) | C12: 2000 | D12: =+' Qtr-1 April-24 to June-24 '!F30 -> 1960 | E12: =+' Qtr- 2 July-24 to Sept-24 (2)'!F28 -> 0 | F12: =+' Qtr-3 Octo-24 to Dec-24'!F31 -> 0 | G12: =+' Qtr-4 Jan-25 to march-25'!F28 -> 0 | H12: =SUM(D12:G12) -> 1960 | I12: =H12/C12 -> 0.98 | J12: =C12-H12 -> 40 | K12: =J12/C12 -> 0.02
A13: 1.3.2 | B13: Food for 20 participants & 6 staff @ Rs.120 x 26 Person | C13: 12480 | D13: =+' Qtr-1 April-24 to June-24 '!F35 -> 3120 | E13: =+' Qtr- 2 July-24 to Sept-24 (2)'!F31 -> 0 | F13: =+' Qtr-3 Octo-24 to Dec-24'!F36 -> 6120 | G13: =+' Qtr-4 Jan-25 to march-25'!F33 -> 0 | H13: =SUM(D13:G13) -> 9240 | I13: =H13/C13 -> 0.74038462 | J13: =C13-H13 -> 3240 | K13: =J13/C13 -> 0.25961538
A14: 1.3.3 | B14: Project village to training venue Transportation charges 20 participants x 1 Project villages @ Rs.2500/-; 2 vehicles | C14: 20000 | D14: =+' Qtr-1 April-24 to June-24 '!F39 -> 5000 | E14: =+' Qtr- 2 July-24 to Sept-24 (2)'!F34 -> 0 | F14: =+' Qtr-3 Octo-24 to Dec-24'!F41 -> 10000 | G14: =+' Qtr-4 Jan-25 to march-25'!F37 -> 0 | H14: =SUM(D14:G14) -> 15000 | I14: =H14/C14 -> 0.75 | J14: =C14-H14 -> 5000 | K14: =J14/C14 -> 0.25
A15: 1.3.4 | B15: Arrangements & training matterials @ Rs.500/- | C15: 2000 | D15: =+' Qtr-1 April-24 to June-24 '!F43 -> 500 | E15: =+' Qtr- 2 July-24 to Sept-24 (2)'!F37 -> 0 | F15: =+' Qtr-3 Octo-24 to Dec-24'!F45 -> 900 | G15: =+' Qtr-4 Jan-25 to march-25'!F41 -> 0 | H15: =SUM(D15:G15) -> 1400 | I15: =H15/C15 -> 0.7 | J15: =C15-H15 -> 600 | K15: =J15/C15 -> 0.3
B16: Activities Sub Total 1.3 | C16: =SUM(C12:C15) -> 36480 | D16: =SUM(D12:D15) -> 10580 | E16: =SUM(E12:E15) -> 0 | F16: =SUM(F12:F15) -> 17020 | G16: =SUM(G12:G15) -> 0 | H16: =SUM(H12:H15) -> 27600 | I16: =SUM(I12:I15) -> 3.1703846 | J16: =SUM(J12:J15) -> 8880 | K16: =J16/C16 -> 0.24342105 | L16: =SUM(L12:L15) -> 0
A17: 1.4 | B17: Training on Natural Resource Management a) Soil health ( Testing, treatment and preservation) b) Organic farming (Chemical free) c) Compost pit & its preparation d) Vermin compost making e) Bio- Pesticide f) Bio- fertilizer
A18: 1.4.1 | B18: Honorarium, travelling & food for resource person @Rs.2000 | C18: 8000 | D18: =+' Qtr-1 April-24 to June-24 '!F49 -> 1990 | E18: =+' Qtr- 2 July-24 to Sept-24 (2)'!F43 -> 1930 | F18: =+' Qtr-3 Octo-24 to Dec-24'!F51 -> 4000 | G18: =+' Qtr-4 Jan-25 to march-25'!F46 -> 0 | H18: =SUM(D18:G18) -> 7920 | I18: =H18/C18 -> 0.99 | J18: =C18-H18 -> 80 | K18: =J18/C18 -> 0.01
A19: 1.4.2 | B19: Food for 35 participants form 7 project located villages each village 5 participants & 6 staff @ Rs.120 x 41 Person =Rs.3360 | C19: 19680 | D19: =+' Qtr-1 April-24 to June-24 '!F53 -> 4920 | E19: =+' Qtr- 2 July-24 to Sept-24 (2)'!F47 -> 4680 | F19: =+' Qtr-3 Octo-24 to Dec-24'!F55 -> 9360 | G19: =+' Qtr-4 Jan-25 to march-25'!F50 -> 0 | H19: =SUM(D19:G19) -> 18960 | I19: =H19/C19 -> 0.96341463 | J19: =C19-H19 -> 720 | K19: =J19/C19 -> 0.036585366
A20: 1.4.3 | B20: Project village to training venue transportation charges Rs.7500/- each village 5 participants x 7 Project villges 3 vehicles for 2 trainings | C20: 30000 | D20: =+' Qtr-1 April-24 to June-24 '!F57 -> 5000 | E20: =+' Qtr- 2 July-24 to Sept-24 (2)'!F51 -> 5000 | F20: =+' Qtr-3 Octo-24 to Dec-24'!F59 -> 10000 | G20: =+' Qtr-4 Jan-25 to march-25'!F54 -> 0 | H20: =SUM(D20:G20) -> 20000 | I20: =H20/C20 -> 0.66666667 | J20: =C20-H20 -> 10000 | K20: =J20/C20 -> 0.33333333
A21: 1.4.4 | B21: Arrangements & training matterials @ Rs.500/- | C21: 2000 | D21: =+' Qtr-1 April-24 to June-24 '!F61 -> 525 | E21: =+' Qtr- 2 July-24 to Sept-24 (2)'!F55 -> 525 | F21: =+' Qtr-3 Octo-24 to Dec-24'!F63 -> 990 | G21: =+' Qtr-4 Jan-25 to march-25'!F58 -> 0 | H21: =SUM(D21:G21) -> 2040 | I21: =H21/C21 -> 1.02 | J21: =C21-H21 -> -40 | K21: =J21/C21 -> -0.02
B22: Activities Sub Total 1.4 | C22: =SUM(C18:C21) -> 59680 | D22: =SUM(D18:D21) -> 12435 | E22: =SUM(E18:E21) -> 12135 | F22: =SUM(F18:F21) -> 24350 | G22: =SUM(G18:G21) -> 0 | H22: =SUM(H18:H21) -> 48920 | I22: =SUM(I18:I21) -> 3.6400813 | J22: =SUM(J18:J21) -> 10760 | K22: =J22/C22 -> 0.18029491 | L22: =SUM(L18:L21) -> 0
A23: 1.5 | B23: Pulses Seeds (Horse gram & Black gram) distribution
A24: 1.5.1 | B24: Pulses Seeds Distribution for 437 families Black Gram 1kg, Kulthi 1kg @Rs.212.86/- for 2 Kg x 437 families (Contribution Local labor charges@500 x 437 families) | C24: 157320 | D24: =+' Qtr-1 April-24 to June-24 '!F66 -> 0 | E24: =+' Qtr- 2 July-24 to Sept-24 (2)'!F60 -> 154754 | F24: =+' Qtr-3 Octo-24 to Dec-24'!F68 -> 3500 | G24: =+' Qtr-4 Jan-25 to march-25'!F63 -> 0 | H24: =SUM(D24:G24) -> 158254 | I24: =H24/C24 -> 1.0059369 | J24: =C24-H24 -> -934 | K24: =J24/C24 -> -0.0059369438
B25: Activities Sub Total 1.5 | C25: =C24 -> 157320 | D25: =D24 -> 0 | E25: =E24 -> 154754 | F25: =F24 -> 3500 | G25: =G24 -> 0 | H25: =H24 -> 158254 | I25: =I24 -> 1.0059369 | J25: =J24 -> -934 | K25: =J25/C25 -> -0.0059369438 | L25: =L24 -> 0
A26: 1.6 | B26: Exposure visit on adaption of improved new technology
A27: 1.6.1 | B27: Honorarium for resource person @Rs.2000 | C27: 0 | D27: =+' Qtr-1 April-24 to June-24 '!F69 -> 0 | E27: =+' Qtr- 2 July-24 to Sept-24 (2)'!F65 -> 0 | F27: =+' Qtr-3 Octo-24 to Dec-24'!F73 -> 0 | G27: =+' Qtr-4 Jan-25 to march-25'!F68 -> 0 | H27: =SUM(D27:G27) -> 0 | I27: =H27/C27 -> #DIV/0! | J27: =C27-H27 -> 0 | K27: =J27/C27 -> #DIV/0!
A28: 1.6.2 | B28: Food for 35 participants & 6 staff @ Rs.200 x 41 Person x 1 day = 8400/- | C28: 0 | D28: =+' Qtr-1 April-24 to June-24 '!F70 -> 0 | E28: =+' Qtr- 2 July-24 to Sept-24 (2)'!F68 -> 0 | F28: =+' Qtr-3 Octo-24 to Dec-24'!F76 -> 0 | G28: =+' Qtr-4 Jan-25 to march-25'!F71 -> 0 | H28: =SUM(D28:G28) -> 0 | I28: =H28/C28 -> #DIV/0! | J28: =C28-H28 -> 0 | K28: =J28/C28 -> #DIV/0!
A29: 1.6.3 | B29: Bus charges @ Rs.25000/- in Year -1 @ Rs. 26000/- x 2 bus in Year-2 and for Long distance place Exposure Visit in Yr-3 Bus Charges @Rs.35000/- | C29: 0 | D29: =+' Qtr-1 April-24 to June-24 '!F71 -> 0 | E29: =+' Qtr- 2 July-24 to Sept-24 (2)'!F71 -> 0 | F29: =+' Qtr-3 Octo-24 to Dec-24'!F79 -> 0 | G29: =+' Qtr-4 Jan-25 to march-25'!F75 -> 0 | H29: =SUM(D29:G29) -> 0 | I29: =H29/C29 -> #DIV/0! | J29: =C29-H29 -> 0 | K29: =J29/C29 -> #DIV/0!
A30: 1.6.4 | B30: First Aid medicine & other expenses @ Rs.500/- and Rs.1000/- | C30: 0 | D30: =+' Qtr-1 April-24 to June-24 '!F72 -> 0 | E30: =+' Qtr- 2 July-24 to Sept-24 (2)'!F74 -> 0 | F30: =+' Qtr-3 Octo-24 to Dec-24'!F82 -> 0 | G30: =+' Qtr-4 Jan-25 to march-25'!F79 -> 0 | H30: =SUM(D30:G30) -> 0 | I30: =H30/C30 -> #DIV/0! | J30: =C30-H30 -> 0 | K30: =J30/C30 -> #DIV/0!
B31: Activities Sub Total 1.6 | C31: =SUM(C27:C30) -> 0 | D31: =SUM(D27:D30) -> 0 | E31: =SUM(E27:E30) -> 0 | F31: =SUM(F27:F30) -> 0 | G31: =SUM(G27:G30) -> 0 | H31: =SUM(H27:H30) -> 0 | I31: =SUM(I27:I30) -> #DIV/0! | J31: =SUM(J27:J30) -> 0 | K31: =J31/C31 -> #DIV/0! | L31: =SUM(L27:L30) -> 0
B32: Activities Sub Total for Outcomes :1 | C32: =SUM(C31,C25,C22,C16,C10) -> 333400 | D32: =SUM(D31,D25,D22,D16,D10) -> 42380 | E32: =SUM(E31,E25,E22,E16,E10) -> 184469 | F32: =SUM(F31,F25,F22,F16,F10) -> 63605 | G32: =SUM(G31,G25,G22,G16,G10) -> 0 | H32: =SUM(H31,H25,H22,H16,H10) -> 290454 | I32: =SUM(I31,I25,I22,I16,I10) -> #DIV/0! | J32: =SUM(J31,J25,J22,J16,J10) -> 42946 | K32: =J32/C32 -> 0.12881224 | L32: =SUM(L31,L25,L22,L16,L10) -> 0
B33: Activities for Outcome :2
A34: 2.1 | B34: Training to the CBO’s (SHG) on topics a) Account book keeping, b) Record maintaining, c) Rules and Regulations, d) Responsibilities of the group leaders and members. e) Training on loan taking and refunding. f) Sack bag potatoes farming g) tuber crop farming i) Encourage to farming of Millet ( Mandia)
A35: 2.1.1 | B35: Honorarium , Travelling & food for Resource person @Rs.2000 | C35: 8000 | D35: =+' Qtr-1 April-24 to June-24 '!F80 -> 1990 | E35: =+' Qtr- 2 July-24 to Sept-24 (2)'!F82 -> 1930 | F35: =+' Qtr-3 Octo-24 to Dec-24'!F90 -> 1930 | G35: =+' Qtr-4 Jan-25 to march-25'!F87 -> 0 | H35: =SUM(D35:G35) -> 5850 | I35: =H35/C35 -> 0.73125 | J35: =C35-H35 -> 2150 | K35: =J35/C35 -> 0.26875
A36: 2.1.2 | B36: Food for 35 participants form 7 project located villages each village 5 participants & 6 staff @ Rs.120 x 42 Person =Rs.3360 | C36: 19680 | D36: =+' Qtr-1 April-24 to June-24 '!F84 -> 4920 | E36: =+' Qtr- 2 July-24 to Sept-24 (2)'!F86 -> 4440 | F36: =+' Qtr-3 Octo-24 to Dec-24'!F94 -> 4680 | G36: =+' Qtr-4 Jan-25 to march-25'!F91 -> 0 | H36: =SUM(D36:G36) -> 14040 | I36: =H36/C36 -> 0.71341463 | J36: =C36-H36 -> 5640 | K36: =J36/C36 -> 0.28658537
A37: 2.1.3 | B37: Project village to training venue transportation charges Rs.2500/- each village 5 participants x 7 Project villages, 2 vehicles | C37: 20000 | D37: =+' Qtr-1 April-24 to June-24 '!F88 -> 5000 | E37: =+' Qtr- 2 July-24 to Sept-24 (2)'!F90 -> 5000 | F37: =+' Qtr-3 Octo-24 to Dec-24'!F98 -> 5000 | G37: =+' Qtr-4 Jan-25 to march-25'!F95 -> 0 | H37: =SUM(D37:G37) -> 15000 | I37: =H37/C37 -> 0.75 | J37: =C37-H37 -> 5000 | K37: =J37/C37 -> 0.25
A38: 2.1.4 | B38: Arrangements & training materials @ Rs.500/- | C38: 2000 | D38: =+' Qtr-1 April-24 to June-24 '!F92 -> 525 | E38: =+' Qtr- 2 July-24 to Sept-24 (2)'!F94 -> 465 | F38: =+' Qtr-3 Octo-24 to Dec-24'!F102 -> 495 | G38: =+' Qtr-4 Jan-25 to march-25'!F99 -> 0 | H38: =SUM(D38:G38) -> 1485 | I38: =H38/C38 -> 0.7425 | J38: =C38-H38 -> 515 | K38: =J38/C38 -> 0.2575
B39: Activities Sub Total 2.1 | C39: =SUM(C35:C38) -> 49680 | D39: =SUM(D35:D38) -> 12435 | E39: =SUM(E35:E38) -> 11835 | F39: =SUM(F35:F38) -> 12105 | G39: =SUM(G35:G38) -> 0 | H39: =SUM(H35:H38) -> 36375 | I39: =SUM(I35:I38) -> 2.9371646 | J39: =SUM(J35:J38) -> 13305 | K39: =J39/C39 -> 0.26781401 | L39: =SUM(L35:L38) -> 0
A40: 2.2 | B40: Trainings on Alternate Livelihood Options: Poultry & Goat Rearing
A41: 2.2.1 | B41: Honorarium , travelling & food for resource person @Rs.2500 | C41: 5000 | D41: =+' Qtr-1 April-24 to June-24 '!F98 -> 0 | E41: =+' Qtr- 2 July-24 to Sept-24 (2)'!F100 -> 2440 | F41: =+' Qtr-3 Octo-24 to Dec-24'!F108 -> 0 | G41: =+' Qtr-4 Jan-25 to march-25'!F105 -> 0 | H41: =SUM(D41:G41) -> 2440 | I41: =H41/C41 -> 0.488 | J41: =C41-H41 -> 2560 | K41: =J41/C41 -> 0.512
A42: 2.2.2 | B42: Food for 35 participants form 7 project located villages each village 5 participants &6 staff @ Rs.120 x 41 Person =Rs.3360 | C42: 9840 | D42: =+' Qtr-1 April-24 to June-24 '!F102 -> 0 | E42: =+' Qtr- 2 July-24 to Sept-24 (2)'!F104 -> 4440 | F42: =+' Qtr-3 Octo-24 to Dec-24'!F112 -> 0 | G42: =+' Qtr-4 Jan-25 to march-25'!F109 -> 0 | H42: =SUM(D42:G42) -> 4440 | I42: =H42/C42 -> 0.45121951 | J42: =C42-H42 -> 5400 | K42: =J42/C42 -> 0.54878049
A43: 2.2.3 | B43: Project village to training venue transportation charges @Rs.2500/- 2 vehicles | C43: 10000 | D43: =+' Qtr-1 April-24 to June-24 '!F106 -> 0 | E43: =+' Qtr- 2 July-24 to Sept-24 (2)'!F108 -> 5000 | F43: =+' Qtr-3 Octo-24 to Dec-24'!F116 -> 0 | G43: =+' Qtr-4 Jan-25 to march-25'!F113 -> 0 | H43: =SUM(D43:G43) -> 5000 | I43: =H43/C43 -> 0.5 | J43: =C43-H43 -> 5000 | K43: =J43/C43 -> 0.5
A44: 2.2.4 | B44: Arrangements & training materials @ Rs.500/- | C44: 1000 | D44: =+' Qtr-1 April-24 to June-24 '!F110 -> 0 | E44: =+' Qtr- 2 July-24 to Sept-24 (2)'!F112 -> 527 | F44: =+' Qtr-3 Octo-24 to Dec-24'!F120 -> 0 | G44: =+' Qtr-4 Jan-25 to march-25'!F117 -> 0 | H44: =SUM(D44:G44) -> 527 | I44: =H44/C44 -> 0.527 | J44: =C44-H44 -> 473 | K44: =J44/C44 -> 0.473
B45: Activities Sub Total 2.2 | C45: =SUM(C41:C44) -> 25840 | D45: =SUM(D41:D44) -> 0 | E45: =SUM(E41:E44) -> 12407 | F45: =SUM(F41:F44) -> 0 | G45: =SUM(G41:G44) -> 0 | H45: =SUM(H41:H44) -> 12407 | I45: =SUM(I41:I44) -> 1.9662195 | J45: =SUM(J41:J44) -> 13433 | K45: =J45/C45 -> 0.51985294 | L45: =SUM(L41:L44) -> 0
A46: 2.3 | B46: Training on primary treatments and Vaccination for the domestic animals
A47: 2.3.1 | B47: Honorarium , travelling & food for resource person @Rs.2500 | C47: 5000 | D47: =+' Qtr-1 April-24 to June-24 '!F116 -> 0 | E47: =+' Qtr- 2 July-24 to Sept-24 (2)'!F118 -> 2460 | F47: =+' Qtr-3 Octo-24 to Dec-24'!F126 -> 0 | G47: =+' Qtr-4 Jan-25 to march-25'!F123 -> 0 | H47: =SUM(D47:G47) -> 2460 | I47: =H47/C47 -> 0.492 | J47: =C47-H47 -> 2540 | K47: =J47/C47 -> 0.508
A48: 2.3.2 | B48: Food for 21 participants form 7 project located villages each village 3 participants & 6 staff @ Rs.120 x 21 Person =Rs.1680/- | C48: 6480 | D48: =+' Qtr-1 April-24 to June-24 '!F120 -> 0 | E48: =+' Qtr- 2 July-24 to Sept-24 (2)'!F122 -> 3120 | F48: =+' Qtr-3 Octo-24 to Dec-24'!F130 -> 0 | G48: =+' Qtr-4 Jan-25 to march-25'!F127 -> 0 | H48: =SUM(D48:G48) -> 3120 | I48: =H48/C48 -> 0.48148148 | J48: =C48-H48 -> 3360 | K48: =J48/C48 -> 0.51851852
A49: 2.3.3 | B49: Project village to training venue transportation charges Rs.2500/- each village 2 participants x 7 Project villages 2 vehicles | C49: 10000 | D49: =+' Qtr-1 April-24 to June-24 '!F124 -> 0 | E49: =+' Qtr- 2 July-24 to Sept-24 (2)'!F126 -> 5000 | F49: =+' Qtr-3 Octo-24 to Dec-24'!F134 -> 0 | G49: =+' Qtr-4 Jan-25 to march-25'!F131 -> 0 | H49: =SUM(D49:G49) -> 5000 | I49: =H49/C49 -> 0.5 | J49: =C49-H49 -> 5000 | K49: =J49/C49 -> 0.5
A50: 2.3.4 | B50: Arrangements & training matterials @ Rs.500/- | C50: 1000 | D50: =+' Qtr-1 April-24 to June-24 '!F129 -> 0 | E50: =+' Qtr- 2 July-24 to Sept-24 (2)'!F130 -> 400 | F50: =+' Qtr-3 Octo-24 to Dec-24'!F139 -> 0 | G50: =+' Qtr-4 Jan-25 to march-25'!F136 -> 0 | H50: =SUM(D50:G50) -> 400 | I50: =H50/C50 -> 0.4 | J50: =C50-H50 -> 600 | K50: =J50/C50 -> 0.6
B51: Activities Sub Total 2.3 | C51: =SUM(C47:C50) -> 22480 | D51: =SUM(D47:D50) -> 0 | E51: =SUM(E47:E50) -> 10980 | F51: =SUM(F47:F50) -> 0 | G51: =SUM(G47:G50) -> 0 | H51: =SUM(H47:H50) -> 10980 | I51: =SUM(I47:I50) -> 1.8734815 | J51: =SUM(J47:J50) -> 11500 | K51: =J51/C51 -> 0.51156584 | L51: =SUM(L47:L50) -> 0
A52: 2.4 | B52: Need based training on Income Generation activity like fish cultivation
A53: 2.4.1 | B53: Honorarium , travelling & food for resource person @Rs.2500 | C53: 5000 | D53: =+' Qtr-1 April-24 to June-24 '!F135 -> 2480 | E53: =+' Qtr- 2 July-24 to Sept-24 (2)'!F135 -> 0 | F53: =+' Qtr-3 Octo-24 to Dec-24'!F145 -> 2440 | G53: =+' Qtr-4 Jan-25 to march-25'!F142 -> 0 | H53: =SUM(D53:G53) -> 4920 | I53: =H53/C53 -> 0.984 | J53: =C53-H53 -> 80 | K53: =J53/C53 -> 0.016
A54: 2.4.2 | B54: Food for 35 participants & 6 staff @ Rs.120 x 41 Person | C54: 9840 | D54: =+' Qtr-1 April-24 to June-24 '!F139 -> 4680 | E54: =+' Qtr- 2 July-24 to Sept-24 (2)'!F138 -> 0 | F54: =+' Qtr-3 Octo-24 to Dec-24'!F149 -> 4920 | G54: =+' Qtr-4 Jan-25 to march-25'!F146 -> 0 | H54: =SUM(D54:G54) -> 9600 | I54: =H54/C54 -> 0.97560976 | J54: =C54-H54 -> 240 | K54: =J54/C54 -> 0.024390244
A55: 2.4.3 | B55: Project village to training venue transportation charges Rs.2500/- 2 vehicles | C55: 10000 | D55: =+' Qtr-1 April-24 to June-24 '!F143 -> 0 | E55: =+' Qtr- 2 July-24 to Sept-24 (2)'!F142 -> 5000 | F55: =+' Qtr-3 Octo-24 to Dec-24'!F153 -> 5000 | G55: =+' Qtr-4 Jan-25 to march-25'!F150 -> 0 | H55: =SUM(D55:G55) -> 10000 | I55: =H55/C55 -> 1 | J55: =C55-H55 -> 0 | K55: =J55/C55 -> 0
A56: 2.4.4 | B56: Arrangements & training matterials @ Rs.500/- | C56: 1000 | D56: =+' Qtr-1 April-24 to June-24 '!F146 -> 495 | E56: =+' Qtr- 2 July-24 to Sept-24 (2)'!F145 -> 0 | F56: =+' Qtr-3 Octo-24 to Dec-24'!F156 -> 525 | G56: =+' Qtr-4 Jan-25 to march-25'!F153 -> 0 | H56: =SUM(D56:G56) -> 1020 | I56: =H56/C56 -> 1.02 | J56: =C56-H56 -> -20 | K56: =J56/C56 -> -0.02
B57: Activities Sub Total 2.4 | C57: =SUM(C53:C56) -> 25840 | D57: =SUM(D53:D56) -> 7655 | E57: =SUM(E53:E56) -> 5000 | F57: =SUM(F53:F56) -> 12885 | G57: =SUM(G53:G56) -> 0 | H57: =SUM(H53:H56) -> 25540 | I57: =SUM(I53:I56) -> 3.9796098 | J57: =SUM(J53:J56) -> 300 | K57: =J57/C57 -> 0.011609907 | L57: =SUM(L53:L56) -> 0
A58: 2.5 | B58: Training on Nutritional Kitchen garden and commercial vegetable gardening a) Fruits b) Vegetable
A59: 2.5.1 | B59: Resource person travelling and honorarium charges for Year-1 only and then Project staff will conduct it | C59: 0 | D59: =+' Qtr-1 April-24 to June-24 '!F152 -> 0 | E59: =+' Qtr- 2 July-24 to Sept-24 (2)'!F150 -> 0 | F59: =+' Qtr-3 Octo-24 to Dec-24'!F162 -> 0 | G59: =+' Qtr-4 Jan-25 to march-25'!F159 -> 0 | H59: =SUM(D59:G59) -> 0 | I59: =H59/C59 -> #DIV/0! | J59: =C59-H59 -> 0 | K59: =J59/C59 -> #DIV/0!
A60: 2.5.2 | B60: Food for 35 participants form 7 project located villages each village 5 participants & 6 staff @ Rs.120 x 41 Person | C60: 14760 | D60: =+' Qtr-1 April-24 to June-24 '!F156 -> 4920 | E60: =+' Qtr- 2 July-24 to Sept-24 (2)'!F153 -> 0 | F60: =+' Qtr-3 Octo-24 to Dec-24'!F166 -> 9240 | G60: =+' Qtr-4 Jan-25 to march-25'!F163 -> 0 | H60: =SUM(D60:G60) -> 14160 | I60: =H60/C60 -> 0.95934959 | J60: =C60-H60 -> 600 | K60: =J60/C60 -> 0.040650407
A61: 2.5.3 | B61: Project village to training venue transportaion charges Rs.2500, 2 Vehicles x2 trainings | C61: 15000 | D61: =+' Qtr-1 April-24 to June-24 '!F160 -> 5000 | E61: =+' Qtr- 2 July-24 to Sept-24 (2)'!F156 -> 0 | F61: =+' Qtr-3 Octo-24 to Dec-24'!F170 -> 10000 | G61: =+' Qtr-4 Jan-25 to march-25'!F167 -> 0 | H61: =SUM(D61:G61) -> 15000 | I61: =H61/C61 -> 1 | J61: =C61-H61 -> 0 | K61: =J61/C61 -> 0
A62: 2.5.4 | B62: Arrangements & training matterials @ Rs.500/- Year-3 @Rs.400/- | C62: 1500 | D62: =+' Qtr-1 April-24 to June-24 '!F163 -> 525 | E62: =+' Qtr- 2 July-24 to Sept-24 (2)'!F159 -> 0 | F62: =+' Qtr-3 Octo-24 to Dec-24'!F174 -> 990 | G62: =+' Qtr-4 Jan-25 to march-25'!F170 -> 0 | H62: =SUM(D62:G62) -> 1515 | I62: =H62/C62 -> 1.01 | J62: =C62-H62 -> -15 | K62: =J62/C62 -> -0.01
B63: Activities Sub Total 2.5 | C63: =SUM(C59:C62) -> 31260 | D63: =SUM(D59:D62) -> 10445 | E63: =SUM(E59:E62) -> 0 | F63: =SUM(F59:F62) -> 20230 | G63: =SUM(G59:G62) -> 0 | H63: =SUM(H59:H62) -> 30675 | I63: =SUM(I59:I62) -> #DIV/0! | J63: =SUM(J59:J62) -> 585 | K63: =J63/C63 -> 0.018714012 | L63: =SUM(L59:L62) -> 0
A64: 2.6 | B64: Vaccination and medication to the domestic animals
A65: 2.6.1 | B65: Vet visit 6 times in a year @ 1200 per visit | C65: 7200 | D65: =+' Qtr-1 April-24 to June-24 '!F170 -> 0 | E65: =+' Qtr- 2 July-24 to Sept-24 (2)'!F165 -> 3600 | F65: =+' Qtr-3 Octo-24 to Dec-24'!F181 -> 0 | G65: =+' Qtr-4 Jan-25 to march-25'!F177 -> 0 | H65: =SUM(D65:G65) -> 3600 | I65: =H65/C65 -> 0.5 | J65: =C65-H65 -> 3600 | K65: =J65/C65 -> 0.5
A66: 2.6.2 | B66: Vaccination & medication to the domestic animals medicens avarage expenses each hhs @ 200/- x 437, twice in a year | C66: 174800 | D66: =+' Qtr-1 April-24 to June-24 '!F175 -> 0 | E66: =+' Qtr- 2 July-24 to Sept-24 (2)'!F169 -> 87399 | F66: =+' Qtr-3 Octo-24 to Dec-24'!F186 -> 0 | G66: =+' Qtr-4 Jan-25 to march-25'!F182 -> 0 | H66: =SUM(D66:G66) -> 87399 | I66: =H66/C66 -> 0.49999428 | J66: =C66-H66 -> 87401 | K66: =J66/C66 -> 0.50000572
B67: Activities Sub Total 2.6 | C67: =SUM(C65:C66) -> 182000 | D67: =SUM(D65:D66) -> 0 | E67: =SUM(E65:E66) -> 90999 | F67: =SUM(F65:F66) -> 0 | G67: =SUM(G65:G66) -> 0 | H67: =SUM(H65:H66) -> 90999 | I67: =SUM(I65:I66) -> 0.99999428 | J67: =SUM(J65:J66) -> 91001 | K67: =J67/C67 -> 0.50000549 | L67: =SUM(L65:L66) -> 0
A68: 2.7 | B68: Distribution of goats
A69: 2.7.1 | B69: Goat distribution @Rs.4500 x 62 No. of farmers (each farmer 1 goat) from 7 Targeted villages (Contribution by participants for goats shed making @Rs.2000 x 62 families) | C69: 0 | D69: =+' Qtr-1 April-24 to June-24 '!F184 -> 0 | E69: =+' Qtr- 2 July-24 to Sept-24 (2)'!F174 -> 0 | F69: =+' Qtr-3 Octo-24 to Dec-24'!F195 -> 0 | G69: =+' Qtr-4 Jan-25 to march-25'!F191 -> 0 | H69: =SUM(D69:G69) -> 0 | I69: =H69/C69 -> #DIV/0! | J69: =C69-H69 -> 0 | K69: =J69/C69 -> #DIV/0!
A70: 2.7.2 | B70: Goats transpotation cost @ Rs.5250/- | C70: 0 | D70: =+' Qtr-1 April-24 to June-24 '!F190 -> 0 | E70: =+' Qtr- 2 July-24 to Sept-24 (2)'!F177 -> 0 | F70: =+' Qtr-3 Octo-24 to Dec-24'!F201 -> 0 | G70: =+' Qtr-4 Jan-25 to march-25'!F197 -> 0 | H70: =SUM(D70:G70) -> 0 | I70: =H70/C70 -> #DIV/0! | J70: =C70-H70 -> 0 | K70: =J70/C70 -> #DIV/0!
B71: Activities Sub Total 2.7 | C71: =SUM(C69:C70) -> 0 | D71: =SUM(D69:D70) -> 0 | E71: =SUM(E69:E70) -> 0 | F71: =SUM(F69:F70) -> 0 | G71: =SUM(G69:G70) -> 0 | H71: =SUM(H69:H70) -> 0 | I71: =SUM(I69:I70) -> #DIV/0! | J71: =SUM(J69:J70) -> 0 | K71: =J71/C71 -> #DIV/0! | L71: =SUM(L69:L70) -> 0
A72: 2.8 | B72: Training on Minor Millet farming
A73: 2.8.1 | B73: Millet (Mandia) seeds distribution to the 20 farmers for doing of cultivation @ Rs.50 x 1.5 kg x 30 farmer ( Contribution fencing and labor charges Rs.200 x 30 = Rs.6000) | C73: 4800 | D73: =+' Qtr-1 April-24 to June-24 '!F196 -> 4800 | E73: =+' Qtr- 2 July-24 to Sept-24 (2)'!F182 -> 0 | F73: =+' Qtr-3 Octo-24 to Dec-24'!F207 -> 0 | G73: =+' Qtr-4 Jan-25 to march-25'!F203 -> 0 | H73: =SUM(D73:G73) -> 4800 | I73: =H73/C73 -> 1 | J73: =C73-H73 -> 0 | K73: =J73/C73 -> 0
A74: 2.8.2 | B74: Millet (Mandia) transpotation cost @ 1500/- | C74: 1500 | D74: =+' Qtr-1 April-24 to June-24 '!F202 -> 0 | E74: =+' Qtr- 2 July-24 to Sept-24 (2)'!F185 -> 0 | F74: =+' Qtr-3 Octo-24 to Dec-24'!F213 -> 0 | G74: =+' Qtr-4 Jan-25 to march-25'!F209 -> 0 | H74: =SUM(D74:G74) -> 0 | I74: =H74/C74 -> 0 | J74: =C74-H74 -> 1500 | K74: =J74/C74 -> 1
B75: Activities Sub Total 2.8 | C75: =SUM(C73:C74) -> 6300 | D75: =SUM(D73:D74) -> 4800 | E75: =SUM(E73:E74) -> 0 | F75: =SUM(F73:F74) -> 0 | G75: =SUM(G73:G74) -> 0 | H75: =SUM(H73:H74) -> 4800 | I75: =SUM(I73:I74) -> 1 | J75: =SUM(J73:J74) -> 1500 | K75: =J75/C75 -> 0.23809524 | L75: =SUM(L73:L74) -> 0
A76: 2.9 | B76: Distribution of small Petty business materials
A77: 2.9.1 | B77: Selected people will be distributed the business materials as per their choice | C77: 0 | D77: =+' Qtr-1 April-24 to June-24 '!F207 -> 0 | E77: =+' Qtr- 2 July-24 to Sept-24 (2)'!F190 -> 0 | F77: =+' Qtr-3 Octo-24 to Dec-24'!F218 -> 0 | G77: =+' Qtr-4 Jan-25 to march-25'!F214 -> 0 | H77: =SUM(D77:G77) -> 0 | I77: =H77/C77 -> #DIV/0! | J77: =C77-H77 -> 0 | K77: =J77/C77 -> #DIV/0!
B78: Activities Sub Total 2.10 | C78: =C77 -> 0 | D78: =D77 -> 0 | E78: =E77 -> 0 | F78: =F77 -> 0 | G78: =G77 -> 0 | H78: =H77 -> 0 | I78: =I77 -> #DIV/0! | J78: =J77 -> 0 | K78: =J78/C78 -> #DIV/0! | L78: =L77 -> 0
A79: 2.1 | B79: Vegetable seeds distribution for Kitchen gardening
A80: 2.10.1 | B80: Vegetable Seeds support (Contribution fencing and labor charges @250 x 437 families) | C80: 0 | D80: =+' Qtr-1 April-24 to June-24 '!F212 -> 0 | E80: =+' Qtr- 2 July-24 to Sept-24 (2)'!F195 -> 0 | F80: =+' Qtr-3 Octo-24 to Dec-24'!F223 -> 0 | G80: =+' Qtr-4 Jan-25 to march-25'!F219 -> 0 | H80: =SUM(D80:G80) -> 0 | I80: =H80/C80 -> #DIV/0! | J80: =C80-H80 -> 0 | K80: =J80/C80 -> #DIV/0!
A81: 2.10.2 | B81: Seeds transpotation cost @ 1000/- | C81: 0 | D81: =+' Qtr-1 April-24 to June-24 '!F215 -> 0 | E81: =+' Qtr- 2 July-24 to Sept-24 (2)'!F198 -> 0 | F81: =+' Qtr-3 Octo-24 to Dec-24'!F226 -> 0 | G81: =+' Qtr-4 Jan-25 to march-25'!F222 -> 0 | H81: =SUM(D81:G81) -> 0 | I81: =H81/C81 -> #DIV/0! | J81: =C81-H81 -> 0 | K81: =J81/C81 -> #DIV/0!
B82: Activities Sub Total 2.10 | C82: =SUM(C80:C81) -> 0 | D82: =SUM(D80:D81) -> 0 | E82: =SUM(E80:E81) -> 0 | F82: =SUM(F80:F81) -> 0 | G82: =SUM(G80:G81) -> 0 | H82: =SUM(H80:H81) -> 0 | I82: =SUM(I80:I81) -> #DIV/0! | J82: =SUM(J80:J81) -> 0 | K82: =J82/C82 -> #DIV/0! | L82: =SUM(L80:L81) -> 0
A83: 2.11 | B83: Distribution of earthen pot for micro water harvest and use it in the kitchen garden
A84: 2.11.1 | B84: Promote 437 hh to do homestead kitchen garden and will be provided a mud water pot for harvesting of west water @ Rs 120 (437 hh contribute their own labor & fencing it for making kitchen garden @ Rs.250 x 1 days x 437 hh = Rs109250/- | C84: 0 | D84: =+' Qtr-1 April-24 to June-24 '!F218 -> 0 | E84: =+' Qtr- 2 July-24 to Sept-24 (2)'!F203 -> 0 | F84: =+' Qtr-3 Octo-24 to Dec-24'!F231 -> 0 | G84: =+' Qtr-4 Jan-25 to march-25'!F227 -> 0 | H84: =SUM(D84:G84) -> 0
A85: 2.11.2 | B85: Mud pot purchasing and transpotation cost @ Rs.3000/- | C85: 0 | D85: =+' Qtr-1 April-24 to June-24 '!F219 -> 0 | E85: =+' Qtr- 2 July-24 to Sept-24 (2)'!F206 -> 0 | F85: =+' Qtr-3 Octo-24 to Dec-24'!F234 -> 0 | G85: =+' Qtr-4 Jan-25 to march-25'!F230 -> 0 | H85: =SUM(D85:G85) -> 0
B86: Activities Sub Total 2.11 | C86: =SUM(C84:C85) -> 0 | D86: =SUM(D84:D85) -> 0 | E86: =SUM(E84:E85) -> 0 | F86: =SUM(F84:F85) -> 0 | G86: =SUM(G84:G85) -> 0 | H86: =SUM(H84:H85) -> 0 | I86: =SUM(I84:I85) -> 0 | J86: =SUM(J84:J85) -> 0 | L86: =SUM(L84:L85) -> 0
A87: 2.12 | B87: Distribution of fish seeds for fish Cultivation
A88: 2.12.1 | B88: Fish seeds distribution to pond holder farmers for doing of fish cultivation @ Rs.2000/- x 35 person = Rs.70000/- | D88: =+' Qtr-1 April-24 to June-24 '!F223 -> 0 | E88: =+' Qtr- 2 July-24 to Sept-24 (2)'!F210 -> 0 | F88: =+' Qtr-3 Octo-24 to Dec-24'!F239 -> 0 | G88: =+' Qtr-4 Jan-25 to march-25'!F233 -> 0 | H88: =SUM(D88:G88) -> 0
B89: Activities Sub Total 2.12 | C89: =C88 -> 0 | D89: =D88 -> 0 | E89: =E88 -> 0 | F89: =F88 -> 0 | G89: =G88 -> 0 | H89: =H88 -> 0 | I89: =I88 -> 0 | J89: =J88 -> 0 | L89: =L88 -> 0
B90: Activities Sub Total for Outcomes :2 | C90: =SUM(C89,C86,C82,C78,C75,C71,C67,C63,C57,C51,C45,C39) -> 343400 | D90: =SUM(D89,D86,D82,D78,D75,D71,D67,D63,D57,D51,D45,D39) -> 35335 | E90: =SUM(E89,E86,E82,E78,E75,E71,E67,E63,E57,E51,E45,E39) -> 131221 | F90: =SUM(F89,F86,F82,F78,F75,F71,F67,F63,F57,F51,F45,F39) -> 45220 | G90: =SUM(G89,G86,G82,G78,G75,G71,G67,G63,G57,G51,G45,G39) -> 0 | H90: =SUM(H89,H86,H82,H78,H75,H71,H67,H63,H57,H51,H45,H39) -> 211776 | I90: =SUM(I89,I86,I82,I78,I75,I71,I67,I63,I57,I51,I45,I39) -> #DIV/0! | J90: =SUM(J89,J86,J82,J78,J75,J71,J67,J63,J57,J51,J45,J39) -> 131624 | K90: =J90/C90 -> 0.38329645 | L90: =SUM(L89,L86,L82,L78,L75,L71,L67,L63,L57,L51,L45,L39) -> 0
B91: Activities for Outcome :3
A92: 3.1 | B92: Training of on Govt. programs, Schemes related to food, livelihood and social security schemes etc.
A93: 3.1.1 | B93: Honorarium , travel & food for resource person @Rs.2500 | C93: 5000 | D93: =+' Qtr-1 April-24 to June-24 '!F232 -> 2490 | E93: =+' Qtr- 2 July-24 to Sept-24 (2)'!F216 -> 0 | F93: =+' Qtr-3 Octo-24 to Dec-24'!F249 -> 0 | G93: =+' Qtr-4 Jan-25 to march-25'!F243 -> 0 | H93: =SUM(D93:G93) -> 2490 | I93: =H93/C93 -> 0.498 | J93: =C93-H93 -> 2510 | K93: =J93/C93 -> 0.502
A94: 3.1.2 | B94: Food for 35 participants | C94: 7000 | D94: =+' Qtr-1 April-24 to June-24 '!F237 -> 4920 | E94: =+' Qtr- 2 July-24 to Sept-24 (2)'!F219 -> 0 | F94: =+' Qtr-3 Octo-24 to Dec-24'!F254 -> 0 | G94: =+' Qtr-4 Jan-25 to march-25'!F248 -> 0 | H94: =SUM(D94:G94) -> 4920 | I94: =H94/C94 -> 0.70285714 | J94: =C94-H94 -> 2080 | K94: =J94/C94 -> 0.29714286
A95: 3.1.3 | B95: Project village to transportaion charges Rs.2500/- each village 5 participants and 6 staff, 3 vehicles | C95: 15000 | D95: =+' Qtr-1 April-24 to June-24 '!F244 -> 5000 | E95: =+' Qtr- 2 July-24 to Sept-24 (2)'!F222 -> 0 | F95: =+' Qtr-3 Octo-24 to Dec-24'!F261 -> 0 | G95: =+' Qtr-4 Jan-25 to march-25'!F255 -> 0 | H95: =SUM(D95:G95) -> 5000 | I95: =H95/C95 -> 0.33333333 | J95: =C95-H95 -> 10000 | K95: =J95/C95 -> 0.66666667
A96: 3.1.4 | B96: Arrangements & training matterials @ Rs.1000/- | C96: 2000 | D96: =+' Qtr-1 April-24 to June-24 '!F250 -> 1015 | E96: =+' Qtr- 2 July-24 to Sept-24 (2)'!F225 -> 0 | F96: =+' Qtr-3 Octo-24 to Dec-24'!F267 -> 0 | G96: =+' Qtr-4 Jan-25 to march-25'!F261 -> 0 | H96: =SUM(D96:G96) -> 1015 | I96: =H96/C96 -> 0.5075 | J96: =C96-H96 -> 985 | K96: =J96/C96 -> 0.4925
B97: Activities Sub Total 3.1 | C97: =SUM(C93:C96) -> 29000 | D97: =SUM(D93:D96) -> 13425 | E97: =SUM(E93:E96) -> 0 | F97: =SUM(F93:F96) -> 0 | G97: =SUM(G93:G96) -> 0 | H97: =SUM(H93:H96) -> 13425 | I97: =SUM(I93:I96) -> 2.0416905 | J97: =SUM(J93:J96) -> 15575 | K97: =J97/C97 -> 0.53706897 | L97: =SUM(L93:L96) -> 0
A98: 3.2 | B98: Liaisioning with government offices
A99: 3.2.1 | B99: Transportation and food cost of community leaders to follow up on Lift Irrigation schemes | C99: 24000 | D99: =+' Qtr-1 April-24 to June-24 '!F258 -> 0 | E99: =+' Qtr- 2 July-24 to Sept-24 (2)'!F230 -> 0 | F99: =+' Qtr-3 Octo-24 to Dec-24'!F275 -> 11990 | G99: =+' Qtr-4 Jan-25 to march-25'!F269 -> 0 | H99: =SUM(D99:G99) -> 11990 | I99: =H99/C99 -> 0.49958333 | J99: =C99-H99 -> 12010 | K99: =J99/C99 -> 0.50041667
A100: 3.2.2 | B100: Documents and other expenses | C100: 4000 | D100: =+' Qtr-1 April-24 to June-24 '!F263 -> 0 | E100: =+' Qtr- 2 July-24 to Sept-24 (2)'!F233 -> 0 | F100: =+' Qtr-3 Octo-24 to Dec-24'!F280 -> 0 | G100: =+' Qtr-4 Jan-25 to march-25'!F274 -> 0 | H100: =SUM(D100:G100) -> 0 | I100: =H100/C100 -> 0 | J100: =C100-H100 -> 4000 | K100: =J100/C100 -> 1
...

Sheet  Qtr-1 April-24 to June-24 
B1: Partner: DAPTA (Development Agency for Poor and Tribal Awakening)
A2: Quarterly/Monthly Reporting Format
A3: Ensuring food and livelihood security of indigenous and other marginalized communities in Thakurmunda Block, Mayurbhanj, Odisha
D4: Accounting Period: | E4: Start: 1 April 2024
E5: End: 30 June 2024
A6: Date: Grant received on | D6: 02.05.2024 | E6: Total Annual MCC Budget: | H6: Rs. 26,75,000/-
A7: Opening Balance : on 1 April 2024 Cash in Hand | D7: 67601.6
A8: Cash in Bank | D8: 0
A9: Total Balance available on 1. April 2024 | D9: =D7+D8 -> 67601.6
B10: Bank interest earned | D10: 2150
A11: Grant Received from MCC for Qtr-1 2024-25: | D11: 577475 | E11: NOTE: Please add more rows if needed but make sure that the value is added to the fomula
A12: Total Balance available | D12: =SUM(D9:D11) -> 647226.6
A13: Budget ID | B13: Vendor/Expense Description | C13: MCC Approved budget-Yr-2 | D13: Quarterly Budgeted Amount Qtr-1 2024 | E13: Date | F13: Expense Amt | G13: Voucher or receipt number | H13: Budgeted Amt less Expense Amount | I13: Partner / Farmer Contribution
A14: 1 | B14: Outcome :1 Activities
A15: 1.1 | B15: Baseline | C15: 0
B17: Total 1.1 | D17: 0 | F17: =SUM(F16:F16) -> 0 | H17: =D17-F17 -> 0 | I17: =SUM(I16:I16) -> 0
A18: 1.2 | B18: Monthly PRA/ Data collection/ Village Community Meeting
A19: 1.2.1 | B19: Monthly Village Community Meeting (Biscuits / Snacks /per time /12 Months) @Rs.15 x 437 + 6 staff =Rs.6660/- | C19: 79920
B20: Being the amount paid to Jyotshnarani Pradhan prop. of New Family Bazar,Thakurmunda through NEFT Chq. No.046885 towards purchased of Biscuits for participants of 06nos Monthly village community Meeting month of April-2024. Vide Bill No.89 dtd. 04.04.2024 | E20: 09.05.2024 | F20: 6555 | G20: P.V No. 07
B21: Being the amount paid to Jyotshnarani Pradhan prop. of New Family Bazar,Thakurmunda through NEFT Chq. No.046897 towards purchased of Biscuits for participants of 06nos Monthly village community Meeting month of May-2024. Vide Bill No.157 dtd.15.05.2024 | E21: 11.06.2024 | F21: 6300 | G21: P.V No. 28
B22: Being the amount paid to Jyotshnarani Pradhan prop. of New Family Bazar,Thakurmunda through NEFT Chq. No.046907 towards purchased of Biscuits for participants of 06nos Monthly village community Meeting month of June-2024. Vide Bill No.124 dtd.04.06.2024 | E22: 29.06.2024 | F22: 6510 | G22: P.V No. 42
B23: Total 1.2.1 | D23: 19980 | F23: =SUM(F20:F22) -> 19365 | H23: =D23-F23 -> 615 | I23: =SUM(I20:I22) -> 0
B24: Activities Sub Total 1.2 | C24: =SUM(C15,C19) -> 79920 | D24: =D23+D17 -> 19980 | F24: =SUM(F23) -> 19365 | H24: =D24-F24 -> 615 | I24: =SUM(I23) -> 0
A25: 1.3 | B25: Training on Improved agriculture methods and Technology :- a) SRI (Paddy farming in row) b) Multi cropping c) Crop diversification d) Crop rotation e) Azola growing f) Seed preservation g) Seed treatment
A26: 1.3.1 | B26: Honorarium , travelling & food for resource person @Rs.2000 (above mentioned some subject will be conducted by the Project staff) | C26: 2000
B27: Being the amount paid to Jagannath Sahu through NEFT Chq. No.046890 towards Resouce person honorarium with travel for Training on improved agriculture methods and Technology. on dtd.24.05.2024 held at.DAPTA Office ,Thakurmunda. | E27: 31.05.2024 | F27: 1750 | G27: P.V No.18
B28: Being the amount paid to Narayan Barik Prop. Of Hotel Swagatika through NEFT Chq. No.046891 towards supply of Food for RP on Training on improved agriculture methods and Technology. on dtd.24.05.2024 held at.DAPTA Office ,Thakurmunda. Vide Bill No.1581 dtd.24.05.2024 | E28: 31.05.2024 | F28: 210 | G28: P.v No. 24
B30: Total 1.3.1 | D30: 2000 | F30: =SUM(F27:F29) -> 1960 | H30: =D30-F30 -> 40 | I30: =SUM(I27:I29) -> 0
A31: 1.3.2 | B31: Food for 20 participants & 6 staff @ Rs.120 x 26 Person | C31: 12480
B32: Being the amount paid to Narayan Barik Prop. Of Hotel Swagatika through NEFT Chq. No.046891 towards supply of Food for Participants on Training on Improved agriculture methods and Technology on dtd.24.05.24. Vide bill No.1582 dtd.24.05.2024 | E32: 31.05.2024 | F32: 3120 | G32: P.V No.22
B35: Total 1.3.2 | D35: 3120 | F35: =SUM(F32:F34) -> 3120 | H35: =D35-F35 -> 0 | I35: =SUM(I32:I34) -> 0
A36: 1.3.3 | B36: Project village to training venue Transportation charges 20 participants x 1 Project villages @ Rs.2500/-; 2 vehicles | C36: 20000
B37: Being the amount paid to Ramasingh Badra,Prop. of Badra Tour & Travel through NEFT Chq. No.046890 towards hiring of 2no of vehicle for participants transportation on Training on Improved agriculture methods and Technology on dtd.24.05.24 held at.DAPTA,Thakurmunda Vide Bill No.92, 93 dtd.24.05.2024 | E37: 31.05.2024 | F37: 5000 | G37: P.V. No.20
B39: Total 1.3.3 | D39: 5000 | F39: =SUM(F37:F38) -> 5000 | H39: =D39-F39 -> 0 | I39: =SUM(I37:I38) -> 0
A40: 1.3.4 | B40: Arrangements & training matterials @ Rs.500/- | C40: 2000
B41: Being the amount paid to Baigyanik Mohanta, Prop. of Gayatree Book Store through NEFT Chq. No.046891 towards Training Materials for Participants on Training on Improved agriculture methods and Technology on dtd.24.05.24 held at.DAPTA,Thakurmunda Vide Bill No.219 dtd.24.05.2024 | E41: 31.05.2024 | F41: 500 | G41: P.V No.23
B43: Total 1.3.4 | D43: 500 | F43: =SUM(F41:F42) -> 500 | H43: =D43-F43 -> 0 | I43: =SUM(I41:I42) -> 0
B44: Activities Sub Total 1.3 | C44: =SUM(C26:C40) -> 36480 | D44: =SUM(D43,D39,D35,D30) -> 10620 | F44: =SUM(F43,F39,F35,F30) -> 10580 | H44: =D44-F44 -> 40 | I44: =SUM(I43,I39,I35,I30) -> 0
A45: 1.4 | B45: Training on Natural Resource Management a) Soil health ( Testing, treatment and preservation) b) Organic farming (Chemical free) c) Compost pit & its preparation d) Vermin compost making e) Bio- Pesticide f) Bio- fertilizer
A46: 1.4.1 | B46: Honorarium, travelling & food for resource person @Rs.2000 | C46: 8000
B47: Being the amount paid to Narayan Barik Prop. Of Hotel Swagatikathrough NEFT Chq. no.046887 towards resource person food cost for Training on natural resouce managment dtd.10.05.24 held at. DAPTA Office, Thakurmunda. Vide Bill No.1564 dtd.10.05.2024 | E47: 17.05.2024 | F47: 240 | G47: P.V No.13
B48: Being the amount paid to Jagannath Sahu through NEFT Chq. No.046888 towards Resouce person honorarium with travel forTraining on Natural Resource Management dtd.10.05.24 held at.DAPTA Office ,Thakurmunda. | E48: 17.05.2024 | F48: 1750 | G48: p.v No.15
B49: Total 1.4.1 | D49: 2000 | F49: =SUM(F47:F48) -> 1990 | H49: =D49-F49 -> 10 | I49: =SUM(I47:I48) -> 0
A50: 1.4.2 | B50: Food for 35 participants form 7 project located villages each village 5 participants & 6 staff @ Rs.120 x 41 Person =Rs.3360 | C50: 19680
B51: Being the amount paid to Narayan Barik, Prop of. Hotel Swagatika through NEFT Chq. No.04687 towards supply of food for participants on Training on Natural Resource Management dtd.10.05.2024 held at. DAPTA Office, Thakurmunda. Vide Bill No.1562 dtd.10.05.2024 | E51: 17.05.2024 | F51: 4920 | G51: P.V. No.10
B53: Total 1.4.2 | D53: 4920 | F53: =SUM(F51:F52) -> 4920 | H53: =D53-F53 -> 0 | I53: =SUM(I51:I52) -> 0
A54: 1.4.3 | B54: Project village to training venue transportation charges Rs.7500/- each village 5 participants x 7 Project villges 3 vehicles for 2 trainings | C54: 30000
B55: Being the amount paid to Ramasingh Badra Prop. of Badra Tour & Travels through NEFT Chq. No.046887 towards hiring of 2no of vehicle for transportation participants on Training on Natural Resource Management dtd.10.05.2024 held at. DAPTA Office, Thakurmunda. Vide Bill No.62,63 dtd.10.05.2024 | E55: 17.05.2024 | F55: 5000 | G55: P.V No.17
B57: Total 1.4.3 | D57: 7500 | F57: =SUM(F55:F56) -> 5000 | H57: =D57-F57 -> 2500 | I57: =SUM(I55:I56) -> 0
A58: 1.4.4 | B58: Arrangements & training matterials @ Rs.500/- | C58: 2000
B59: Being the amount paid to Baigyanik Mohanta prop. Of Gayatree Book store through NEFT Chq. No.04687 towards purchased of trng materials on , Trng on natural resource management dtd.10.05.24. Vide Bill No.231 dtd.09.05.2024. | E59: 17.05.2024 | F59: 525 | G59: P.V No.11
B61: Total 1.4.4 | D61: 500 | F61: =SUM(F59:F60) -> 525 | H61: =D61-F61 -> -25 | I61: =SUM(I59:I60) -> 0
B62: Activities Sub Total 1.4 | C62: =SUM(C46:C58) -> 59680 | D62: =SUM(D61,D57,D53,D49) -> 14920 | F62: =SUM(F61,F57,F53,F49) -> 12435 | H62: =D62-F62 -> 2485 | I62: =SUM(I61,I57,I53,I49) -> 0
A63: 1.5 | B63: Pulses Seeds (Horse gram & Black gram) distribution
A64: 1.5.1 | B64: Pulses Seeds Distribution for 437 families Black Gram 1kg, Kulthi 1kg @Rs.212.86/- for 2 Kg x 437 families (Contribution Local labor charges@500 x 437 families) | C64: 157320
B66: Total 1.5.1 | F66: =SUM(F65:F65) -> 0 | H66: =D66-F66 -> 0 | I66: =SUM(I65:I65) -> 0
B67: Activities Sub Total 1.5 | C67: =C64 -> 157320 | D67: =D66 -> 0 | F67: =F66 -> 0 | H67: =D67-F67 -> 0 | I67: =I66 -> 0
A68: 1.6 | B68: Exposure visit on adaption of improved new technology
A69: 1.6.1 | B69: Honorarium for resource person @Rs.2000
A70: 1.6.2 | B70: Food for 35 participants & 6 staff @ Rs.200 x 41 Person x 1 day = 8400/-
A71: 1.6.3 | B71: Bus charges @ Rs.25000/- in Year -1 @ Rs. 26000/- x 2 bus in Year-2 and for Long distance place Exposure Visit in Yr-3 Bus Charges @Rs.35000/-
A72: 1.6.4 | B72: First Aid medicine & other expenses @ Rs.500/- and Rs.1000/-
B73: Activities Sub Total 1.6 | C73: =SUM(C69:C72) -> 0 | D73: 0 | H73: =D73-F73 -> 0
B74: Activities Sub Total for Outcomes :1 | C74: =SUM(C73,C67,C62,C44,C24) -> 333400 | D74: =SUM(D73,D67,D62,D44,D24) -> 45520 | F74: =SUM(F73,F67,F62,F44,F24,F17) -> 42380 | H74: =D74-F74 -> 3140 | I74: =SUM(I73,I67,I62,I44,I24,I17) -> 0
B75: Activities for Outcome :2
A76: 2.1 | B76: Training to the CBO’s (SHG) on topics a) Account book keeping, b) Record maintaining, c) Rules and Regulations, d) Responsibilities of the group leaders and members. e) Training on loan taking and refunding. f) Sack bag potatoes farming g) tuber crop farming i) Encourage to farming of Millet ( Mandia)
A77: 2.1.1 | B77: Honorarium , Travelling & food for Resource person @Rs.2000 | C77: 8000
B78: Being the amount paid to Ratikanta Mishra through NEFT Chq. no.046887 towards resource person honorarium with Travel cost for Training to the CBOs on dtd.14.05.24 held at. DAPTA office, Thakurmunda. | E78: 17.05.2024 | F78: 1750 | G78: P.V No.12
B79: Being the amount paid to Narayan Barik, Prop. Of Hotel Swagatika through NEFT Chq. no.046887 towards resource person food cost for Training to the CBOs on dtd.14.05.24 held at. DAPTA office, Thakurmunda. Vide Bill No.1572 dtd.14.05.2024 | E79: 17.05.2024 | F79: 240 | G79: P.V No.13
B80: Total 2.1.1 | D80: 2000 | F80: =SUM(F78:F79) -> 1990 | H80: =D80-F80 -> 10 | I80: =SUM(I78:I79) -> 0
A81: 2.1.2 | B81: Food for 35 participants form 7 project located villages each village 5 participants & 6 staff @ Rs.120 x 42 Person =Rs.3360 | C81: 19680
B82: Being the amount paid to Narayan Barik, Prop of. Hotel Swagatika through NEFT Chq. No.04687 towards supply of food for participants on Training to the CBOs on dtd.14.05.24 held at. DAPTA Office, Thakurmunda vide Bill No.1566 dtd.14.05.2024 | E82: 17.05.2024 | F82: 4920 | G82: P.V No.10
B84: Total 2.1.2 | D84: 4920 | F84: =SUM(F82:F83) -> 4920 | H84: =D84-F84 -> 0 | I84: =SUM(I82:I83) -> 0
A85: 2.1.3 | B85: Project village to training venue transportation charges Rs.2500/- each village 5 participants x 7 Project villages, 2 vehicles | C85: 20000
B86: Being the amount paid to Ramasingh Badra Prop. of Badra Tour & Travels through NEFT Chq. No.046887 towards hiring of 2no of vehicle for transportation participants on Training to the CBO’s (SHG) on topicson dtd. 14.05.24 Held at. DAPTA Office, Thakurmunda. Vide Bill No. 70, 71 dtd.17.05.2024 | E86: 17.05.2024 | F86: 5000 | G86: P.V No.17
B88: Total 2.1.3 | D88: 5000 | F88: =SUM(F86:F87) -> 5000 | H88: =D88-F88 -> 0 | I88: =SUM(I86:I87) -> 0
A89: 2.1.4 | B89: Arrangements & training materials @ Rs.500/- | C89: 2000
B90: Being the amount paid to Baigyanik Mohanta prop. Of Gayatree Book store through NEFT Chq. No.04687 towards purchased of Training to the CBO’s (SHG) dtd.14.05.24. Vide Bill No.211 dtd.13.05.2024 | E90: 17.05.2024 | F90: 525 | G90: P.V No. 11
B92: Total 2.1.4 | D92: 500 | F92: =SUM(F90:F91) -> 525 | H92: =D92-F92 -> -25 | I92: =SUM(I90:I91) -> 0
B93: Activities Sub Total 2.1 | C93: =SUM(C77:C89) -> 49680 | D93: =SUM(D92,D88,D84,D80) -> 12420 | F93: =SUM(F92,F88,F84,F80) -> 12435 | H93: =D93-F93 -> -15 | I93: =SUM(I92,I88,I84,I80) -> 0
A94: 2.2 | B94: Trainings on Alternate Livelihood Options: Poultry & Goat Rearing
A95: 2.2.1 | B95: Honorarium , travelling & food for resource person @Rs.2500 | C95: 5000
B98: Total 2.2.1 | D98: 0 | F98: =SUM(F96:F97) -> 0 | H98: =D98-F98 -> 0 | I98: =SUM(I96:I97) -> 0
A99: 2.2.2 | B99: Food for 35 participants form 7 project located villages each village 5 participants &6 staff @ Rs.120 x 41 Person =Rs.3360 | C99: 9840
B102: Total 2.2.2 | D102: 0 | F102: =SUM(F100:F101) -> 0 | H102: =D102-F102 -> 0 | I102: =SUM(I100:I101) -> 0
A103: 2.2.3 | B103: Project village to training venue transportation charges @Rs.2500/- 2 vehicles | C103: 10000
B106: Total 2.2.3 | D106: 0 | F106: =SUM(F104:F105) -> 0 | H106: =D106-F106 -> 0 | I106: =SUM(I104:I105) -> 0
A107: 2.2.4 | B107: Arrangements & training materials @ Rs.500/- | C107: 1000
B110: Total 2.2.4 | D110: 0 | F110: =SUM(F108:F109) -> 0 | H110: =D110-F110 -> 0
B111: Activities Sub Total 2.2 | C111: =SUM(C95:C107) -> 25840 | D111: =SUM(D110,D106,D102,D98) -> 0 | F111: =SUM(F110,F106,F102,F98) -> 0 | H111: =D111-F111 -> 0 | I111: =SUM(I110,I106,I102,I98) -> 0
A112: 2.3 | B112: Training on primary treatments and Vaccination for the domestic animals
A113: 2.3.1 | B113: Honorarium , travelling & food for resource person @Rs.2500 | C113: 5000
B116: Total 2.3.1 | F116: =SUM(F114:F115) -> 0 | H116: =D116-F116 -> 0
A117: 2.3.2 | B117: Food for 21 participants form 7 project located villages each village 3 participants & 6 staff @ Rs.120 x 21 Person =Rs.1680/- | C117: 6480
B120: Total 2.3.2 | F120: =SUM(F118:F119) -> 0 | H120: =D120-F120 -> 0
A121: 2.3.3 | B121: Project village to training venue transportation charges Rs.2500/- each village 2 participants x 7 Project villages 2 vehicles | C121: 10000
B124: Total 2.3.3 | F124: =SUM(F122:F123) -> 0 | H124: =D124-F124 -> 0
A125: 2.3.4 | B125: Arrangements & training matterials @ Rs.500/- | C125: 1000
B129: Total 2.3.4 | F129: =SUM(F126:F128) -> 0 | H129: =D129-F129 -> 0
B130: Activities Sub Total 2.3 | C130: =SUM(C113:C125) -> 22480 | D130: =SUM(D129,D124,D120,D116) -> 0 | F130: =SUM(F129,F124,F120,F116) -> 0 | H130: =D130-F130 -> 0
...

Sheet  Qtr- 2 July-24 to Sept-24  (2)
B1: Partner: DAPTA (Development Agency for Poor and Tribal Awakening)
A2: Quarterly/Monthly Reporting Format
A3: Ensuring food and livelihood security of indigenous and other marginalized communities in Thakurmunda Block, Mayurbhanj, Odisha
D4: Accounting Period: | E4: Start: 1 July 2024
E5: End: 30 Sept 2024
A6: Date: Grant received on | D6: 16.07.2024 | E6: Total Annual MCC Budget: | H6: =+' Qtr-1 April-24 to June-24 '!H6:I6 -> Rs. 26,75,000/-
A7: Opening Balalnce : on 1 July 2024 Cash in Cash | D7: 111252.22
A8: Cash in Bank | D8: 0
A9: Total Balance available on 1.July 2024 | D9: =D8+D7 -> 111252.22
A10: Bank interest earned | D10: 2994
A11: Grant Received from MCC for Qtr-2 2024-25: | D11: 720885 | E11: NOTE: Please add more rows if needed but make sure that the value is added to the fomula
A12: Total Balance available | D12: =SUM(D9:D11) -> 835131.22
A13: Budget ID | B13: Vendor/Expense Description | C13: MCC Approved budget-Yr-1 | D13: Quarterly Budgeted Amount Qtr-2 2024 | E13: Date | F13: Expense Amt | G13: Voucher or receipt number | H13: Budgeted Amt less Expense Amount | I13: Partner / Farmer Contribution
A14: 1 | B14: Outcome :1 Activities
A15: 1.1 | B15: Baseline | C15: 0
B17: Total 1.1 | D17: 0 | F17: =SUM(F16:F16) -> 0 | H17: =D17-F17 -> 0
A18: 1.2 | B18: Monthly PRA/ Data collection/ Village Community Meeting
A19: 1.2.1 | B19: Monthly Village Community Meeting (Biscuits / Snacks /per time /12 Months) @Rs.15 x 437 + 6 staff =Rs.6660/- | C19: 79920
B20: Being the amount paid to Jyotshnarani Pradhan prop. of New Family Bazar,Thakurmunda through NEFT Chq. No.046916 towards purchased of Biscuits for participants of 06nos Monthly village community Meeting month of July-2024. vide Bill No. 176 dtd.02.07.24. | E20: 31.07.24 | F20: 6480 | G20: P.V No.52
B21: Being the amount paid to Lizarani Barik prop. of Lijarani Traders,Thakurmunda through NEFT Chq. No.046930 towards purchased of Biscuits for participants of 06nos Monthly village community Meeting month of Aug-2024. Vide Bill No.055 dtd.02.08.2024 | E21: 30.08.2024 | F21: 5100 | G21: P.V No.64
B22: Being the amount paid to Lijarani Barik prop. of Lijarani Traders,Thakurmunda through NEFT Chq. No.046943 towards purchased of Biscuits for participants of 06nos Monthly village community Meeting month of Sept-2024.Vide Bill No.064 dtd.3.09.2024 | E22: 30.09.24 | F22: 6000 | G22: P.V No.77
B23: Total 1.2.1 | D23: 19980 | F23: =SUM(F20:F22) -> 17580 | H23: =D23-F23 -> 2400
B24: Activities Sub Total 1.2 | C24: =SUM(C15,C19) -> 79920 | D24: =D23+D17 -> 19980 | F24: =SUM(F23) -> 17580 | H24: =D24-F24 -> 2400 | I24: =SUM(I15,I19) -> 0
A25: 1.3 | B25: Training on Improved agriculture methods and Technology :- a) SRI (Paddy farming in row) b) Multi cropping c) Crop diversification d) Crop rotation e) Azola growing f) Seed preservation g) Seed treatment
A26: 1.3.1 | B26: Honorarium , travelling & food for resource person @Rs.2000 (above mentioned some subject will be conducted by the Project staff) | C26: 2000
B28: Total 1.3.1 | D28: 0 | F28: =SUM(F27:F27) -> 0 | H28: =D28-F28 -> 0
A29: 1.3.2 | B29: Food for 20 participants & 6 staff @ Rs.120 x 26 Person | C29: 12480
B31: Total 1.3.2 | D31: 3120 | F31: =SUM(F30:F30) -> 0 | H31: =D31-F31 -> 3120
A32: 1.3.3 | B32: Project village to training venue Transportation charges 20 participants x 1 Project villages @ Rs.2500/-; 2 vehicles | C32: 20000
B34: Total 1.3.3 | D34: 5000 | F34: =SUM(F33:F33) -> 0 | H34: =D34-F34 -> 5000
A35: 1.3.4 | B35: Arrangements & training matterials @ Rs.500/- | C35: 2000
B37: Total 1.3.4 | D37: 500 | F37: =SUM(F36:F36) -> 0 | H37: =D37-F37 -> 500
B38: Activities Sub Total 1.3 | C38: =SUM(C26:C35) -> 36480 | D38: =SUM(D37,D34,D31,D28) -> 8620 | F38: =SUM(F37,F34,F31,F28) -> 0 | H38: =D38-F38 -> 8620
A39: 1.4 | B39: Training on Natural Resource Management a) Soil health ( Testing, treatment and preservation) b) Organic farming (Chemical free) c) Compost pit & its preparation d) Vermin compost making e) Bio- Pesticide f) Bio- fertilizer
A40: 1.4.1 | B40: Honorarium, travelling & food for resource person @Rs.2000 | C40: 8000
B41: Being the amount paid to Narayan Barik, Prop of. Hotel Swagatika through NEFT Chq. No.04687 towards supply of food for Resource Person on Natural resource management Training dtd.13.08.2024 held at DAPTA,Thakurmunda. Vide Bill No.1698 dtd.13.08.24 | E41: 22.08.24 | F41: 180 | G41: P.V No.60
B42: Being the amount paid to Jagannath Sahu through NEFT Chq. No.046925 towards Resouce person honorarium with travel on Natural resource management training dtd.13.08.24 held at.DAPTA Office ,Thakurmunda. | E42: 22.08.24 | F42: 1750 | G42: P.V No.61
B43: Total 1.4.1 | D43: 2000 | F43: =SUM(F41:F42) -> 1930 | H43: =D43-F43 -> 70
A44: 1.4.2 | B44: Food for 35 participants form 7 project located villages each village 5 participants & 6 staff @ Rs.120 x 41 Person =Rs.3360 | C44: 19680
B45: Being the amount paid to Narayan Barik, Prop of. Hotel Swagatika through NEFT Chq. No.04687 towards supply of food for participants on Natural resource management Training dtd.13.08.2024 held at DAPTA,Thakurmunda. Vide Bill No.1697 dtd.13.08.24 | E45: 22.08.24 | F45: 4680 | G45: P.V No.60
B47: Total 1.4.2 | D47: 4920 | F47: =SUM(F45:F46) -> 4680 | H47: =D47-F47 -> 240
A48: 1.4.3 | B48: Project village to training venue transportation charges Rs.7500/- each village 5 participants x 7 Project villges 3 vehicles for 2 trainings | C48: 30000
B49: Being the amount paid to Ramasingh Badra through NEFT Chq. No.046925 towards hiring of 2no of vehicle for transportation of participants on Natural resource management training dtd.13.08.2024 held at. DAPTA Office,Thakurmunda. Vide Bill No.125 & 126 dtd.13.08.24 | E49: 22.08.24 | F49: 5000 | G49: P.V No.59
B51: Total 1.4.3 | D51: 7500 | F51: =SUM(F49:F50) -> 5000 | H51: =D51-F51 -> 2500
A52: 1.4.4 | B52: Arrangements & training matterials @ Rs.500/- | C52: 2000
B53: Being the amount paid to Gayatree Book store through NEFT Chq. No.046925 towards purchased of Training materials for Participants on Natural resource management Training dtd.13.08.2024 held at. DAPTA Office, Thakurmunda. Vide Bill No.243 dtd.13.08.24 | E53: 22.08.204 | F53: 525 | G53: P.V No.62
B55: Total 1.4.4 | D55: 500 | F55: =SUM(F53:F54) -> 525 | H55: =D55-F55 -> -25
B56: Activities Sub Total 1.4 | C56: =SUM(C40:C52) -> 59680 | D56: =SUM(D55,D51,D47,D43) -> 14920 | F56: =SUM(F55,F51,F47,F43) -> 12135 | H56: =D56-F56 -> 2785
A57: 1.5 | B57: Pulses Seeds (Horse gram & Black gram) distribution
A58: 1.5.1 | B58: Pulses Seeds Distribution for 437 families Black Gram 1kg, Kulthi 1kg @Rs.212.86/- for 2 Kg x 437 families (Contribution Local labor charges@500 x 437 families) | C58: 157320
B59: Being the amount paid to Jatin Kumar Nayak , Prop. of Palishree krushi Seva Kandra, through NEFT Chq. No.046941 towards purchased of Pulses Seeds ( Black Gram & Horse Gram) for distribution to 437 Families vide Bill No.317 dtd.14.09.2024 | E59: 23.09.24 | F59: 154754 | G59: P.V No.76
B60: Total 1.5.1 | F60: =SUM(F59:F59) -> 154754 | H60: =D60-F60 -> -154754
B61: Activities Sub Total 1.5 | C61: =C58 -> 157320 | D61: 157320 | F61: =F60 -> 154754 | H61: =D61-F61 -> 2566
A62: 1.6 | B62: Exposure visit on adaption of improved new technology
A63: 1.6.1 | B63: Honorarium for resource person @Rs.2000
B65: Total 1.6.1 | F65: =SUM(F64:F64) -> 0 | H65: =D65-F65 -> 0
A66: 1.6.2 | B66: Food for 35 participants & 6 staff @ Rs.200 x 41 Person x 1 day = 8400/-
B68: Total 1.6.2 | F68: =SUM(F67:F67) -> 0 | H68: =D68-F68 -> 0
A69: 1.6.3 | B69: Bus charges @ Rs.25000/- in Year -1 @ Rs. 26000/- x 2 bus in Year-2 and for Long distance place Exposure Visit in Yr-3 Bus Charges @Rs.35000/-
B71: Total 1.6.3 | F71: =SUM(F70:F70) -> 0 | H71: =D71-F71 -> 0
A72: 1.6.4 | B72: First Aid medicine & other expenses @ Rs.500/- and Rs.1000/-
B74: Total 1.6.4 | F74: =SUM(F73:F73) -> 0 | H74: =D74-F74 -> 0
B75: Activities Sub Total 1.6 | C75: =SUM(C63:C72) -> 0 | D75: 0 | F75: =SUM(F74+F71+F68+F65) -> 0 | H75: =D75-F75 -> 0
B76: Activities Sub Total for Outcomes :1 | C76: =SUM(C75,C61,C56,C38,C24) -> 333400 | D76: =SUM(D75,D61,D56,D38,D24) -> 200840 | F76: =SUM(F75,F61,F56,F38,F24,F17) -> 184469 | H76: =D76-F76 -> 16371
B77: Activities for Outcome :2
A78: 2.1 | B78: Training to the CBO’s (SHG) on topics a) Account book keeping, b) Record maintaining, c) Rules and Regulations, d) Responsibilities of the group leaders and members. e) Training on loan taking and refunding. f) Sack bag potatoes farming g) tuber crop farming i) Encourage to farming of Millet ( Mandia)
A79: 2.1.1 | B79: Honorarium , Travelling & food for Resource person @Rs.2000 | C79: 8000
B80: Being the amount paid to Narayan Barik, Prop of. Hotel Swagatika through NEFT Chq. No.046930 towards supply of food for Resource Person on Training to the CBOs dtd.14.08.24 held at. DAPTA,Office,Thakurmunda. Vide Bill No.1703 dtd. 14.08.24. | E80: 30.08.24 | F80: 180 | G80: P.V No.67
B81: Being the amount paid to Ramani ranjan Ojha through NEFT Chq. no.046931 towards resource person honorarium with Travel cost for Training to the CBOs on dtd.14.08.24 held at. DAPTA office, Thakurmunda. | E81: 30.08.24 | F81: 1750 | G81: P.V No.69
B82: Total 2.1.1 | D82: 2000 | F82: =SUM(F80:F81) -> 1930 | H82: =D82-F82 -> 70
A83: 2.1.2 | B83: Food for 35 participants form 7 project located villages each village 5 participants & 6 staff @ Rs.120 x 42 Person =Rs.3360 | C83: 19680
B84: Being the amount paid to Narayan Barik, Prop of. Hotel Swagatika through NEFT Chq. No.046930 towards supply of food for participants on Training to the CBO’s (SHG) dtd.14.08.2024 held at. DAPTA, Office,Thakurmunda. Vide Bill No.1702 dtd.14.08.2024 | E84: 30.08.24 | F84: 4440 | G84: P.V No.66
B86: Total 2.1.2 | D86: 4920 | F86: =SUM(F84:F85) -> 4440 | H86: =D86-F86 -> 480
A87: 2.1.3 | B87: Project village to training venue transportation charges Rs.2500/- each village 5 participants x 7 Project villages, 2 vehicles | C87: 20000
B88: Being the amount paid to Ramasingh Badra, through NEFT Chq. No.046931 towards hiring of 2no of vehicle for transportation participants on Training to the CBOs dtd.14.08.24 held at. DAPTA,Office, Thakurmunda. Vide Bill No.127 & 128 dtd.14.08.2024 | E88: 30.08.2024 | F88: 5000 | G88: P.V No.68
B90: Total 2.1.3 | D90: 5000 | F90: =SUM(F88:F89) -> 5000 | H90: =D90-F90 -> 0
A91: 2.1.4 | B91: Arrangements & training materials @ Rs.500/- | C91: 2000
B92: Being the amount paid to Gayatree Book store through NEFT Chq. No.046930 towards purchased of Training materials on Training to the CBOs held at . DAPTA,Office, Thakurmunda on dtd.14.08.24. Vide Bill No.248 dtd.14.08.2024. | E92: 30.08.24 | F92: 465 | G92: P.V No.65
B94: Total 2.1.4 | D94: 500 | F94: =SUM(F92:F93) -> 465 | H94: =D94-F94 -> 35
B95: Activities Sub Total 2.1 | C95: =SUM(C79:C91) -> 49680 | D95: =SUM(D94,D90,D86,D82) -> 12420 | F95: =SUM(F94,F90,F86,F82) -> 11835 | H95: =D95-F95 -> 585
A96: 2.2 | B96: Trainings on Alternate Livelihood Options: Poultry & Goat Rearing
A97: 2.2.1 | B97: Honorarium , travelling & food for resource person @Rs.2500 | C97: 5000
B98: Being the amount paid to Narayan Barik, Prop of. Hotel Swagatika through NEFT Chq. No.046930 towards supply of food for Resource Person on Alternate Livelihood Options: Poultry & Goat Rearing Training dtd.27.08.24 held at.DAPTA,Office,Thakurmunda. Vide Bill No.1710 dtd. 27.08.24. | E98: 30.08.24 | F98: 190 | G98: P.V No.67
B99: Being the amount paid to Priti Prasanna Sahoo, R.P through NEFT Chq. no.046931 towards resource person honorarium with Travel cost for Trainings on Alternate Livelihood Options: Poultry & Goat Rearing dtd.27.08.24 held at.DAPTA,Office,Thakurmunda. | E99: 30.08.2024 | F99: 2250 | G99: P.V No.69
B100: Total 2.2.1 | D100: 2500 | F100: =SUM(F98:F99) -> 2440 | H100: =D100-F100 -> 60
A101: 2.2.2 | B101: Food for 35 participants form 7 project located villages each village 5 participants &6 staff @ Rs.120 x 41 Person =Rs.3360 | C101: 9840
B102: Being the amount paid to Narayan Barik, Prop of. Hotel Swagatika through NEFT Chq. No.046930 towards supply of food for participants on Alternate Livelihood Options: Poultry & Goat Rearing Training dtd.27.08.2024 held at. DAPTA, Office,Thakurmunda. Vide Bill No.1709 dtd.27.08.2024 | E102: 30.08.24 | F102: 4440 | G102: P.V No.66
B104: Total 2.2.2 | D104: 4920 | F104: =SUM(F102:F103) -> 4440 | H104: =D104-F104 -> 480
A105: 2.2.3 | B105: Project village to training venue transportation charges @Rs.2500/- 2 vehicles | C105: 10000
B106: Being the amount paid to Ramasingh Badra, through NEFT Chq. No.046931 towards hiring of 2no of vehicle for transportation participants on Alternate Livelihood Options: Poultry & Goat Rearing Training dtd.27.08.24 held at. DAPTA,Office, Thakurmunda. Vide Bill No.136 & 137 dtd.27.08.2024 | E106: 30.08.2024 | F106: 5000 | G106: P.V No.68
B108: Total 2.2.3 | D108: 5000 | F108: =SUM(F106:F107) -> 5000 | H108: =D108-F108 -> 0
A109: 2.2.4 | B109: Arrangements & training materials @ Rs.500/- | C109: 1000
B110: Being the amount paid to Gayatree Book store through NEFT Chq. No.046930 towards purchased of Training materials on Alternate Livelihood Options: Poultry & Goat Rearing training held at . DAPTA,Office, Thakurmunda on dtd. 27.08.24. Vide Bill No.251 dtd.27.08.2024. | E110: 30.08.24 | F110: 527 | G110: P.V No.65
B112: Total 2.2.4 | D112: 500 | F112: =SUM(F110:F111) -> 527 | H112: =D112-F112 -> -27
B113: Activities Sub Total 2.2 | C113: =SUM(C97:C109) -> 25840 | D113: =SUM(D112,D108,D104,D100) -> 12920 | F113: =SUM(F112,F108,F104,F100) -> 12407 | H113: =D113-F113 -> 513
A114: 2.3 | B114: Training on primary treatments and Vaccination for the domestic animals
A115: 2.3.1 | B115: Honorarium , travelling & food for resource person @Rs.2500 | C115: 5000
B116: Being the amount paid to Narayan Barik, Prop of. Hotel Swagatika through NEFT Chq. No.046930 towards supply of food for Resource Person on Primary treatments and Vaccination for the domestic animals Training dtd.28.08.24 held at.DAPTA,Office,Thakurmunda. Vide Bill No.1712 dtd. 28.08.24. | E116: 30.08.24 | F116: 210 | G116: P.V No.67
B117: Being the amount paid to Priti Prasanna Sahoo, R.P through NEFT Chq. no.046931 towards resource person honorarium with Travel cost for Training on primary treatments and Vaccination for the domestic animals dtd.28.08.24 held at.DAPTA,Office,Thakurmunda. | E117: 30.08.204 | F117: 2250 | G117: P.V No.69
B118: Total 2.3.1 | D118: 2500 | F118: =SUM(F116:F117) -> 2460 | H118: =D118-F118 -> 40
...

Sheet  Qtr-3 Octo-24 to Dec-24
B1: Partner: DAPTA (Development Agency for Poor and Tribal Awakening)
A2: Quarterly/Monthly Reporting Format
A3: Ensuring food and livelihood security of indigenous and other marginalized communities in Thakurmunda Block, Mayurbhanj, Odisha
D4: Accounting Period: | E4: Start: 1 Octo. 2024
E5: End: 31 Dec. 2024
A6: Date: Grant received on | D6: 15.10.2024 | E6: Total Annual MCC Budget: | H6: =+' Qtr-1 April-24 to June-24 '!H6:I6 -> Rs. 26,75,000/-
A7: Opening Balalnce : on 1 Octo. 2024 Cash in Hand | D7: 0
A8: Cash in Bank | D8: 70766.32
A9: Total Balance available on 1.Octo. 2024 | D9: =D8+D7 -> 70766.32
A10: Bank interest earned | D10: 2912
A11: Grant Received from MCC for Qtr-3 2024-25: | D11: 526803 | E11: NOTE: Please add more rows if needed but make sure that the value is added to the fomula
A12: Total Balance available | D12: =SUM(D9:D11) -> 600481.32
A13: Budget ID | B13: Vendor/Expense Description | C13: MCC Approved budget-Yr-1 | D13: Quarterly Budgeted Amount Qtr-3 2024 | E13: Date | F13: Expense Amt | G13: Voucher or receipt number | H13: Budgeted Amt less Expense Amount | I13: Partner / Farmer Contribution
A14: 1 | B14: Outcome :1 Activities
A15: 1.1 | B15: Baseline | C15: 0
B18: Total 1.1 | D18: 0 | F18: =SUM(F16:F17) -> 0 | H18: =D18-F18 -> 0 | I18: =SUM(I16:I17) -> 0
A19: 1.2 | B19: Monthly PRA/ Data collection/ Village Community Meeting
A20: 1.2.1 | B20: Monthly Village Community Meeting (Biscuits / Snacks /per time /12 Months) @Rs.15 x 437 + 6 staff =Rs.6660/- | C20: 79920
B21: Being the amount paid to Lijarani Barik prop. of Lijarani Traders,Thakurmunda through NEFT Chq. No.052134 towards purchased of Biscuits for participants of 06nos Monthly village community Meeting month of October-2024. Vide Bill No.066 dtd.30.10.2024 | E21: 04.11.2024 | F21: 6000 | G21: Pv. No.101
B22: Being the amount paid to Lijarani Barik prop. of Lijarani Traders,Thakurmunda through NEFT Chq. No.052150 towards purchased of Biscuits for participants of 06nos Monthly village community Meeting month of November-2024. Vide Bill No. 071 dtd. 02.11.2024 | E22: 30.11.2024 | F22: 6435 | G22: Pv. No.117
B23: Being the amount paid to Lijarani Barik prop. of Lijarani Traders,Thakurmunda through NEFT Chq. No.052064 towards purchased of Biscuits for participants of 06nos Monthly village community Meeting month of Dec-2024. Vide Bill No. 073 dtd. 30.12.2024 | E23: 30.12.2024 | F23: 6300 | G23: Pv. No.134
B24: Total 1.2.1 | D24: 19980 | F24: =SUM(F21:F23) -> 18735 | H24: =D24-F24 -> 1245 | I24: =SUM(I21:I23) -> 0
B25: Activities Sub Total 1.2 | C25: =SUM(C15,C20) -> 79920 | D25: =D24+D18 -> 19980 | F25: =SUM(F24) -> 18735 | H25: =D25-F25 -> 1245 | I25: =SUM(I24) -> 0
A26: 1.3 | B26: Training on Improved agriculture methods and Technology :- a) SRI (Paddy farming in row) b) Multi cropping c) Crop diversification d) Crop rotation e) Azola growing f) Seed preservation g) Seed treatment
A27: 1.3.1 | B27: Honorarium , travelling & food for resource person @Rs.2000 (above mentioned some subject will be conducted by the Project staff) | C27: 2000
B31: Total 1.3.1 | F31: =SUM(F28:F30) -> 0 | H31: =D31-F31 -> 0
A32: 1.3.2 | B32: Food for 20 participants & 6 staff @ Rs.120 x 26 Person | C32: 12480
B33: Being the amount paid to Narayan Barik Prop. Of . Hotel Swagatika through NEFT Chq. No.052142 towards supply of Food for Participants on Improved agriculture Methods & Technology Training on dtd.13.11.2024 held at. DAPTA Office, Thakurmunda. Vide Bill No. 1748 dtd.13.11.2024 | E33: 14.11.2024 | F33: 3000 | G33: Pv. No.112
B34: Being the amount paid to Narayan Barik Prop. Of .Hotel Swagatika through NEFT Chq. No.052055 towards supply of Food for Participants on Improved agriculture Methods & Technology Training on dtd.29.11.2024 held at. DAPTA Office, Thakurmunda Vide Bill No.1754 dtd. 29.11.2024. | E34: 09.12.2024 | F34: 3120 | G34: Pv. No.124
B36: Total 1.3.2 | D36: 3120 | F36: =SUM(F33:F35) -> 6120 | H36: =D36-F36 -> -3000 | I36: =SUM(I33:I35) -> 0
A37: 1.3.3 | B37: Project village to training venue Transportation charges 20 participants x 1 Project villages @ Rs.2500/-; 2 vehicles | C37: 20000
B38: Being the amount paid to Ramasingh Badra, Prop. Of badra Tour & travel through NEFT Chq. No.052143 towards hiring of 2no of vehicle for transportation on Improved agriculture Agriculture methods & Technology on dtd.13.11.24 held at. DAPTA Office, Thakurmunda.142 & 143 dtd. 13.11.2024. | E38: 14.11.2024 | F38: 5000 | G38: Pv. No.114
B39: Being the amount paid toRamasingh Badra Prop. of Badra tour & travel through NEFT Chq. No.052024 towards Hiring 2nos of Vehicle for Participants on r Trng on Improved Agriculture dtd.29.11.24. held at. DAPTA office, Thakurmunda. Vide Bill No.150& 151 dtd. 29.11.2024. | E39: 09.12.2024 | F39: 5000 | G39: Pv. No.121
B41: Total 1.3.3 | D41: 5000 | F41: =SUM(F38:F40) -> 10000 | H41: =D41-F41 -> -5000 | I41: =SUM(I38:I40) -> 0
A42: 1.3.4 | B42: Arrangements & training matterials @ Rs.500/- | C42: 2000
B43: Being the amount paid to Baigyanik Mohanta Prop. Of Gayatree Book Store through NEFT Chq. No.052142 towards purchased of Training Materials for Participants on Improved agriculture Agriculture Methods & Technology Training dtd.13.11.24 held at. DAPTA Office, Thakurmunda. Vide Bill no. 273 dtd. 13.11.2024 | E43: 14.11.2024 | F43: 400 | G43: Pv. No.113
B44: Being the amount paid to Baigyanik Mohanta Prop. Of Gayatree Book Store through NEFT Chq. No.052055 towards purchased of Training Materials for Participants on Improved agriculture Agriculture Methods & Technology Training dtd.29.11.2024 held at. DAPTA Office, Thakurmunda. Vide Bill No.281 dtd. 29.11.2024. | E44: 09.12.2024 | F44: 500 | G44: Pv. No.123
B45: Total 1.3.4 | D45: 500 | F45: =SUM(F43:F44) -> 900 | H45: =D45-F45 -> -400 | I45: =SUM(I43:I44) -> 0
B46: Activities Sub Total 1.3 | C46: =SUM(C27:C42) -> 36480 | D46: =SUM(D45,D41,D36,D31) -> 8620 | F46: =SUM(F45,F41,F36,F31) -> 17020 | H46: =D46-F46 -> -8400 | I46: =SUM(I45,I41,I36,I31) -> 0
A47: 1.4 | B47: Training on Natural Resource Management a) Soil health ( Testing, treatment and preservation) b) Organic farming (Chemical free) c) Compost pit & its preparation d) Vermin compost making e) Bio- Pesticide f) Bio- fertilizer
A48: 1.4.1 | B48: Honorarium, travelling & food for resource person @Rs.2000 | C48: 8000
B49: Being the amount paid to Ravi Shankar Behera,RP through NEFT Chq. No.052126 towards Resouce person honorarium of Training on natural resource management dtd.29.09.24 held at.DAPTA Office ,Thakurmunda. | E49: 08.10.2024 | F49: 2000 | G49: Pv. No.88
B50: Being the amount paid to Jagannath Sahu through NEFT Chq. No.052137 towards Resouce person honorarium with travel Training on natural resource management dtd.08.11.24 held at.DAPTA Office ,Thakurmunda. | E50: 12.11.2024 | F50: 2000 | G50: Pv. No.105
B51: Total 1.4.1 | D51: 2000 | F51: =F49+F50 -> 4000 | H51: =D51-F51 -> -2000
A52: 1.4.2 | B52: Food for 35 participants form 7 project located villages each village 5 participants & 6 staff @ Rs.120 x 41 Person =Rs.3360 | C52: 19680
B53: Being the amount paid to Narayan Barik, Prop of. Hotel Swagatika through NEFT Chq. No.052127 towards supply of food for participants for Training on natural resource management dtd 29.09.2024 held at DAPTA,Thakurmunda. Vide Bill No.1729 dtd.29.09.2024 | E53: 08.10.2024 | F53: 4560 | G53: Pv. No.92
B54: Being the amount paid to Narayan Barik, Prop of. Hotel Swagatika through NEFT Chq. No.052138 towards supply of food for participants on Training on natural resource management dtd.08.11.2024 held at DAPTA,Thakurmunda. Vide Bill No.1743 dtd. 08.11.2024 | E54: 12.11.2024 | F54: 4800 | G54: Pv. No.107
B55: Total 1.4.2 | D55: 4920 | F55: =SUM(F53:F54) -> 9360 | H55: =D55-F55 -> -4440 | I55: =SUM(I53:I54) -> 0
A56: 1.4.3 | B56: Project village to training venue transportation charges Rs.7500/- each village 5 participants x 7 Project villges 3 vehicles for 2 trainings | C56: 30000
B57: Being the amount paid to Ramasingh Badra Prop. of Badra Tour & Travel through NEFT Chq. No.052126 towards hiring of 2no of vehicle for transportation participants on Training on natural resource management dtd.29.09.24 held at.Th.munda. Vide Bill No.134 & 135 dtd.29.09.24 | E57: 08.10.2024 | F57: 5000 | G57: Pv No.87
B58: Being the amount paid to Ramasingh Badra,Prop. Of Barda Tour & Travel through NEFT Chq. No.052137 towards hiring of 2no of vehicle for transportation participants on Training on natural resource management dtd.08.11.24 held at. DAPTA Office, Thakurmunda. Vide Bill No. 137 &138 dtd.08.11.2024. | E58: 12.11.2024 | F58: 5000 | G58: Pv No.106
B59: Total 1.4.3 | D59: 7500 | F59: =SUM(F57:F58) -> 10000 | H59: =D59-F59 -> -2500 | I59: =SUM(I57:I58) -> 0
A60: 1.4.4 | B60: Arrangements & training matterials @ Rs.500/- | C60: 2000
B61: Being the amount paid to Baigyanik Mohanta Prop. of Gayatree Book store through NEFT Chq. No.052127 towards purchased of Training materials for Participants on Training on natural resource management dtd.29.09.2024 held at. DAPTA Office, Thakurmunda.Vide Bill No.261 dtd.29.09.2024 | E61: 08.10.2024 | F61: 480 | G61: Pv No.91
B62: Being the amount paid to Baigyanik Mohanta Prop. of Gayatree Book store through NEFT Chq. No.052138 towards purchased of Training materials for Participants on Training on natural resource management dtd.08.11.2024 held at. DAPTA Office, Thakurmunda. Vide Bill No.269 dtd.08.11.2024 | E62: 12.11.2024 | F62: 510 | G62: Pv No.108
B63: Total 1.4.4 | D63: 500 | F63: =SUM(F61:F62) -> 990 | H63: =D63-F63 -> -490
B64: Activities Sub Total 1.4 | C64: =SUM(C48:C60) -> 59680 | D64: =SUM(D63,D59,D55,D51) -> 14920 | F64: =SUM(F63,F59,F55,F51) -> 24350 | H64: =D64-F64 -> -9430
A65: 1.5 | B65: Pulses Seeds (Horse gram & Black gram) distribution
A66: 1.5.1 | B66: Pulses Seeds Distribution for 437 families Black Gram 1kg, Kulthi 1kg @Rs.212.86/- for 2 Kg x 437 families (Contribution Local labor charges@500 x 437 families) | C66: 157320 | I66: 207500
B67: Being the amount paid to Ramasingh Badra Prop. of Badra Tour & Travel through NEFT Chq. No.052126 towards hiring 1nos vehicle for transportation for Pluses distrubution to 7Villages. Vide Bill No.130 dtd. 25.09.2024 | E67: 08.10.2024 | F67: 3500 | G67: Pv No.87
B68: Total 1.5.1 | F68: =SUM(F67:F67) -> 3500 | H68: =D68-F68 -> -3500 | I68: =SUM(I66:I67) -> 207500
B69: Activities Sub Total 1.5 | C69: =C66 -> 157320 | D69: =D68 -> 0 | F69: =F68 -> 3500 | H69: =D69-F69 -> -3500 | I69: =I68 -> 207500
A70: 1.6 | B70: Exposure visit on adaption of improved new technology
A71: 1.6.1 | B71: Honorarium for resource person @Rs.2000
B73: Total 1.5.1 | F73: =SUM(F72:F72) -> 0 | H73: =D73-F73 -> 0 | I73: =SUM(I72:I72) -> 0
A74: 1.6.2 | B74: Food for 35 participants & 6 staff @ Rs.200 x 41 Person x 1 day = 8400/-
B76: Total 1.6.2 | F76: =SUM(F75:F75) -> 0 | H76: =D76-F76 -> 0 | I76: =SUM(I75:I75) -> 0
A77: 1.6.3 | B77: Bus charges @ Rs.25000/- in Year -1 @ Rs. 26000/- x 2 bus in Year-2 and for Long distance place Exposure Visit in Yr-3 Bus Charges @Rs.35000/-
B79: Total 1.6.3 | F79: =SUM(F78:F78) -> 0 | H79: =D79-F79 -> 0 | I79: =SUM(I78:I78) -> 0
A80: 1.6.4 | B80: First Aid medicine & other expenses @ Rs.500/- and Rs.1000/-
B82: Total 1.6.4 | F82: =SUM(F81:F81) -> 0 | H82: =D82-F82 -> 0 | I82: =SUM(I81:I81) -> 0
B83: Activities Sub Total 1.6 | C83: =SUM(C71:C80) -> 0 | D83: 0 | F83: =SUM(F82+F79+F76+F73) -> 0 | H83: =D83-F83 -> 0 | I83: =SUM(I82+I79+I76+I73) -> 0
B84: Activities Sub Total for Outcomes :1 | C84: =SUM(C83,C69,C64,C46,C25) -> 333400 | D84: =SUM(D83,D69,D64,D46,D25) -> 43520 | F84: =SUM(F83,F69,F64,F46,F25,F18) -> 63605 | H84: =D84-F84 -> -20085 | I84: =SUM(I83,I69,I64,I46,I25,I18) -> 207500
B85: Activities for Outcome :2
A86: 2.1 | B86: Training to the CBO’s (SHG) on topics a) Account book keeping, b) Record maintaining, c) Rules and Regulations, d) Responsibilities of the group leaders and members. e) Training on loan taking and refunding. f) Sack bag potatoes farming g) tuber crop farming i) Encourage to farming of Millet ( Mandia)
A87: 2.1.1 | B87: Honorarium , Travelling & food for Resource person @Rs.2000 | C87: 8000
B88: Being the amount paid to Narayan Barik, Prop of. Hotel Swagatika through NEFT Chq. No.0452059 towards supply of food for R.P on Training to the CBOs dtd.18.12.2024 held at. Dapta office, Thakurmunda Vide Bill No.73 dtd.18.12.2024 | E88: 21.12.2024 | F88: 180 | G88: Pv. No.129
B89: Being the amount paid to Ramani ranjan Ojha through NEFT Chq. no.052060 towards resource person honorarium with Travel cost for Training to the CBOs on dtd.18.12.24 held at. DAPTA office, Thakurmunda. | E89: 21.12.2024 | F89: 1750 | G89: Pv. No. 130
B90: Total 2.1.1 | D90: 2000 | F90: =SUM(F88:F89) -> 1930 | H90: =D90-F90 -> 70 | I90: =SUM(I88:I89) -> 0
A91: 2.1.2 | B91: Food for 35 participants form 7 project located villages each village 5 participants & 6 staff @ Rs.120 x 42 Person =Rs.3360 | C91: 19680
B92: Being the amount paid to Suvendu Barik, Prop of. Hotel Suvendu through NEFT Chq. No.052059 towards supply of food for participants on Training to the CBOs on dtd.18.12.24 Held at. DAPTA office, Thakurmunda. Vide Bill No. 72 dtd.18.12.22024 | E92: 21.12.2024 | F92: 4680 | G92: Pv. No.127
B94: Total 2.1.2 | D94: 4920 | F94: =SUM(F92:F93) -> 4680 | H94: =D94-F94 -> 240 | I94: =SUM(I92:I93) -> 0
A95: 2.1.3 | B95: Project village to training venue transportation charges Rs.2500/- each village 5 participants x 7 Project villages, 2 vehicles | C95: 20000
B96: Being the amount paid to Jandai Hembram Prop. Of Hembram tour & Travels through NEFT Chq. No.052059 towards hiring of 2no of vehicle for transportation participants on Training to the CBOs dtd. 18.12.24 held at DAPTA office,Thakurmunda. Vide Bill No.278 &279 dtd.18.12.2024. | E96: 21.12.2024 | F96: 5000 | G96: Pv. No.128
B98: Total 2.1.3 | D98: 5000 | F98: =SUM(F96:F97) -> 5000 | H98: =D98-F98 -> 0 | I98: =SUM(I96:I97) -> 0
A99: 2.1.4 | B99: Arrangements & training materials @ Rs.500/- | C99: 2000
B100: Being the amount paid to Baigyanik Mohanta Prop. Of Gayatree Book store through NEFT Chq. No.052059 towards purchased of trng materials on Training to the CBOs dtd.18.12.24 held at DAPTA Office, Thakurmunda. Vide Bill No. 289 dtd.18.12.2024 | E100: 21.12.2024 | F100: 495 | G100: Pv. No.126
B102: Total 2.1.4 | D102: 500 | F102: =SUM(F100:F101) -> 495 | H102: =D102-F102 -> 5 | I102: =SUM(I100:I101) -> 0
B103: Activities Sub Total 2.1 | C103: =SUM(C87:C99) -> 49680 | D103: =SUM(D102,D98,D94,D90) -> 12420 | F103: =SUM(F102,F98,F94,F90) -> 12105 | H103: =D103-F103 -> 315 | I103: =SUM(I102,I98,I94,I90) -> 0
A104: 2.2 | B104: Trainings on Alternate Livelihood Options: Poultry & Goat Rearing
A105: 2.2.1 | B105: Honorarium , travelling & food for resource person @Rs.2500 | C105: 5000
B108: Total 2.2.1 | D108: 0 | F108: =SUM(F106:F107) -> 0 | H108: =D108-F108 -> 0 | I108: =SUM(I106:I107) -> 0
A109: 2.2.2 | B109: Food for 35 participants form 7 project located villages each village 5 participants &6 staff @ Rs.120 x 41 Person =Rs.3360 | C109: 9840
B112: Total 2.2.2 | D112: 0 | F112: =SUM(F110:F111) -> 0 | H112: =D112-F112 -> 0 | I112: =SUM(I110:I111) -> 0
A113: 2.2.3 | B113: Project village to training venue transportation charges @Rs.2500/- 2 vehicles | C113: 10000
B116: Total 2.2.3 | D116: 0 | F116: =SUM(F114:F115) -> 0 | H116: =D116-F116 -> 0 | I116: =SUM(I114:I115) -> 0
A117: 2.2.4 | B117: Arrangements & training materials @ Rs.500/- | C117: 1000
B120: Total 2.2.4 | D120: 0 | F120: =SUM(F118:F119) -> 0 | H120: =D120-F120 -> 0 | I120: =SUM(I118:I119) -> 0
B121: Activities Sub Total 2.2 | C121: =SUM(C105:C117) -> 25840 | D121: =SUM(D120,D116,D112,D108) -> 0 | F121: =SUM(F120,F116,F112,F108) -> 0 | H121: =D121-F121 -> 0 | I121: =SUM(I120,I116,I112,I108) -> 0
A122: 2.3 | B122: Training on primary treatments and Vaccination for the domestic animals
...

Sheet  Qtr-4 Jan-25 to march-25
B1: Partner: DAPTA (Development Agency for Poor and Tribal Awakening)
A2: Quarterly/Monthly Reporting Format
A3: Ensuring food and livelihood security of indigenous and other marginalized communities in Thakurmunda Block, Mayurbhanj, Odisha
D4: Accounting Period: | E4: Start: 1 Jan. 2025
E5: End: 30 March 2025
A6: Date: Grant received on | D6: 0 | E6: Total Annual MCC Budget: | H6: =+' Qtr-1 April-24 to June-24 '!H6:I6 -> Rs. 26,75,000/-
A7: Opening Balalnce : on 1 Jan. 2025 Cash in Hand | D7: 0
A8: Bank interest | D8: 0
A9: Total Balance available on 1. Jan 2025 | D9: =D7+D8 -> 0
A10: Grant Received from MCC for Qtr-2 2024-25: | E10: NOTE: Please add more rows if needed but make sure that the value is added to the fomula
A11: Total Balance available | D11: =SUM(D8:D10) -> 0
A12: Budget ID | B12: Vendor/Expense Description | C12: MCC Approved budget-Yr-1 | D12: Quarterly Budgeted Amount Qtr-4 2025 | E12: Date | F12: Expense Amt | G12: Voucher or receipt number | H12: Budgeted Amt less Expense Amount | I12: Partner / Farmer Contribution
A13: 1 | B13: Outcome :1 Activities
A14: 1.1 | B14: Baseline | C14: 0
B16: Total 1.1 | D16: 0 | F16: =SUM(F15:F15) -> 0 | H16: =D16-F16 -> 0
A17: 1.2 | B17: Monthly PRA/ Data collection/ Village Community Meeting
A18: 1.2.1 | B18: Monthly Village Community Meeting (Biscuits / Snacks /per time /12 Months) @Rs.15 x 437 + 6 staff =Rs.6660/- | C18: 79920
B21: Total 1.2.1 | D21: 19980 | F21: =SUM(F19:F20) -> 0 | H21: =D21-F21 -> 19980
B22: Activities Sub Total 1.2 | C22: =SUM(C14,C18) -> 79920 | D22: =D21+D16 -> 19980 | F22: =SUM(F21) -> 0 | H22: =D22-F22 -> 19980 | I22: =SUM(I14,I18) -> 0
A23: 1.3 | B23: Training on Improved agriculture methods and Technology :- a) SRI (Paddy farming in row) b) Multi cropping c) Crop diversification d) Crop rotation e) Azola growing f) Seed preservation g) Seed treatment
A24: 1.3.1 | B24: Honorarium , travelling & food for resource person @Rs.2000 (above mentioned some subject will be conducted by the Project staff) | C24: 2000
B28: Total 1.3.1 | D28: 2000 | F28: =SUM(F25:F27) -> 0 | H28: =D28-F28 -> 2000
A29: 1.3.2 | B29: Food for 20 participants & 6 staff @ Rs.120 x 26 Person | C29: 12480
B33: Total 1.3.2 | D33: 3120 | F33: =SUM(F30:F32) -> 0 | H33: =D33-F33 -> 3120
A34: 1.3.3 | B34: Project village to training venue Transportation charges 20 participants x 1 Project villages @ Rs.2500/-; 2 vehicles | C34: 20000
B37: Total 1.3.3 | D37: 5000 | F37: =SUM(F35:F36) -> 0 | H37: =D37-F37 -> 5000
A38: 1.3.4 | B38: Arrangements & training matterials @ Rs.500/- | C38: 2000
B41: Total 1.3.4 | D41: 500 | F41: =SUM(F39:F40) -> 0 | H41: =D41-F41 -> 500
B42: Activities Sub Total 1.3 | C42: =SUM(C24:C38) -> 36480 | D42: =SUM(D41,D37,D33,D28) -> 10620 | F42: =SUM(F41,F37,F33,F28) -> 0 | H42: =D42-F42 -> 10620
A43: 1.4 | B43: Training on Natural Resource Management a) Soil health ( Testing, treatment and preservation) b) Organic farming (Chemical free) c) Compost pit & its preparation d) Vermin compost making e) Bio- Pesticide f) Bio- fertilizer
A44: 1.4.1 | B44: Honorarium, travelling & food for resource person @Rs.2000 | C44: 8000
B46: Total 1.4.1 | D46: 2000 | F46: =F45 -> 0 | H46: =D46-F46 -> 2000
A47: 1.4.2 | B47: Food for 35 participants form 7 project located villages each village 5 participants & 6 staff @ Rs.120 x 41 Person =Rs.3360 | C47: 19680
B50: Total 1.4.2 | D50: 4920 | F50: =SUM(F48:F49) -> 0 | H50: =D50-F50 -> 4920
A51: 1.4.3 | B51: Project village to training venue transportation charges Rs.7500/- each village 5 participants x 7 Project villges 3 vehicles for 2 trainings | C51: 30000
B54: Total 1.4.3 | D54: 7500 | F54: =SUM(F52:F53) -> 0 | H54: =D54-F54 -> 7500
A55: 1.4.4 | B55: Arrangements & training matterials @ Rs.500/- | C55: 2000
B58: Total 1.4.4 | D58: 500 | F58: =SUM(F56:F57) -> 0 | H58: =D58-F58 -> 500
B59: Activities Sub Total 1.4 | C59: =SUM(C44:C55) -> 59680 | D59: =SUM(D58,D54,D50,D46) -> 14920 | F59: =SUM(F58,F54,F50,F46) -> 0 | H59: =D59-F59 -> 14920
A60: 1.5 | B60: Pulses Seeds (Horse gram & Black gram) distribution
A61: 1.5.1 | B61: Pulses Seeds Distribution for 437 families Black Gram 1kg, Kulthi 1kg @Rs.212.86/- for 2 Kg x 437 families (Contribution Local labor charges@500 x 437 families) | C61: 157320
B63: Total 1.5.1 | F63: =SUM(F62:F62) -> 0 | H63: =D63-F63 -> 0
B64: Activities Sub Total 1.5 | C64: =C61 -> 157320 | D64: =D63 -> 0 | F64: =F63 -> 0 | H64: =D64-F64 -> 0
A65: 1.6 | B65: Exposure visit on adaption of improved new technology
A66: 1.6.1 | B66: Honorarium for resource person @Rs.2000
B68: Total 1.6.1 | F68: =SUM(F67:F67) -> 0 | H68: =D68-F68 -> 0
A69: 1.6.2 | B69: Food for 35 participants & 6 staff @ Rs.200 x 41 Person x 1 day = 8400/-
B71: Total 1.6.2 | F71: =SUM(F70:F70) -> 0 | H71: =D71-F71 -> 0
A72: 1.6.3 | B72: Bus charges @ Rs.25000/- in Year -1 @ Rs. 26000/- x 2 bus in Year-2 and for Long distance place Exposure Visit in Yr-3 Bus Charges @Rs.35000/-
B75: Total 1.6.3 | F75: =SUM(F73:F74) -> 0 | H75: =D75-F75 -> 0
A76: 1.6.4 | B76: First Aid medicine & other expenses @ Rs.500/- and Rs.1000/-
B79: Total 1.6.4 | F79: =SUM(F77:F78) -> 0 | H79: =D79-F79 -> 0
B80: Activities Sub Total 1.6 | C80: =SUM(C66:C76) -> 0 | D80: 0 | F80: =F79+F75+F71+F68 -> 0 | H80: =D80-F80 -> 0
B81: Activities Sub Total for Outcomes :1 | C81: =SUM(C80,C64,C59,C42,C22) -> 333400 | D81: =SUM(D80,D64,D59,D42,D22) -> 45520 | F81: =SUM(F80,F64,F59,F42,F22,F16) -> 0 | H81: =D81-F81 -> 45520
B82: Activities for Outcome :2
A83: 2.1 | B83: Training to the CBO’s (SHG) on topics a) Account book keeping, b) Record maintaining, c) Rules and Regulations, d) Responsibilities of the group leaders and members. e) Training on loan taking and refunding. f) Sack bag potatoes farming g) tuber crop farming i) Encourage to farming of Millet ( Mandia)
A84: 2.1.1 | B84: Honorarium , Travelling & food for Resource person @Rs.2000 | C84: 8000
B87: Total 2.1.1 | D87: 2000 | F87: =SUM(F85:F86) -> 0 | H87: =D87-F87 -> 2000
A88: 2.1.2 | B88: Food for 35 participants form 7 project located villages each village 5 participants & 6 staff @ Rs.120 x 42 Person =Rs.3360 | C88: 19680
B91: Total 2.1.2 | D91: 4920 | F91: =SUM(F89:F90) -> 0 | H91: =D91-F91 -> 4920
A92: 2.1.3 | B92: Project village to training venue transportation charges Rs.2500/- each village 5 participants x 7 Project villages, 2 vehicles | C92: 20000
B95: Total 2.1.3 | D95: 5000 | F95: =SUM(F93:F94) -> 0 | H95: =D95-F95 -> 5000
A96: 2.1.4 | B96: Arrangements & training materials @ Rs.500/- | C96: 2000
B99: Total 2.1.4 | D99: 500 | F99: =SUM(F97:F98) -> 0 | H99: =D99-F99 -> 500
B100: Activities Sub Total 2.1 | C100: =SUM(C84:C96) -> 49680 | D100: =SUM(D99,D95,D91,D87) -> 12420 | F100: =SUM(F99,F95,F91,F87) -> 0 | H100: =D100-F100 -> 12420
A101: 2.2 | B101: Trainings on Alternate Livelihood Options: Poultry & Goat Rearing
A102: 2.2.1 | B102: Honorarium , travelling & food for resource person @Rs.2500 | C102: 5000
B105: Total 2.2.1 | D105: 0 | F105: =SUM(F103:F104) -> 0 | H105: =D105-F105 -> 0
A106: 2.2.2 | B106: Food for 35 participants form 7 project located villages each village 5 participants &6 staff @ Rs.120 x 41 Person =Rs.3360 | C106: 9840
B109: Total 2.2.2 | D109: 0 | F109: =SUM(F107:F108) -> 0 | H109: =D109-F109 -> 0
A110: 2.2.3 | B110: Project village to training venue transportation charges @Rs.2500/- 2 vehicles | C110: 10000
B113: Total 2.2.3 | D113: 0 | F113: =SUM(F111:F112) -> 0 | H113: =D113-F113 -> 0
A114: 2.2.4 | B114: Arrangements & training materials @ Rs.500/- | C114: 1000
B117: Total 2.2.4 | D117: 0 | F117: =SUM(F115:F116) -> 0 | H117: =D117-F117 -> 0
B118: Activities Sub Total 2.2 | C118: =SUM(C102:C114) -> 25840 | D118: =SUM(D117,D113,D109,D105) -> 0 | F118: =SUM(F117,F113,F109,F105) -> 0 | H118: =D118-F118 -> 0
A119: 2.3 | B119: Training on primary treatments and Vaccination for the domestic animals
A120: 2.3.1 | B120: Honorarium , travelling & food for resource person @Rs.2500 | C120: 5000
B123: Total 2.3.1 | F123: =SUM(F121:F122) -> 0 | H123: =D123-F123 -> 0
A124: 2.3.2 | B124: Food for 21 participants form 7 project located villages each village 3 participants & 6 staff @ Rs.120 x 21 Person =Rs.1680/- | C124: 6480
B127: Total 2.3.2 | F127: =SUM(F125:F126) -> 0 | H127: =D127-F127 -> 0
A128: 2.3.3 | B128: Project village to training venue transportation charges Rs.2500/- each village 2 participants x 7 Project villages 2 vehicles | C128: 10000
B131: Total 2.3.3 | F131: =SUM(F129:F130) -> 0 | H131: =D131-F131 -> 0
A132: 2.3.4 | B132: Arrangements & training matterials @ Rs.500/- | C132: 1000
B136: Total 2.3.4 | F136: =SUM(F133:F135) -> 0 | H136: =D136-F136 -> 0
B137: Activities Sub Total 2.3 | C137: =SUM(C120:C132) -> 22480 | D137: =SUM(D136,D131,D127,D123) -> 0 | F137: =SUM(F136,F131,F127,F123) -> 0 | H137: =D137-F137 -> 0
A138: 2.4 | B138: Need based training on Income Generation activity like fish cultivation
A139: 2.4.1 | B139: Honorarium , travelling & food for resource person @Rs.2500 | C139: 5000
B142: Total 2.4.1 | D142: 2500 | F142: =SUM(F140:F141) -> 0 | H142: =D142-F142 -> 2500
A143: 2.4.2 | B143: Food for 35 participants & 6 staff @ Rs.120 x 41 Person | C143: 9840
B146: Total 2.4.2 | D146: 4920 | F146: =SUM(F144:F145) -> 0 | H146: =D146-F146 -> 4920
A147: 2.4.3 | B147: Project village to training venue transportation charges Rs.2500/- 2 vehicles | C147: 10000
B150: Total 2.4.3 | D150: 5000 | F150: =SUM(F148:F149) -> 0 | H150: =D150-F150 -> 5000
A151: 2.4.4 | B151: Arrangements & training matterials @ Rs.500/- | C151: 1000
B153: Total 2.4.4 | D153: 500 | F153: =SUM(F152:F152) -> 0 | H153: =D153-F153 -> 500
B154: Activities Sub Total 2.4 | C154: =SUM(C139:C151) -> 25840 | D154: =SUM(D153,D150,D146,D142) -> 12920 | F154: =SUM(F153,F150,F146,F142) -> 0 | H154: =D154-F154 -> 12920
A155: 2.5 | B155: Training on Nutritional Kitchen garden and commercial vegetable gardening a) Fruits b) Vegetable
A156: 2.5.1 | B156: Resource person travelling and honorarium charges for Year-1 only and then Project staff will conduct it | C156: 0
B159: Total 2.5.1 | D159: 0 | F159: =SUM(F157:F158) -> 0 | H159: =D159-F159 -> 0
A160: 2.5.2 | B160: Food for 35 participants form 7 project located villages each village 5 participants & 6 staff @ Rs.120 x 41 Person | C160: 14760
B163: Total 2.5.2 | D163: 4920 | F163: =SUM(F161:F162) -> 0 | H163: =D163-F163 -> 4920
...
